Workbook
Name Период_1: #REF!
Name Период_10: #REF!
Name Период_11: #REF!
Name Период_12: #REF!
Name Период_13: #REF!
Name Период_14: #REF!
Name Период_15: #REF!
Name Период_16: #REF!
Name Период_17: #REF!
Name Период_18: #REF!
Name Период_19: #REF!
Name Период_2: #REF!
Name Период_20: #REF!
Name Период_21: #REF!
Name Период_22: #REF!
Name Период_23: #REF!
Name Период_24: #REF!
Name Период_25: #REF!
Name Период_26: #REF!
Name Период_3: #REF!
Name Период_4: #REF!
Name Период_5: #REF!
Name Период_6: #REF!
Name Период_7: #REF!
Name Период_8: #REF!
Name Период_9: #REF!
Name СП_R100C10: #REF!
Name СП_R100C11: #REF!
Name СП_R100C12: #REF!
Name СП_R100C13: #REF!
Name СП_R100C14: #REF!
Name СП_R100C15: #REF!
Name СП_R100C16: #REF!
Name СП_R100C17: #REF!
Name СП_R100C18: #REF!
Name СП_R100C19: #REF!
Name СП_R100C20: #REF!
Name СП_R100C21: #REF!
Name СП_R100C22: #REF!
Name СП_R100C23: #REF!
Name СП_R100C24: #REF!
Name СП_R100C25: #REF!
Name СП_R100C26: #REF!
Name СП_R100C27: #REF!
Name СП_R100C28: #REF!
Name СП_R100C3: #REF!
Name СП_R100C4: #REF!
Name СП_R100C5: #REF!
Name СП_R100C6: #REF!
Name СП_R100C7: #REF!
Name СП_R100C8: #REF!
Name СП_R100C9: #REF!
Name СП_R101C10: #REF!
Name СП_R101C11: #REF!
Name СП_R101C12: #REF!
Name СП_R101C13: #REF!
Name СП_R101C14: #REF!
Name СП_R101C15: #REF!
Name СП_R101C16: #REF!
Name СП_R101C17: #REF!

Sheet МАСТЕР ПЛАН
AA2: Вариант 4 | AE2: FALSE
AA4: 1+2 оч | AB4: 1оч | AC4: 2оч
Z5: жилье | AA5: =AB5+AC5 -> 169659.3 | AB5: 113733.8 | AC5: 55925.5
Z6: нежилье | AA6: =AB6+AC6 -> 8263.1 | AB6: 5160.1 | AC6: 3103
AA7: =AA5+AA6 -> 177922.4 | AB7: =AB5+AB6 -> 118893.9 | AC7: =AC5+AC6 -> 59028.5
Z8: ЗУ | AA8: =AB8+AC8 -> 47620 | AB8: =AC17 -> 29890 | AC8: =AB17 -> 17730
AA11: Вариант 3 | AE11: FALSE
AA13: 1+2 оч | AB13: 1оч | AC13: 2оч
Z14: жилье | AA14: =AB14+AC14 -> 169659.3 | AB14: 55925.5 | AC14: 113733.8
Z15: нежилье | AA15: =AB15+AC15 -> 8263.1 | AB15: 3103 | AC15: 5160.1
AA16: =AA14+AA15 -> 177922.4 | AB16: =AB14+AB15 -> 59028.5 | AC16: =AC14+AC15 -> 118893.9
Z17: ЗУ | AA17: =AB17+AC17 -> 47620 | AB17: 17730 | AC17: =29890 -> 29890
AA19: Вариант 1 | AE19: TRUE
AB20: =AB22/$AA$22 -> 0.53874801 | AC20: =AC22/$AA$22 -> 0.46125199
AA21: 1+2 оч | AB21: 1оч | AC21: 2оч
Z22: жилье | AA22: =AB22+AC22 -> 169435.8 | AB22: 91283.2 | AC22: 78152.6
Z23: нежилье | AA23: =AB23+AC23 -> 8707.4 | AB23: 5042.8 | AC23: 3664.6
AA24: =AA22+AA23 -> 178143.2 | AB24: =AB22+AB23 -> 96326 | AC24: =AC22+AC23 -> 81817.2
Z25: ЗУ | AA25: =AB25+AC25 -> 47620 | AB25: 25440 | AC25: 22180
AA28: Вариант 2 | AE28: FALSE
AB29: =DB!B107 -> 0.5 | AC29: =1-AB29 -> 0.5
AA30: 1+2 оч | AB30: 1оч | AC30: 2оч
Z31: жилье | AA31: 169659.3 | AB31: =$AA$31*AB29 -> 84829.65 | AC31: =$AA$31*AC29 -> 84829.65
Z32: нежилье | AA32: 8263.1 | AB32: =$AA$32*AB29 -> 4131.55 | AC32: =$AA$32*AC29 -> 4131.55
AA33: 177922.4 | AB33: =AB31+AB32 -> 88961.2 | AC33: =AC31+AC32 -> 88961.2
Z34: ЗУ | AA34: =AB34+AC34 -> 47620 | AB34: =29890 -> 29890 | AC34: 17730
AA41: ПРИБЫЛЬ | AB41: =DB!U38 -> 9345.5509 | AC41: 9215.744 | AD41: =AB41-AC41 -> 129.80687
AA42: PV | AB42: =DB!U44 -> 1866.4393 | AC42: 1883.7835 | AD42: =AB42-AC42 -> -17.344287
AA43: LLSR | AB43: =DB!U43 -> 1.1966655 | AC43: 1.1946846 | AD43: =AB43-AC43 -> 0.0019809278
AA44: IRR ПРОЕКТА (pre-tax) | AB44: =DB!U41 -> 0.1755044 | AC44: 0.17660578 | AD44: =AB44-AC44 -> -0.0011013809
G55: Вопросы:
F57: 1 | G57: СОШ - сроки
F58: 2 | G58: м/м - кол-во в подземной части? Площадь подземки на 1 м/м
F59: 3 | G59: средняя площадь квартиры

Sheet RESUME
B2: Резюме изменений проекта (вкладка RESUME)
B3: Название проекта: | E3: =DB!C2 -> КАСАТКИНА | J3: =OFFSET($Q3,,MATCH(J$5,$R$5:$W$5,0)) -> 📌 | K3: =OFFSET($Q3,,MATCH(K$5,$R$5:$W$5,0)) -> 📌 | L3: =OFFSET($Q3,,MATCH(L$5,$R$5:$W$5,0)) -> 📌 | R3: 📌 | S3: 📌 | T3: 📌 | U3: 📌 | V3: 📌 | W3: 📌
H4: =K4 -> 1 оч | I4: =L4 -> 2 оч | J4: =OFFSET($Q4,,MATCH(J$5,$R$5:$W$5,0)) -> ТЭПы 50 / 50 | K4: =OFFSET($Q4,,MATCH(K$5,$R$5:$W$5,0)) -> 1 оч | L4: =OFFSET($Q4,,MATCH(L$5,$R$5:$W$5,0)) -> 2 оч | M4: =CONCATENATE(K4," vs ",L4) -> 1 оч vs 2 оч | N4: Текущая ФМ <2Q2025 | R4: ТЭПы 50 / 50 | S4: 1 оч | T4: 2 оч | V4: 1 оч | W4: 2 оч
B5: ПОКАЗАТЕЛИ | F5: млн.руб. | H5: =K5 -> 45779 | I5: =L5 -> 45780 | J5: 45778 | K5: 45779 | L5: 45780 | M5: +/- | N5: FACT | O5: PLAN | P5: Комм. | R5: 45778 | S5: =R5+1 -> 45779 | T5: =R5+2 -> 45780 | U5: 45809 | V5: 45810 | W5: 45811
B6: ПЛОЩАДЬ ЗУ | H6: кв.м. | J6: =SUMIFS($R6:$W6,$R$5:$W$5,$J$5) -> 47620 | K6: =SUMIFS($R6:$W6,$R$5:$W$5,$K$5) -> 25440 | L6: =SUMIFS($R6:$W6,$R$5:$W$5,$L$5) -> 22180 | M6: =L6-K6 -> -3260 | P6: =LEFT(Y6,4) | R6: =DB!P51 -> 47620 | S6: ='DB1'!P51 -> 25440 | T6: ='DB2'!P51 -> 22180
B7: ПЛОТНОСТЬ | F7: 40000 | G7: (м2/Га) | H7: кв.м. | J7: =SUMIFS($R7:$W7,$R$5:$W$5,$J$5) -> 35000 | K7: =SUMIFS($R7:$W7,$R$5:$W$5,$K$5) -> 35000 | L7: =SUMIFS($R7:$W7,$R$5:$W$5,$L$5) -> 35000 | M7: =L7-K7 -> 0 | P7: =LEFT(Y7,4) | R7: =DB!P2 -> 35000 | S7: ='DB1'!P2 -> 35000 | T7: ='DB2'!P2 -> 35000
B8: ГНС бум. | H8: кв.м. | J8: =SUMIFS($R8:$W8,$R$5:$W$5,$J$5) -> 178143.2 | K8: =SUMIFS($R8:$W8,$R$5:$W$5,$K$5) -> 96326 | L8: =SUMIFS($R8:$W8,$R$5:$W$5,$L$5) -> 81817.2 | M8: =L8-K8 -> -14508.8 | P8: =LEFT(Y8,4) | R8: =DB!F7 -> 178143.2 | S8: ='DB1'!F7 -> 96326 | T8: ='DB2'!F7 -> 81817.2
B9: ГНС | H9: кв.м. | J9: =SUMIFS($R9:$W9,$R$5:$W$5,$J$5) -> 178143.2 | K9: =SUMIFS($R9:$W9,$R$5:$W$5,$K$5) -> 96326 | L9: =SUMIFS($R9:$W9,$R$5:$W$5,$L$5) -> 81817.2 | M9: =L9-K9 -> -14508.8 | P9: =LEFT(Y9,4) | R9: =DB!F7 -> 178143.2 | S9: ='DB1'!F7 -> 96326 | T9: ='DB2'!F7 -> 81817.2
B10: =DB!D8 -> 0.95112135 | C10: квартиры | H10: кв.м. | J10: =SUMIFS($R10:$W10,$R$5:$W$5,$J$5) -> 169435.8 | K10: =SUMIFS($R10:$W10,$R$5:$W$5,$K$5) -> 91283.2 | L10: =SUMIFS($R10:$W10,$R$5:$W$5,$L$5) -> 78152.6 | M10: =L10-K10 -> -13130.6 | P10: =LEFT(Y10,4) | R10: =DB!F8 -> 169435.8 | S10: ='DB1'!F8 -> 91283.2 | T10: ='DB2'!F8 -> 78152.6
C11: офисы | H11: кв.м. | J11: =SUMIFS($R11:$W11,$R$5:$W$5,$J$5) -> 0 | K11: =SUMIFS($R11:$W11,$R$5:$W$5,$K$5) -> 0 | L11: =SUMIFS($R11:$W11,$R$5:$W$5,$L$5) -> 0 | M11: =L11-K11 -> 0 | P11: =LEFT(Y11,4)
B12: ='DB1'!D11 -> 0.05235139 | C12: стритритейл | H12: кв.м. | J12: =SUMIFS($R12:$W12,$R$5:$W$5,$J$5) -> 8707.4 | K12: =SUMIFS($R12:$W12,$R$5:$W$5,$K$5) -> 5042.8 | L12: =SUMIFS($R12:$W12,$R$5:$W$5,$L$5) -> 3664.6 | M12: =L12-K12 -> -1378.2 | P12: =LEFT(Y12,4) | R12: =DB!F11 -> 8707.4 | S12: ='DB1'!F11 -> 5042.8 | T12: ='DB2'!F11 -> 3664.6
C13: ДОУ | H13: кв.м. | J13: =SUMIFS($R13:$W13,$R$5:$W$5,$J$5) -> 0 | K13: =SUMIFS($R13:$W13,$R$5:$W$5,$K$5) -> 0 | L13: =SUMIFS($R13:$W13,$R$5:$W$5,$L$5) -> 0 | M13: =L13-K13 -> 0 | P13: =LEFT(Y13,4)
B14: ОБЩАЯ ПЛОЩАДЬ ОБЪЕКТА по стандарту СП (РНС и экспертиза) | H14: кв.м. | J14: =SUMIFS($R14:$W14,$R$5:$W$5,$J$5) -> 0 | K14: =SUMIFS($R14:$W14,$R$5:$W$5,$K$5) -> 0 | L14: =SUMIFS($R14:$W14,$R$5:$W$5,$L$5) -> 0 | M14: =L14-K14 -> 0 | P14: =LEFT(Y14,4) | R14: =R15+R16 -> 0 | S14: =S15+S16 -> 0 | T14: =T15+T16 -> 0
B15: наземная часть | F15: 0.0535 | G15: (стены) | H15: кв.м. | J15: =SUMIFS($R15:$W15,$R$5:$W$5,$J$5) -> 0 | K15: =SUMIFS($R15:$W15,$R$5:$W$5,$K$5) -> 0 | L15: =SUMIFS($R15:$W15,$R$5:$W$5,$L$5) -> 0 | M15: =L15-K15 -> 0 | P15: =LEFT(Y15,4)
B16: подземная часть | H16: кв.м. | J16: =SUMIFS($R16:$W16,$R$5:$W$5,$J$5) -> 0 | K16: =SUMIFS($R16:$W16,$R$5:$W$5,$K$5) -> 0 | L16: =SUMIFS($R16:$W16,$R$5:$W$5,$L$5) -> 0 | M16: =L16-K16 -> 0 | P16: =LEFT(Y16,4)
B17: ОБЩАЯ ПЛОЩАДЬ ОБЪЕКТА по станд. МРГ | F17: =DB!G5 -> 0.07 | G17: (стены) | H17: кв.м. | J17: =SUMIFS($R17:$W17,$R$5:$W$5,$J$5) -> 210153.18 | K17: =SUMIFS($R17:$W17,$R$5:$W$5,$K$5) -> 113543.18 | L17: =SUMIFS($R17:$W17,$R$5:$W$5,$L$5) -> 96609.996 | M17: =L17-K17 -> -16933.184 | P17: =LEFT(Y17,4) | R17: =R18+R23 -> 210153.18 | S17: =S18+S23 -> 113543.18 | T17: =T18+T23 -> 96609.996
B18: наземная часть | H18: кв.м. | J18: =SUMIFS($R18:$W18,$R$5:$W$5,$J$5) -> 165673.18 | K18: =SUMIFS($R18:$W18,$R$5:$W$5,$K$5) -> 89583.18 | L18: =SUMIFS($R18:$W18,$R$5:$W$5,$L$5) -> 76089.996 | M18: =L18-K18 -> -13493.184 | P18: =LEFT(Y18,4) | R18: =SUM(R19:R22) -> 165673.18 | S18: =SUM(S19:S22) -> 89583.18 | T18: =SUM(T19:T22) -> 76089.996
C19: квартиры | H19: кв.м. | J19: =SUMIFS($R19:$W19,$R$5:$W$5,$J$5) -> 157575.29 | K19: =SUMIFS($R19:$W19,$R$5:$W$5,$K$5) -> 84893.376 | L19: =SUMIFS($R19:$W19,$R$5:$W$5,$L$5) -> 72681.918 | M19: =L19-K19 -> -12211.458 | P19: =LEFT(Y19,4) | R19: =DB!G8 -> 157575.29 | S19: ='DB1'!G8 -> 84893.376 | T19: ='DB2'!G8 -> 72681.918
C20: офисы | H20: кв.м. | J20: =SUMIFS($R20:$W20,$R$5:$W$5,$J$5) -> 0 | K20: =SUMIFS($R20:$W20,$R$5:$W$5,$K$5) -> 0 | L20: =SUMIFS($R20:$W20,$R$5:$W$5,$L$5) -> 0 | M20: =L20-K20 -> 0 | P20: =LEFT(Y20,4)
C21: стритритейл | H21: кв.м. | J21: =SUMIFS($R21:$W21,$R$5:$W$5,$J$5) -> 8097.882 | K21: =SUMIFS($R21:$W21,$R$5:$W$5,$K$5) -> 4689.804 | L21: =SUMIFS($R21:$W21,$R$5:$W$5,$L$5) -> 3408.078 | M21: =L21-K21 -> -1281.726 | P21: =LEFT(Y21,4) | R21: =DB!G11 -> 8097.882 | S21: ='DB1'!G11 -> 4689.804 | T21: ='DB2'!G11 -> 3408.078
C22: ДОУ | H22: кв.м. | J22: =SUMIFS($R22:$W22,$R$5:$W$5,$J$5) -> 0 | K22: =SUMIFS($R22:$W22,$R$5:$W$5,$K$5) -> 0 | L22: =SUMIFS($R22:$W22,$R$5:$W$5,$L$5) -> 0 | M22: =L22-K22 -> 0 | P22: =LEFT(Y22,4)
B23: подземная часть | H23: кв.м. | J23: =SUMIFS($R23:$W23,$R$5:$W$5,$J$5) -> 44480 | K23: =SUMIFS($R23:$W23,$R$5:$W$5,$K$5) -> 23960 | L23: =SUMIFS($R23:$W23,$R$5:$W$5,$L$5) -> 20520 | M23: =L23-K23 -> -3440 | P23: =LEFT(Y23,4) | R23: =SUM(R24:R25) -> 44480 | S23: =SUM(S24:S25) -> 23960 | T23: =SUM(T24:T25) -> 20520
C24: парковка | F24: =DB!D16 -> 40 | G24: м2/м-м | H24: кв.м. | J24: =SUMIFS($R24:$W24,$R$5:$W$5,$J$5) -> 44480 | K24: =SUMIFS($R24:$W24,$R$5:$W$5,$K$5) -> 23960 | L24: =SUMIFS($R24:$W24,$R$5:$W$5,$L$5) -> 20520 | M24: =L24-K24 -> -3440 | P24: =LEFT(Y24,4) | R24: =DB!G16 -> 44480 | S24: ='DB1'!G16 -> 23960 | T24: ='DB2'!G16 -> 20520
C25: кладовки | H25: кв.м. | J25: =SUMIFS($R25:$W25,$R$5:$W$5,$J$5) -> 0 | K25: =SUMIFS($R25:$W25,$R$5:$W$5,$K$5) -> 0 | L25: =SUMIFS($R25:$W25,$R$5:$W$5,$L$5) -> 0 | M25: =L25-K25 -> 0 | P25: =LEFT(Y25,4)
B26: ПОЛЕЗНАЯ ПЛОЩАДЬ ОБЪЕКТА | H26: кв.м. | J26: =SUMIFS($R26:$W26,$R$5:$W$5,$J$5) -> 116376.12 | K26: =SUMIFS($R26:$W26,$R$5:$W$5,$K$5) -> 62942.716 | L26: =SUMIFS($R26:$W26,$R$5:$W$5,$L$5) -> 53433.401 | M26: =L26-K26 -> -9509.3151 | P26: =LEFT(Y26,4) | R26: =SUM(R27,R35) -> 116376.12 | S26: =SUM(S27,S35) -> 62942.716 | T26: =SUM(T27,T35) -> 53433.401
B27: наземная часть | H27: кв.м. | J27: =SUMIFS($R27:$W27,$R$5:$W$5,$J$5) -> 116376.12 | K27: =SUMIFS($R27:$W27,$R$5:$W$5,$K$5) -> 62942.716 | L27: =SUMIFS($R27:$W27,$R$5:$W$5,$L$5) -> 53433.401 | M27: =L27-K27 -> -9509.3151 | P27: =LEFT(Y27,4) | R27: =SUM(R28,R32,R33,R34) -> 116376.12 | S27: =SUM(S28,S32,S33,S34) -> 62942.716 | T27: =SUM(T28,T32,T33,T34) -> 53433.401
C28: квартиры | H28: кв.м. | J28: =SUMIFS($R28:$W28,$R$5:$W$5,$J$5) -> 110302.71 | K28: =SUMIFS($R28:$W28,$R$5:$W$5,$K$5) -> 59425.363 | L28: =SUMIFS($R28:$W28,$R$5:$W$5,$L$5) -> 50877.343 | M28: =L28-K28 -> -8548.0206 | P28: =LEFT(Y28,4) | R28: =SUM(R29:R31) -> 110302.71 | S28: =SUM(S29:S31) -> 59425.363 | T28: =SUM(T29:T31) -> 50877.343
D29: MR Base | H29: кв.м. | J29: =SUMIFS($R29:$W29,$R$5:$W$5,$J$5) -> 110302.71 | K29: =SUMIFS($R29:$W29,$R$5:$W$5,$K$5) -> 59425.363 | L29: =SUMIFS($R29:$W29,$R$5:$W$5,$L$5) -> 50877.343 | M29: =L29-K29 -> -8548.0206 | P29: =LEFT(Y29,4) | R29: =DB!H8 -> 110302.71 | S29: ='DB1'!H8 -> 59425.363 | T29: ='DB2'!H8 -> 50877.343
D30: MR Ready | H30: кв.м. | J30: =SUMIFS($R30:$W30,$R$5:$W$5,$J$5) -> 0 | K30: =SUMIFS($R30:$W30,$R$5:$W$5,$K$5) -> 0 | L30: =SUMIFS($R30:$W30,$R$5:$W$5,$L$5) -> 0 | M30: =L30-K30 -> 0 | P30: =LEFT(Y30,4)
D31: без отделки | H31: кв.м. | J31: =SUMIFS($R31:$W31,$R$5:$W$5,$J$5) -> 0 | K31: =SUMIFS($R31:$W31,$R$5:$W$5,$K$5) -> 0 | L31: =SUMIFS($R31:$W31,$R$5:$W$5,$L$5) -> 0 | M31: =L31-K31 -> 0 | P31: =LEFT(Y31,4)
C32: офисы | H32: кв.м. | J32: =SUMIFS($R32:$W32,$R$5:$W$5,$J$5) -> 0 | K32: =SUMIFS($R32:$W32,$R$5:$W$5,$K$5) -> 0 | L32: =SUMIFS($R32:$W32,$R$5:$W$5,$L$5) -> 0 | M32: =L32-K32 -> 0 | P32: =LEFT(Y32,4)
C33: стритритейл | H33: кв.м. | J33: =SUMIFS($R33:$W33,$R$5:$W$5,$J$5) -> 6073.4115 | K33: =SUMIFS($R33:$W33,$R$5:$W$5,$K$5) -> 3517.353 | L33: =SUMIFS($R33:$W33,$R$5:$W$5,$L$5) -> 2556.0585 | M33: =L33-K33 -> -961.2945 | P33: =LEFT(Y33,4) | R33: =DB!H11 -> 6073.4115 | S33: ='DB1'!H11 -> 3517.353 | T33: ='DB2'!H11 -> 2556.0585
C34: ДОУ | H34: кв.м. | J34: =SUMIFS($R34:$W34,$R$5:$W$5,$J$5) -> 0 | K34: =SUMIFS($R34:$W34,$R$5:$W$5,$K$5) -> 0 | L34: =SUMIFS($R34:$W34,$R$5:$W$5,$L$5) -> 0 | M34: =L34-K34 -> 0 | P34: =LEFT(Y34,4)
B35: подземная часть | H35: кв.м. | J35: =SUMIFS($R35:$W35,$R$5:$W$5,$J$5) -> 0 | K35: =SUMIFS($R35:$W35,$R$5:$W$5,$K$5) -> 0 | L35: =SUMIFS($R35:$W35,$R$5:$W$5,$L$5) -> 0 | M35: =L35-K35 -> 0 | P35: =LEFT(Y35,4) | R35: =SUM(R36) -> 0 | S35: =SUM(S36) -> 0 | T35: =SUM(T36) -> 0
C36: кладовки | H36: кв.м. | J36: =SUMIFS($R36:$W36,$R$5:$W$5,$J$5) -> 0 | K36: =SUMIFS($R36:$W36,$R$5:$W$5,$K$5) -> 0 | L36: =SUMIFS($R36:$W36,$R$5:$W$5,$L$5) -> 0 | M36: =L36-K36 -> 0 | P36: =LEFT(Y36,4)
B37: LOSS-FACTOR по стандарту МР Групп | H37: % | J37: =SUMIFS($R37:$W37,$R$5:$W$5,$J$5) -> 0.29755607 | K37: =SUMIFS($R37:$W37,$R$5:$W$5,$K$5) -> 0.29738243 | L37: =SUMIFS($R37:$W37,$R$5:$W$5,$L$5) -> 0.2977605 | M37: =L37-K37 -> 0.00037806485 | P37: =LEFT(Y37,4) | R37: =DB!I18 -> 0.29755607 | S37: ='DB1'!I18 -> 0.29738243 | T37: ='DB2'!I18 -> 0.2977605
B38: квартиры | H38: % | J38: =SUMIFS($R38:$W38,$R$5:$W$5,$J$5) -> 0.3 | K38: =SUMIFS($R38:$W38,$R$5:$W$5,$K$5) -> 0.3 | L38: =SUMIFS($R38:$W38,$R$5:$W$5,$L$5) -> 0.3 | M38: =L38-K38 -> 0 | P38: =LEFT(Y38,4) | R38: =DB!I8 -> 0.3 | S38: ='DB1'!I8 -> 0.3 | T38: ='DB2'!I8 -> 0.3
B39: офисы | H39: % | J39: =SUMIFS($R39:$W39,$R$5:$W$5,$J$5) -> 0 | K39: =SUMIFS($R39:$W39,$R$5:$W$5,$K$5) -> 0 | L39: =SUMIFS($R39:$W39,$R$5:$W$5,$L$5) -> 0 | M39: =L39-K39 -> 0 | P39: =LEFT(Y39,4)
B40: стритритейл | H40: % | J40: =SUMIFS($R40:$W40,$R$5:$W$5,$J$5) -> 0.25 | K40: =SUMIFS($R40:$W40,$R$5:$W$5,$K$5) -> 0.25 | L40: =SUMIFS($R40:$W40,$R$5:$W$5,$L$5) -> 0.25 | M40: =L40-K40 -> 0 | P40: =LEFT(Y40,4) | R40: =DB!I11 -> 0.25 | S40: ='DB1'!I11 -> 0.25 | T40: ='DB2'!I11 -> 0.25
B41: КОЛИЧЕСТВО ЭЛЕМЕНТОВ ОБЪЕКТА | H41: шт. | J41: =SUMIFS($R41:$W41,$R$5:$W$5,$J$5) -> 3254 | K41: =SUMIFS($R41:$W41,$R$5:$W$5,$K$5) -> 1755 | L41: =SUMIFS($R41:$W41,$R$5:$W$5,$L$5) -> 1499 | M41: =L41-K41 -> -256 | P41: =LEFT(Y41,4) | R41: =SUM(R42,R46) -> 3254 | S41: =SUM(S42,S46) -> 1755 | T41: =SUM(T42,T46) -> 1499
B42: наземная часть | H42: шт. | J42: =SUMIFS($R42:$W42,$R$5:$W$5,$J$5) -> 2142 | K42: =SUMIFS($R42:$W42,$R$5:$W$5,$K$5) -> 1156 | L42: =SUMIFS($R42:$W42,$R$5:$W$5,$L$5) -> 986 | M42: =L42-K42 -> -170 | P42: =LEFT(Y42,4) | R42: =SUM(R43:R45) -> 2142 | S42: =SUM(S43:S45) -> 1156 | T42: =SUM(T43:T45) -> 986
C43: квартиры | F43: =DB!E8 -> 53 | G43: м2/лот | H43: шт. | J43: =SUMIFS($R43:$W43,$R$5:$W$5,$J$5) -> 2081 | K43: =SUMIFS($R43:$W43,$R$5:$W$5,$K$5) -> 1121 | L43: =SUMIFS($R43:$W43,$R$5:$W$5,$L$5) -> 960 | M43: =L43-K43 -> -161 | P43: =LEFT(Y43,4) | R43: =DB!J8 -> 2081 | S43: ='DB1'!J8 -> 1121 | T43: ='DB2'!J8 -> 960
C44: офисы | G44: м2/лот | H44: шт. | J44: =SUMIFS($R44:$W44,$R$5:$W$5,$J$5) -> 0 | K44: =SUMIFS($R44:$W44,$R$5:$W$5,$K$5) -> 0 | L44: =SUMIFS($R44:$W44,$R$5:$W$5,$L$5) -> 0 | M44: =L44-K44 -> 0 | P44: =LEFT(Y44,4)
C45: стритритейл | F45: ='DB1'!E11 -> 100 | G45: м2/лот | H45: шт. | J45: =SUMIFS($R45:$W45,$R$5:$W$5,$J$5) -> 61 | K45: =SUMIFS($R45:$W45,$R$5:$W$5,$K$5) -> 35 | L45: =SUMIFS($R45:$W45,$R$5:$W$5,$L$5) -> 26 | M45: =L45-K45 -> -9 | P45: =LEFT(Y45,4) | R45: =DB!J11 -> 61 | S45: ='DB1'!J11 -> 35 | T45: ='DB2'!J11 -> 26
B46: подземная часть | H46: шт. | J46: =SUMIFS($R46:$W46,$R$5:$W$5,$J$5) -> 1112 | K46: =SUMIFS($R46:$W46,$R$5:$W$5,$K$5) -> 599 | L46: =SUMIFS($R46:$W46,$R$5:$W$5,$L$5) -> 513 | M46: =L46-K46 -> -86 | P46: =LEFT(Y46,4) | R46: =SUM(R47:R48) -> 1112 | S46: =SUM(S47:S48) -> 599 | T46: =SUM(T47:T48) -> 513
C47: парковка | H47: шт. | J47: =SUMIFS($R47:$W47,$R$5:$W$5,$J$5) -> 1112 | K47: =SUMIFS($R47:$W47,$R$5:$W$5,$K$5) -> 599 | L47: =SUMIFS($R47:$W47,$R$5:$W$5,$L$5) -> 513 | M47: =L47-K47 -> -86 | P47: =LEFT(Y47,4) | R47: =DB!J16 -> 1112 | S47: ='DB1'!J16 -> 599 | T47: ='DB2'!J16 -> 513
C48: кладовки | H48: шт. | J48: =SUMIFS($R48:$W48,$R$5:$W$5,$J$5) -> 0 | K48: =SUMIFS($R48:$W48,$R$5:$W$5,$K$5) -> 0 | L48: =SUMIFS($R48:$W48,$R$5:$W$5,$L$5) -> 0 | M48: =L48-K48 -> 0 | P48: =LEFT(Y48,4)
B49: ОБЕСПЕЧЕННОСТЬ М/М | H49: % | J49: =SUMIFS($R49:$W49,$R$5:$W$5,$J$5) -> 0.53435848 | K49: =SUMIFS($R49:$W49,$R$5:$W$5,$K$5) -> 0.53434434 | L49: =SUMIFS($R49:$W49,$R$5:$W$5,$L$5) -> 0.534375 | M49: =L49-K49 -> 3.0664585e-05 | P49: =LEFT(Y49,4) | R49: =DB!C16 -> 0.53435848 | S49: ='DB1'!C16 -> 0.53434434 | T49: ='DB2'!C16 -> 0.534375
B50: СРЕДНЯЯ ЦЕНА РЕАЛИЗАЦИИ | J50: =SUMIFS($R50:$W50,$R$5:$W$5,$J$5) -> 0 | K50: =SUMIFS($R50:$W50,$R$5:$W$5,$K$5) -> 0 | L50: =SUMIFS($R50:$W50,$R$5:$W$5,$L$5) -> 0 | P50: =LEFT(Y50,4)
B51: наземная часть | F51: старт | G51: финиш | J51: =SUMIFS($R51:$W51,$R$5:$W$5,$J$5) -> 0 | K51: =SUMIFS($R51:$W51,$R$5:$W$5,$K$5) -> 0 | L51: =SUMIFS($R51:$W51,$R$5:$W$5,$L$5) -> 0 | M51: =L51-K51 -> 0 | P51: =LEFT(Y51,4) | S51: 0
C52: квартиры | F52: =DB!P8 -> 522.9 | G52: =DB!Q8 -> 710.55666 | H52: т.р/кв.м | J52: =SUMIFS($R52:$W52,$R$5:$W$5,$J$5) -> 630 | K52: =SUMIFS($R52:$W52,$R$5:$W$5,$K$5) -> 630 | L52: =SUMIFS($R52:$W52,$R$5:$W$5,$L$5) -> 630 | M52: =L52-K52 -> 0 | N52: 0 | O52: 0 | P52: =LEFT(Y52,4) | R52: =R53 -> 630 | S52: =S53 -> 630 | T52: =T53 -> 630
D53: MR Base | H53: т.р/кв.м | J53: =SUMIFS($R53:$W53,$R$5:$W$5,$J$5) -> 630 | K53: =SUMIFS($R53:$W53,$R$5:$W$5,$K$5) -> 630 | L53: =SUMIFS($R53:$W53,$R$5:$W$5,$L$5) -> 630 | M53: =L53-K53 -> 0 | N53: 0 | O53: 0 | P53: =LEFT(Y53,4) | R53: =DB!R8 -> 630 | S53: ='CF1'!E17 -> 630 | T53: ='CF2'!E17 -> 630
D54: MR Ready | H54: т.р/кв.м | J54: =SUMIFS($R54:$W54,$R$5:$W$5,$J$5) -> 0 | K54: =SUMIFS($R54:$W54,$R$5:$W$5,$K$5) -> 0 | L54: =SUMIFS($R54:$W54,$R$5:$W$5,$L$5) -> 0 | M54: =L54-K54 -> 0 | N54: 0 | O54: 0 | P54: =LEFT(Y54,4)
D55: без отделки | H55: т.р/кв.м | J55: =SUMIFS($R55:$W55,$R$5:$W$5,$J$5) -> 0 | K55: =SUMIFS($R55:$W55,$R$5:$W$5,$K$5) -> 0 | L55: =SUMIFS($R55:$W55,$R$5:$W$5,$L$5) -> 0 | M55: =L55-K55 -> 0 | N55: 0 | O55: 0 | P55: =LEFT(Y55,4)
C56: офисы | H56: т.р/кв.м | J56: =SUMIFS($R56:$W56,$R$5:$W$5,$J$5) -> 0 | K56: =SUMIFS($R56:$W56,$R$5:$W$5,$K$5) -> 0 | L56: =SUMIFS($R56:$W56,$R$5:$W$5,$L$5) -> 0 | M56: =L56-K56 -> 0 | N56: 0 | O56: 0 | P56: =LEFT(Y56,4)
C57: стритритейл | F57: ='DB1'!P11 -> 700 | G57: ='DB1'!Q11 -> 700 | H57: т.р/кв.м | J57: =SUMIFS($R57:$W57,$R$5:$W$5,$J$5) -> 700 | K57: =SUMIFS($R57:$W57,$R$5:$W$5,$K$5) -> 700 | L57: =SUMIFS($R57:$W57,$R$5:$W$5,$L$5) -> 700 | M57: =L57-K57 -> 0 | N57: 0 | O57: 0 | P57: =LEFT(Y57,4) | R57: =DB!R11 -> 700 | S57: ='DB1'!R11 -> 700 | T57: ='DB2'!R11 -> 700
B58: подземная часть | J58: =SUMIFS($R58:$W58,$R$5:$W$5,$J$5) -> 0 | K58: =SUMIFS($R58:$W58,$R$5:$W$5,$K$5) -> 0 | L58: =SUMIFS($R58:$W58,$R$5:$W$5,$L$5) -> 0 | M58: =L58-K58 -> 0 | P58: =LEFT(Y58,4) | S58: 0
C59: парковка | F59: =DB!P16 -> 4500 | G59: =DB!Q16 -> 4500 | H59: т.р/шт. | J59: =SUMIFS($R59:$W59,$R$5:$W$5,$J$5) -> 4500 | K59: =SUMIFS($R59:$W59,$R$5:$W$5,$K$5) -> 4500 | L59: =SUMIFS($R59:$W59,$R$5:$W$5,$L$5) -> 4500 | M59: =L59-K59 -> 0 | N59: 0 | O59: 0 | P59: =LEFT(Y59,4) | R59: =DB!R16 -> 4500 | S59: ='DB1'!R16 -> 4500 | T59: ='DB2'!R16 -> 4500
C60: кладовки | H60: т.р/кв.м | J60: =SUMIFS($R60:$W60,$R$5:$W$5,$J$5) -> 0 | K60: =SUMIFS($R60:$W60,$R$5:$W$5,$K$5) -> 0 | L60: =SUMIFS($R60:$W60,$R$5:$W$5,$L$5) -> 0 | M60: =L60-K60 -> 0 | N60: 0 | O60: 0 | P60: =LEFT(Y60,4) | S60: 0
B61: СРОК ДО ЗАВЕРШЕНИЯ СТРОИТЕЛЬСТВА | H61: лет | J61: =SUMIFS($R61:$W61,$R$5:$W$5,$J$5) -> 5.5013699 | K61: =SUMIFS($R61:$W61,$R$5:$W$5,$K$5) -> 4.2493151 | L61: =SUMIFS($R61:$W61,$R$5:$W$5,$L$5) -> 5.5013699 | M61: =L61-K61 -> 1.2520548 | P61: =LEFT(Y61,4) | R61: =(R63-R62)/365 -> 5.5013699 | S61: 4.2493151 | T61: =(T63-T62)/365 -> 5.5013699
B62: начало проекта | H62: дата | J62: =SUMIFS($R62:$W62,$R$5:$W$5,$J$5) -> 45748 | K62: =SUMIFS($R62:$W62,$R$5:$W$5,$K$5) -> 45748 | L62: =SUMIFS($R62:$W62,$R$5:$W$5,$L$5) -> 45748 | M62: =(L62-K62)/365 -> 0 | P62: =LEFT(Y62,4) | R62: =DB!U23 -> 45748 | S62: ='DB1'!U23 -> 45748 | T62: ='DB2'!U23 -> 45748
B63: ввод в эксплуатацию | H63: дата | J63: =SUMIFS($R63:$W63,$R$5:$W$5,$J$5) -> 47756 | K63: =SUMIFS($R63:$W63,$R$5:$W$5,$K$5) -> 47391 | L63: =SUMIFS($R63:$W63,$R$5:$W$5,$L$5) -> 47756 | M63: =(L63-K63)/365 -> 1 | P63: =LEFT(Y63,4) | R63: =DB!U27 -> 47756 | S63: ='DB1'!U27 -> 47391 | T63: ='DB2'!U27 -> 47756
B64: ПЕРИОД ПРОДАЖ | H64: лет | J64: =SUMIFS($R64:$W64,$R$5:$W$5,$J$5) -> 5.2520548 | K64: =SUMIFS($R64:$W64,$R$5:$W$5,$K$5) -> 4 | L64: =SUMIFS($R64:$W64,$R$5:$W$5,$L$5) -> 4.2520548 | M64: =L64-K64 -> 0.25205479 | P64: =LEFT(Y64,4) | R64: =(R66-R65)/365 -> 5.2520548 | S64: 4 | T64: =(T66-T65)/365 -> 4.2520548
B65: начало продаж | H65: дата | J65: =SUMIFS($R65:$W65,$R$5:$W$5,$J$5) -> 46296 | K65: =SUMIFS($R65:$W65,$R$5:$W$5,$K$5) -> 46296 | L65: =SUMIFS($R65:$W65,$R$5:$W$5,$L$5) -> 46661 | M65: =(L65-K65)/365 -> 1 | P65: =LEFT(Y65,4) | R65: =DB!M8 -> 46296 | S65: ='DB1'!M8 -> 46296 | T65: ='DB2'!M8 -> 46661
B66: окончание продаж | H66: дата | J66: =SUMIFS($R66:$W66,$R$5:$W$5,$J$5) -> 48213 | K66: =SUMIFS($R66:$W66,$R$5:$W$5,$K$5) -> 48121 | L66: =SUMIFS($R66:$W66,$R$5:$W$5,$L$5) -> 48213 | M66: =(L66-K66)/365 -> 0.25205479 | P66: =LEFT(Y66,4) | R66: =DB!U28 -> 48213 | S66: ='DB1'!U28 -> 48121 | T66: ='DB2'!U28 -> 48213
B67: СРОК ПРОЕКТА | H67: лет | J67: =SUMIFS($R67:$W67,$R$5:$W$5,$J$5) -> 6.7534247 | K67: =SUMIFS($R67:$W67,$R$5:$W$5,$K$5) -> 5.2493151 | L67: =SUMIFS($R67:$W67,$R$5:$W$5,$L$5) -> 6.7534247 | M67: =L67-K67 -> 1.5041096 | P67: =LEFT(Y67,4) | R67: =(R66-R62)/365 -> 6.7534247 | S67: 5.2493151 | T67: =(T66-T62)/365 -> 6.7534247
P68: =LEFT(Y68,4)
B69: ПОСТУПЛЕНИЯ ПО ОПЕРАЦИОННОЙ ДЕЯТЕЛЬНОСТИ | H69: =IFERROR(K69/K$17*1000000,) -> 0 | I69: =IFERROR(L69/L$17*1000000,) -> 0 | J69: =SUMIFS($R69:$W69,$R$5:$W$5,$J$5) -> 0 | K69: =SUMIFS($R69:$W69,$R$5:$W$5,$K$5) -> 0 | L69: =SUMIFS($R69:$W69,$R$5:$W$5,$L$5) -> 0 | M69: =L69-K69 -> 0 | P69: =LEFT(Y69,4) | R69: 0 | S69: 0
B70: ПОСТУПЛЕНИЯ ПО ИНВЕСТИЦИОННОЙ ДЕЯТЕЛЬНОСТИ | H70: =IFERROR(K70/K$17*1000000,) -> 375149.14 | I70: =IFERROR(L70/L$17*1000000,) -> 374189.71 | J70: =SUMIFS($R70:$W70,$R$5:$W$5,$J$5) -> 78746.093 | K70: =SUMIFS($R70:$W70,$R$5:$W$5,$K$5) -> 42595.626 | L70: =SUMIFS($R70:$W70,$R$5:$W$5,$L$5) -> 36150.467 | M70: =L70-K70 -> -6445.1591 | P70: =LEFT(Y70,4) | R70: =SUM(R71) -> 78746.093 | S70: =SUM(S71) -> 42595.626 | T70: =SUM(T71) -> 36150.467
B71: РЕАЛИЗАЦИЯ ПЛОЩАДЕЙ | H71: =IFERROR(K71/K$17*1000000,) -> 375149.14 | I71: =IFERROR(L71/L$17*1000000,) -> 374189.71 | J71: =SUMIFS($R71:$W71,$R$5:$W$5,$J$5) -> 78746.093 | K71: =SUMIFS($R71:$W71,$R$5:$W$5,$K$5) -> 42595.626 | L71: =SUMIFS($R71:$W71,$R$5:$W$5,$L$5) -> 36150.467 | M71: =L71-K71 -> -6445.1591 | P71: =LEFT(Y71,4) | R71: =SUM(R72:R76) -> 78746.093 | S71: =SUM(S72:S76) -> 42595.626 | T71: =SUM(T72:T76) -> 36150.467
B72: КВАРТИРЫ | H72: =IFERROR(K72/K$17*1000000,) -> 329724.59 | I72: =IFERROR(L72/L$17*1000000,) -> 331774.42 | J72: =SUMIFS($R72:$W72,$R$5:$W$5,$J$5) -> 69490.705 | K72: =SUMIFS($R72:$W72,$R$5:$W$5,$K$5) -> 37437.979 | L72: =SUMIFS($R72:$W72,$R$5:$W$5,$L$5) -> 32052.726 | M72: =L72-K72 -> -5385.253 | P72: =LEFT(Y72,4) | R72: =CF!E54 -> 69490.705 | S72: ='CF1'!E35 -> 37437.979 | T72: ='CF2'!E35 -> 32052.726
B73: 2204_Реализация помещений свободного назначения | H73: =IFERROR(K73/K$17*1000000,) -> 0 | I73: =IFERROR(L73/L$17*1000000,) -> 0 | J73: =SUMIFS($R73:$W73,$R$5:$W$5,$J$5) -> 0 | K73: =SUMIFS($R73:$W73,$R$5:$W$5,$K$5) -> 0 | L73: =SUMIFS($R73:$W73,$R$5:$W$5,$L$5) -> 0 | M73: =L73-K73 -> 0 | P73: =LEFT(Y73,4) | S73: 0
B74: 2203_Реализация офисных помещений | H74: =IFERROR(K74/K$17*1000000,) -> 0 | I74: =IFERROR(L74/L$17*1000000,) -> 0 | J74: =SUMIFS($R74:$W74,$R$5:$W$5,$J$5) -> 0 | K74: =SUMIFS($R74:$W74,$R$5:$W$5,$K$5) -> 0 | L74: =SUMIFS($R74:$W74,$R$5:$W$5,$L$5) -> 0 | M74: =L74-K74 -> 0 | P74: =LEFT(Y74,4) | S74: 0
B75: РИТЕЙЛ | H75: =IFERROR(K75/K$17*1000000,) -> 21684.676 | I75: =IFERROR(L75/L$17*1000000,) -> 18520.247 | J75: =SUMIFS($R75:$W75,$R$5:$W$5,$J$5) -> 4251.388 | K75: =SUMIFS($R75:$W75,$R$5:$W$5,$K$5) -> 2462.1471 | L75: =SUMIFS($R75:$W75,$R$5:$W$5,$L$5) -> 1789.2409 | M75: =L75-K75 -> -672.90615 | P75: =LEFT(Y75,4) | R75: =CF!E59 -> 4251.388 | S75: ='CF1'!E44 -> 2462.1471 | T75: ='CF2'!E44 -> 1789.2409
B76: МАШИНОМЕСТА | H76: =IFERROR(K76/K$17*1000000,) -> 23739.867 | I76: =IFERROR(L76/L$17*1000000,) -> 23895.043 | J76: =SUMIFS($R76:$W76,$R$5:$W$5,$J$5) -> 5004 | K76: =SUMIFS($R76:$W76,$R$5:$W$5,$K$5) -> 2695.5 | L76: =SUMIFS($R76:$W76,$R$5:$W$5,$L$5) -> 2308.5 | M76: =L76-K76 -> -387 | P76: =LEFT(Y76,4) | R76: =CF!E63 -> 5004 | S76: ='CF1'!E46 -> 2695.5 | T76: ='CF2'!E46 -> 2308.5
B77: ИТОГО ПОСТУПЛЕНИЯ ПРОЕКТА | H77: =IFERROR(K77/K$17*1000000,) -> 375149.14 | I77: =IFERROR(L77/L$17*1000000,) -> 374189.71 | J77: =SUMIFS($R77:$W77,$R$5:$W$5,$J$5) -> 78746.093 | K77: =SUMIFS($R77:$W77,$R$5:$W$5,$K$5) -> 42595.626 | L77: =SUMIFS($R77:$W77,$R$5:$W$5,$L$5) -> 36150.467 | M77: =L77-K77 -> -6445.1591 | P77: =LEFT(Y77,4) | R77: =R69+R70 -> 78746.093 | S77: =S69+S70 -> 42595.626 | T77: =T69+T70 -> 36150.467
B78: ВЫПЛАТЫ ПО ОПЕРАЦИОННОЙ ДЕЯТЕЛЬНОСТИ | H78: =IFERROR(K78/K$17*1000000,) -> -48139.765 | I78: =IFERROR(L78/L$17*1000000,) -> -55679.314 | J78: =SUMIFS($R78:$W78,$R$5:$W$5,$J$5) -> -10845.12 | K78: =SUMIFS($R78:$W78,$R$5:$W$5,$K$5) -> -5465.9421 | L78: =SUMIFS($R78:$W78,$R$5:$W$5,$L$5) -> -5379.1783 | M78: =L78-K78 -> 86.763761 | P78: =LEFT(Y78,4) | R78: =SUM(R79:R80,R83,R85:R86) -> -10845.12 | S78: =SUM(S79:S80,S83,S85:S86) -> -5465.9421 | T78: =SUM(T79:T80,T83,T85:T86) -> -5379.1783
B79: АХР | H79: =IFERROR(K79/K$17*1000000,) -> -686.96332 | I79: =IFERROR(L79/L$17*1000000,) -> -838.42256 | J79: =SUMIFS($R79:$W79,$R$5:$W$5,$J$5) -> -159 | K79: =SUMIFS($R79:$W79,$R$5:$W$5,$K$5) -> -78 | L79: =SUMIFS($R79:$W79,$R$5:$W$5,$L$5) -> -81 | M79: =(L79-K79) -> -3 | P79: =LEFT(Y79,4) | R79: =CF!E75 -> -159 | S79: ='CF1'!E56 -> -78 | T79: ='CF2'!E56 -> -81
B80: БРОКЕРИДЖ и РАСХОДЫ НА ПРОДАЖУ | H80: =IFERROR(K80/K$17*1000000,) -> -16432.175 | I80: =IFERROR(L80/L$17*1000000,) -> -16350.803 | J80: =SUMIFS($R80:$W80,$R$5:$W$5,$J$5) -> -3445.4124 | K80: =SUMIFS($R80:$W80,$R$5:$W$5,$K$5) -> -1865.7615 | L80: =SUMIFS($R80:$W80,$R$5:$W$5,$L$5) -> -1579.651 | M80: =L80-K80 -> 286.11046 | P80: =LEFT(Y80,4) | R80: =CF!E70+CF!E71+CF!E74 -> -3445.4124 | S80: ='CF1'!E51+'CF1'!E52+'CF1'!E55 -> -1865.7615 | T80: ='CF2'!E51+'CF2'!E55+'CF2'!E52 -> -1579.651
B81: КОМИССИЯ БРОКЕРА | J81: =SUMIFS($R81:$W81,$R$5:$W$5,$J$5) -> 0.03 | K81: =SUMIFS($R81:$W81,$R$5:$W$5,$K$5) -> 0.03 | L81: =SUMIFS($R81:$W81,$R$5:$W$5,$L$5) -> 0.03 | M81: =L81-K81 -> 0 | P81: =LEFT(Y81,4) | R81: =DB!F49 -> 0.03 | S81: ='DB1'!F49 -> 0.03 | T81: ='DB2'!F49 -> 0.03
B82: КОМИССИЯ ЗА УП | J82: =SUMIFS($R82:$W82,$R$5:$W$5,$J$5) -> 0.012 | K82: =SUMIFS($R82:$W82,$R$5:$W$5,$K$5) -> 0.012 | L82: =SUMIFS($R82:$W82,$R$5:$W$5,$L$5) -> 0.012 | M82: =L82-K82 -> 0 | P82: =LEFT(Y82,4) | R82: =DB!F50 -> 0.012 | S82: ='DB1'!F50 -> 0.012 | T82: ='DB2'!F50 -> 0.012
B83: МАРКЕТИНГ И РЕКЛАМА | H83: =IFERROR(K83/K$17*1000000,) -> -11254.474 | I83: =IFERROR(L83/L$17*1000000,) -> -11225.691 | J83: =SUMIFS($R83:$W83,$R$5:$W$5,$J$5) -> -2362.3828 | K83: =SUMIFS($R83:$W83,$R$5:$W$5,$K$5) -> -1277.8688 | L83: =SUMIFS($R83:$W83,$R$5:$W$5,$L$5) -> -1084.514 | M83: =L83-K83 -> 193.35477 | P83: =LEFT(Y83,4) | R83: =CF!E72 -> -2362.3828 | S83: ='CF1'!E53 -> -1277.8688 | T83: ='CF2'!E53 -> -1084.514
B84: ПРОЦЕНТ ОТ ПРОДАЖ | J84: =SUMIFS($R84:$W84,$R$5:$W$5,$J$5) -> 0.03 | K84: =SUMIFS($R84:$W84,$R$5:$W$5,$K$5) -> 0.03 | L84: =SUMIFS($R84:$W84,$R$5:$W$5,$L$5) -> 0.03 | M84: =L84-K84 -> 0 | P84: =LEFT(Y84,4) | R84: =DB!F48 -> 0.03 | S84: ='DB1'!F48 -> 0.03 | T84: ='DB2'!F48 -> 0.03
B85: ЭКСПЛУАТАЦИОННЫЕ РАСХОДЫ | H85: =IFERROR(K85/K$17*1000000,) -> 0 | I85: =IFERROR(L85/L$17*1000000,) -> 0 | J85: =SUMIFS($R85:$W85,$R$5:$W$5,$J$5) -> 0 | K85: =SUMIFS($R85:$W85,$R$5:$W$5,$K$5) -> 0 | L85: =SUMIFS($R85:$W85,$R$5:$W$5,$L$5) -> 0 | M85: =L85-K85 -> 0 | P85: =LEFT(Y85,4) | S85: 0
B86: НАЛОГИ | H86: =IFERROR(K86/K$17*1000000,) -> -19766.153 | I86: =IFERROR(L86/L$17*1000000,) -> -27264.397 | J86: =SUMIFS($R86:$W86,$R$5:$W$5,$J$5) -> -4878.3251 | K86: =SUMIFS($R86:$W86,$R$5:$W$5,$K$5) -> -2244.3118 | L86: =SUMIFS($R86:$W86,$R$5:$W$5,$L$5) -> -2634.0133 | M86: =L86-K86 -> -389.70148 | P86: =LEFT(Y86,4) | R86: =CF!E130 -> -4878.3251 | S86: ='CF1'!E111 -> -2244.3118 | T86: ='CF2'!E111 -> -2634.0133
B87: ВЫПЛАТЫ ПО ИНВЕСТИЦИОННОЙ ДЕЯТЕЛЬНОСТИ | H87: =IFERROR(K87/K$17*1000000,) -> -221675.15 | I87: =IFERROR(L87/L$17*1000000,) -> -234071.06 | J87: =SUMIFS($R87:$W87,$R$5:$W$5,$J$5) -> -47783.306 | K87: =SUMIFS($R87:$W87,$R$5:$W$5,$K$5) -> -25169.702 | L87: =SUMIFS($R87:$W87,$R$5:$W$5,$L$5) -> -22613.604 | M87: =L87-K87 -> 2556.0976 | P87: =LEFT(Y87,4) | R87: =SUM(R88,R89,R90,R91,R92,R94,R95,R96,R98,R93) -> -47783.306 | S87: =SUM(S88,S89,S90,S91,S92,S94,S95,S96,S98,S93) -> -25169.702 | T87: =SUM(T88,T89,T90,T91,T92,T94,T95,T96,T98,T93) -> -22613.604
B88: ПРИОБРЕТЕНИЕ ОБЪЕКТА | H88: =IFERROR(K88/K$17*1000000,) -> -29194.583 | I88: =IFERROR(L88/L$17*1000000,) -> -5449.7466 | J88: =SUMIFS($R88:$W88,$R$5:$W$5,$J$5) -> -3841.3458 | K88: =SUMIFS($R88:$W88,$R$5:$W$5,$K$5) -> -3314.8458 | L88: =SUMIFS($R88:$W88,$R$5:$W$5,$L$5) -> -526.5 | M88: =L88-K88 -> 2788.3458 | P88: =LEFT(Y88,4) | R88: =CF!E79 -> -3841.3458 | S88: ='CF1'!E60 -> -3314.8458 | T88: ='CF2'!E60 -> -526.5
B89: ПРОЕКТИРОВАНИЕ | H89: =IFERROR(K89/K$17*1000000,) -> -8000 | I89: =IFERROR(L89/L$17*1000000,) -> -6500 | J89: =SUMIFS($R89:$W89,$R$5:$W$5,$J$5) -> -1536.3104 | K89: =SUMIFS($R89:$W89,$R$5:$W$5,$K$5) -> -908.34544 | L89: =SUMIFS($R89:$W89,$R$5:$W$5,$L$5) -> -627.96497 | M89: =L89-K89 -> 280.38047 | P89: =LEFT(Y89,4) | R89: =CF!E82 -> -1536.3104 | S89: ='CF1'!E63 -> -908.34544 | T89: ='CF2'!E63 -> -627.96497
B90: СОГЛАСОВАНИЯ И ИЗЫСКАНИЯ | H90: =IFERROR(K90/K$17*1000000,) -> -1000 | I90: =IFERROR(L90/L$17*1000000,) -> -1000 | J90: =SUMIFS($R90:$W90,$R$5:$W$5,$J$5) -> -210.15318 | K90: =SUMIFS($R90:$W90,$R$5:$W$5,$K$5) -> -113.54318 | L90: =SUMIFS($R90:$W90,$R$5:$W$5,$L$5) -> -96.609996 | M90: =L90-K90 -> 16.933184 | P90: =LEFT(Y90,4) | R90: =CF!E83 -> -210.15318 | S90: ='CF1'!E64 -> -113.54318 | T90: ='CF2'!E64 -> -96.609996
B91: ЗЕМЛЯ | H91: =IFERROR(K91/K$17*1000000,) -> -25305.295 | I91: =IFERROR(L91/L$17*1000000,) -> -21577.173 | J91: =SUMIFS($R91:$W91,$R$5:$W$5,$J$5) -> -4957.8143 | K91: =SUMIFS($R91:$W91,$R$5:$W$5,$K$5) -> -2873.2436 | L91: =SUMIFS($R91:$W91,$R$5:$W$5,$L$5) -> -2084.5706 | M91: =L91-K91 -> 788.673 | P91: =LEFT(Y91,4) | R91: =CF!E73+CF!E80+CF!E81 -> -4957.8143 | S91: ='CF1'!E54+'CF1'!E62+'CF1'!E61 -> -2873.2436 | T91: ='CF2'!E61+'CF2'!E62+'CF2'!E54 -> -2084.5706
B92: СМР | H92: =IFERROR(K92/K$17*1000000,) -> -137000 | I92: =IFERROR(L92/L$17*1000000,) -> -137000 | J92: =SUMIFS($R92:$W92,$R$5:$W$5,$J$5) -> -28790.985 | K92: =SUMIFS($R92:$W92,$R$5:$W$5,$K$5) -> -15555.416 | L92: =SUMIFS($R92:$W92,$R$5:$W$5,$L$5) -> -13235.569 | M92: =L92-K92 -> 2319.8462 | P92: =LEFT(Y92,4) | R92: =CF!E84 -> -28790.985 | S92: ='CF1'!E65 -> -15555.416 | T92: ='CF2'!E65 -> -13235.569
B93: СОЦИАЛЬНЫЕ ОБЪЕКТЫ | H93: =IFERROR(K93/K$17*1000000,) -> -2593.5845 | I93: =IFERROR(L93/L$17*1000000,) -> -42177.355 | J93: =SUMIFS($R93:$W93,$R$5:$W$5,$J$5) -> -4369.2379 | K93: =SUMIFS($R93:$W93,$R$5:$W$5,$K$5) -> -294.48383 | L93: =SUMIFS($R93:$W93,$R$5:$W$5,$L$5) -> -4074.7541 | M93: =L93-K93 -> -3780.2703 | P93: =LEFT(Y93,4) | R93: =CF!E87 -> -4369.2379 | S93: ='CF1'!E68 -> -294.48383 | T93: ='CF2'!E68 -> -4074.7541
B94: НАРУЖНЫЕ СЕТИ | H94: =IFERROR(K94/K$17*1000000,) -> -5500 | I94: =IFERROR(L94/L$17*1000000,) -> -5500 | J94: =SUMIFS($R94:$W94,$R$5:$W$5,$J$5) -> -1155.8425 | K94: =SUMIFS($R94:$W94,$R$5:$W$5,$K$5) -> -624.48749 | L94: =SUMIFS($R94:$W94,$R$5:$W$5,$L$5) -> -531.35498 | M94: =L94-K94 -> 93.132512 | P94: =LEFT(Y94,4) | R94: =CF!E90 -> -1155.8425 | S94: ='CF1'!E70 -> -624.48749 | T94: ='CF2'!E70 -> -531.35498
B95: СОДЕРЖАНИЕ ПЛОЩАДКИ | H95: =IFERROR(K95/K$17*1000000,) -> -1000 | I95: =IFERROR(L95/L$17*1000000,) -> -500 | J95: =SUMIFS($R95:$W95,$R$5:$W$5,$J$5) -> -161.84818 | K95: =SUMIFS($R95:$W95,$R$5:$W$5,$K$5) -> -113.54318 | L95: =SUMIFS($R95:$W95,$R$5:$W$5,$L$5) -> -48.304998 | M95: =L95-K95 -> 65.238182 | P95: =LEFT(Y95,4) | R95: =CF!E89 -> -161.84818 | S95: ='CF1'!E71 -> -113.54318 | T95: ='CF2'!E71 -> -48.304998
B96: УПРАВЛЕНИЕ ПРОЕКТОМ | H96: =IFERROR(K96/K$17*1000000,) -> -8929.8182 | I96: =IFERROR(L96/L$17*1000000,) -> -10463.236 | J96: =SUMIFS($R96:$W96,$R$5:$W$5,$J$5) -> -2024.7732 | K96: =SUMIFS($R96:$W96,$R$5:$W$5,$K$5) -> -1013.92 | L96: =SUMIFS($R96:$W96,$R$5:$W$5,$L$5) -> -1010.8532 | M96: =L96-K96 -> 3.0667635 | P96: =LEFT(Y96,4) | R96: =CF!E91+CF!E92 -> -2024.7732 | S96: ='CF1'!E72+'CF1'!E73 -> -1013.92 | T96: ='CF2'!E72+'CF2'!E73 -> -1010.8532
B97: ДЕВЕЛОПМЕНТ | H97: =IFERROR(K97/K$17*1000000,) -> -6429.8182 | I97: =IFERROR(L97/L$17*1000000,) -> -7963.2361 | J97: =SUMIFS($R97:$W97,$R$5:$W$5,$J$5) -> -1499.3902 | K97: =SUMIFS($R97:$W97,$R$5:$W$5,$K$5) -> -730.06201 | L97: =SUMIFS($R97:$W97,$R$5:$W$5,$L$5) -> -769.32821 | M97: =L97-K97 -> -39.266197 | P97: =LEFT(Y97,4) | R97: =CF!E92 -> -1499.3902 | S97: ='CF1'!E73 -> -730.06201 | T97: ='CF2'!E73 -> -769.32821
B98: НЕПРЕДВИДЕННЫЕ РАСХОДЫ | H98: =IFERROR(K98/K$17*1000000,) -> -3151.8717 | I98: =IFERROR(L98/L$17*1000000,) -> -3903.5471 | J98: =SUMIFS($R98:$W98,$R$5:$W$5,$J$5) -> -734.9952 | K98: =SUMIFS($R98:$W98,$R$5:$W$5,$K$5) -> -357.87353 | L98: =SUMIFS($R98:$W98,$R$5:$W$5,$L$5) -> -377.12167 | M98: =L98-K98 -> -19.248136 | P98: =LEFT(Y98,4) | R98: =CF!E93 -> -734.9952 | S98: ='CF1'!E74 -> -357.87353 | T98: ='CF2'!E74 -> -377.12167
B99: ИТОГО РАСХОДЫ ПРОЕКТА | H99: =IFERROR(K99/K$17*1000000,) -> -269814.92 | I99: =IFERROR(L99/L$17*1000000,) -> -289750.37 | J99: =SUMIFS($R99:$W99,$R$5:$W$5,$J$5) -> -58628.426 | K99: =SUMIFS($R99:$W99,$R$5:$W$5,$K$5) -> -30635.644 | L99: =SUMIFS($R99:$W99,$R$5:$W$5,$L$5) -> -27992.782 | M99: =L99-K99 -> 2642.8614 | P99: =LEFT(Y99,4) | R99: =R78+R87 -> -58628.426 | S99: =S78+S87 -> -30635.644 | T99: =T78+T87 -> -27992.782
P100: =LEFT(Y100,4)
B101: САЛЬДО ИНВЕСТИЦИОННОГО БЮДЖЕТА | H101: =IFERROR(K101/K$17*1000000,) -> 105334.22 | I101: =IFERROR(L101/L$17*1000000,) -> 84439.342 | J101: =SUMIFS($R101:$W101,$R$5:$W$5,$J$5) -> 20117.667 | K101: =SUMIFS($R101:$W101,$R$5:$W$5,$K$5) -> 11959.982 | L101: =SUMIFS($R101:$W101,$R$5:$W$5,$L$5) -> 8157.6845 | M101: =L101-K101 -> -3802.2977 | P101: =LEFT(Y101,4) | R101: =R77+R99 -> 20117.667 | S101: =S77+S99 -> 11959.982 | T101: =T77+T99 -> 8157.6845
...

Sheet DB
B2: ПРОЕКТ | C2: КАСАТКИНА | E2: ОЧЕРЕДЬ | F2: 1+2 очереди | G2: ЗУ | H2: =P48 -> 77:02:0019010:102 | L2: ПЛОЩАДЬ ЗУ | M2: =P51/10000 -> 4.762 | O2: ПЛОТНОСТЬ | P2: 35000 | Q2: АДРЕС | R2: ул. КАСАТКИНА, ВЛ. 7 | U2: 45826
B5: ТЭПы | F5: стены = | G5: 0.07 | L5: ДОХОДЫ
F6: ГНС | G6: ОБЩАЯ ПЛОЩАДЬ | H6: ПОЛЕЗНАЯ ПЛОЩАДЬ | I6: LF, % | J6: КОЛ-ВО | P6: ЦЕНА → | Q6: ЦЕНА ← | R6: СРЕДНЯЯ ЦЕНА | S6: ДОХОД, млн. руб. | T6: % | U6: ОБЪЕМ ПРОДАЖ, в кв.
B7: НАЗЕМНАЯ ЧАСТЬ | E7: S лота | F7: =SUM(F8:F14) -> 178143.2 | G7: =SUM(G8:G14) -> 165673.18 | H7: =SUM(H8:H14) -> 116376.12 | I7: =IFERROR(1-SUM(H8:H12)/SUM(G8:G12),"") -> 0.29755607 | L7: =B7 -> НАЗЕМНАЯ ЧАСТЬ | M7: старт | N7: % пост. | O7: c/c | P7: =(J43+J53+P42-S16)/H7*1000 -> 511.42982
A8: ЖИЛАЯ | B8: КВАРТИРЫ | D8: =F8/$F$7 -> 0.95112135 | E8: 53 | F8: ='DB1'!F8+'DB2'!F8 -> 169435.8 | G8: ='DB1'!G8+'DB2'!G8 -> 157575.29 | H8: ='DB1'!H8+'DB2'!H8 -> 110302.71 | I8: 0.3 | J8: ='DB1'!J8+'DB2'!J8 -> 2081 | L8: =B8 -> КВАРТИРЫ | M8: =U25 -> 46296 | O8: =Q8/P8-1 -> 0.35887677 | P8: =_xlfn.MINIFS(CF!$S$24:$AP$24,CF!$S$9:$AP$9,">0") -> 522.9 | Q8: =_xlfn.MAXIFS(CF!$S$24:$AP$24,CF!$S$9:$AP$9,">0") -> 710.55666 | R8: 630 | S8: ='DB1'!S8+'DB2'!S8 -> 69490.705 | T8: =S8/$S$18 -> 0.88246543 | U8: =AVERAGE(CF!S9:AP9) -> 4595.9461
A9: ЖИЛАЯ | B9: АПАРТАМЕНТЫ | E9: =IFERROR(H9/J9,0) -> 0 | F9: ='DB1'!F9+'DB2'!F9 -> 0 | G9: ='DB1'!G9+'DB2'!G9 -> 0 | H9: ='DB1'!H9+'DB2'!H9 -> 0 | I9: 0 | J9: ='DB1'!J9+'DB2'!J9 -> 0 | L9: =B9 -> АПАРТАМЕНТЫ | R9: =IFERROR(S9/H9*1000,0) -> 0 | S9: ='DB1'!S9+'DB2'!S9 -> 0 | T9: =S9/$S$18 -> 0
A10: НЕЖИЛАЯ | B10: ОФИСЫ | E10: =IFERROR(H10/J10,0) -> 0 | F10: ='DB1'!F10+'DB2'!F10 -> 0 | G10: ='DB1'!G10+'DB2'!G10 -> 0 | H10: ='DB1'!H10+'DB2'!H10 -> 0 | I10: 0 | J10: ='DB1'!J10+'DB2'!J10 -> 0 | L10: =B10 -> ОФИСЫ | R10: =IFERROR(S10/H10*1000,0) -> 0 | S10: ='DB1'!S10+'DB2'!S10 -> 0 | T10: =S10/$S$18 -> 0
A11: ТОРГОВЛЯ | B11: РИТЕЙЛ | D11: =F11/$F$7 -> 0.048878655 | E11: =IFERROR(H11/J11,0) -> 99.564123 | F11: ='DB1'!F11+'DB2'!F11 -> 8707.4 | G11: ='DB1'!G11+'DB2'!G11 -> 8097.882 | H11: ='DB1'!H11+'DB2'!H11 -> 6073.4115 | I11: 0.25 | J11: ='DB1'!J11+'DB2'!J11 -> 61 | L11: =B11 -> РИТЕЙЛ | M11: 1 | O11: =Q11/P11-1 -> 0 | P11: =_xlfn.MINIFS(CF!$S$29:$AP$29,CF!$S$16:$AP$16,">0") -> 700 | Q11: =_xlfn.MAXIFS(CF!$S$29:$AP$29,CF!$S$16:$AP$16,">0") -> 700 | R11: =IFERROR(S11/H11*1000,0) -> 700 | S11: ='DB1'!S11+'DB2'!S11 -> 4251.388 | T11: =S11/$S$18 -> 0.053988559
A12: ТОРГОВЛЯ | B12: ТЦ | E12: =IFERROR(H12/J12,0) -> 0 | F12: ='DB1'!F12+'DB2'!F12 -> 0 | G12: ='DB1'!G12+'DB2'!G12 -> 0 | H12: ='DB1'!H12+'DB2'!H12 -> 0 | I12: 0 | J12: ='DB1'!J12+'DB2'!J12 -> 0 | L12: =B12 -> ТЦ | P12: =#REF! -> #REF! | Q12: =#REF! -> #REF! | R12: =IFERROR(S12/H12*1000,0) -> 0 | S12: ='DB1'!S12+'DB2'!S12 -> 0 | T12: =S12/$S$18 -> 0
B13: ШКОЛА | C13: мест | D13: ='DB1'!D13+'DB2'!D13 -> 1000 | F13: ='DB1'!F13+'DB2'!F13 -> 0 | G13: ='DB1'!G13+'DB2'!G13 -> 0 | H13: ='DB1'!H13+'DB2'!H13 -> 0 | I13: =IFERROR(1-(H13/G13),0) -> 0 | J13: ='DB1'!J13+'DB2'!J13 -> 0 | L13: =B13 -> ШКОЛА | R13: =IFERROR(S13/H13*1000,0) -> 0 | S13: ='DB1'!S13+'DB2'!S13 -> 0
A14: =A13 -> 0 | B14: ДОУ | C14: мест | D14: ='DB1'!D14+'DB2'!D14 -> 0 | F14: ='DB1'!F14+'DB2'!F14 -> 0 | G14: ='DB1'!G14+'DB2'!G14 -> 0 | H14: ='DB1'!H14+'DB2'!H14 -> 0 | I14: =IFERROR(1-(H14/G14),0) -> 0 | J14: ='DB1'!J14+'DB2'!J14 -> 0 | L14: =B14 -> ДОУ | R14: =IFERROR(S14/H14*1000,0) -> 0 | S14: ='DB1'!S14+'DB2'!S14 -> 0
B15: ПОДЗЕМНАЯ ЧАСТЬ | D15: S общ. | E15: S пол. | G15: =SUM(G16:G17) -> 44480 | H15: =SUM(H16:H17) -> 16680 | L15: =B15 -> ПОДЗЕМНАЯ ЧАСТЬ
B16: ПАРКИНГ ЖИЛЬЕ | C16: =J16/J8 -> 0.53435848 | D16: 40 | E16: 15 | F16: ='DB1'!F16+'DB2'!F16 -> 0 | G16: ='DB1'!G16+'DB2'!G16 -> 44480 | H16: ='DB1'!H16+'DB2'!H16 -> 16680 | J16: ='DB1'!J16+'DB2'!J16 -> 1112 | L16: =B16 -> ПАРКИНГ ЖИЛЬЕ | N16: 0.7 | P16: =_xlfn.MINIFS(CF!$S$33:$AP$33,CF!$S$18:$AP$18,">0") -> 4500 | Q16: =_xlfn.MAXIFS(CF!$S$33:$AP$33,CF!$S$18:$AP$18,">0") -> 4500 | R16: =IFERROR(S16/J16*1000,0) -> 4500 | S16: ='DB1'!S16+'DB2'!S16 -> 5004 | T16: =S16/$S$18 -> 0.06354601
B17: ПАРКИНГ ОФИС | F17: ='DB1'!F17+'DB2'!F17 -> 0 | G17: ='DB1'!G17+'DB2'!G17 -> 0 | H17: ='DB1'!H17+'DB2'!H17 -> 0 | J17: ='DB1'!J17+'DB2'!J17 -> 0 | L17: =B17 -> ПАРКИНГ ОФИС | N17: 0.7 | R17: =IFERROR(S17/J17*1000,0) -> 0 | S17: ='DB1'!S17+'DB2'!S17 -> 0 | T17: =S17/$S$18 -> 0
B18: ПЛОЩАДИ | F18: =F15+F7 -> 178143.2 | G18: =G15+G7 -> 210153.18 | H18: =SUM(H7,H15) -> 133056.12 | I18: =IFERROR(100%-SUM(H8:H12)/SUM(G8:G12),) -> 0.29755607 | L18: ДОХОДЫ | S18: =SUM(S8:S17) -> 78746.093
B20: ИНВЕСТИЦИИ | L20: ФИНАНСИРОВАНИЕ | R20: СРОКИ
H21: руб./S общ. | I21: руб./S пол. | J21: млн.руб. | L21: КРЕДИТ | U21: кв.
B22: ВХОД | F22: =J22/M2 -> 806.66648 | G22: за Га | H22: =IFERROR(J22/$G$18*1000000,0) -> 18278.79 | I22: =IFERROR(J22/$H$18*1000000,0) -> 28870.118 | J22: ='DB1'!J22+'DB2'!J22 -> 3841.3458 | L22: СТАВКИ | P22: ='TS1'!J85 -> 0.2 | R22: НАЧАЛО РАСЧЕТОВ | U22: 45017
B23: FINDERS FEE | G23: % от входа | H23: =IFERROR(J23/$G$18*1000000,0) -> 0 | I23: =IFERROR(J23/$H$18*1000000,0) -> 0 | J23: ='DB1'!J23+'DB2'!J23 -> 0 | L23: СТАВКА бридж | N23: 0.05 | P23: =P22+N23 -> 0.25 | R23: НАЧАЛО ПРОЕКТА | U23: 45748
B24: ЗЕМЕЛЬНО-ПРАВОВЫЕ ВОПРОСЫ | H24: =J24/$G$18*1000000 -> 23436.307 | I24: =IFERROR(J24/$H$18*1000000,0) -> 37016.069 | J24: ='DB1'!J24+'DB2'!J24 -> 4925.2144 | L24: СТАВКА проектное фин-ие | N24: 0.038 | P24: =P22+N24 -> 0.238 | R24: СРОК ИРД | U24: 5
B25: ВРИ | C25: =IF(D25>0,"со скидкой",0) -> 0 | H25: =IFERROR(J25/$G$18*1000000,0) -> 40248.472 | I25: =IFERROR(J25/$H$18*1000000,0) -> 63569.75 | J25: ='DB1'!J25+'DB2'!J25 -> 8458.3441 | L25: СТАВКА под эскроу | P25: =N24 -> 0.038 | R25: РНС 1 | U25: ='DB1'!U25 -> 46296
B26: ЛЬГОТА | H26: =IFERROR(J26/$G$18*1000000,0) -> -40248.472 | I26: =IFERROR(J26/$H$18*1000000,0) -> -63569.75 | J26: ='DB1'!J26+'DB2'!J26 -> -8458.3441 | L26: КОМИССИИ | R26: СРОК СМР | U26: =(U27-U25)/(365/4) -> 16
B27: ПОКУПКА ЛЬГОТЫ | H27: =IFERROR(J27/$G$18*1000000,0) -> 22313.699 | I27: =IFERROR(J27/$H$18*1000000,0) -> 35242.985 | J27: ='DB1'!J27+'DB2'!J27 -> 4689.2948 | L27: РЕЗЕРВИРОВАНИЕ в банке | O27: =(P31+P32+P33)*P27 -> 303.39455 | P27: 0.005 | R27: РНВ 2 | U27: ='DB2'!U27 -> 47756
B28: РАССРОЧКА ВРИ | H28: =IFERROR(J28/$G$18*1000000,0) -> 0 | I28: =IFERROR(J28/$H$18*1000000,0) -> 0 | J28: ='DB1'!J28+'DB2'!J28 -> 0 | L28: БРОКЕРИДЖ МРГ бридж | O28: =(P31+P32)*P28 -> 0 | P28: 0 | R28: ОКОНЧАНИЕ ПРОДАЖ | U28: =_xlfn.MAXIFS(CF!$F$6:$BM$6,CF!$F$9:$BM$9,">0") -> 48213
B29: АРЕНДА ЗУ/НАЛОГ ЗУ | F29: =P49 -> АРЕНДА | H29: =IFERROR(J29/$G$18*1000000,0) -> 1122.6079 | I29: =IFERROR(J29/$H$18*1000000,0) -> 1773.0836 | J29: ='DB1'!J29+'DB2'!J29 -> 235.91962 | L29: БРОКЕРИДЖ МРГ проектное фин-ие | O29: =(P33+P32)*P29 -> 0 | R29: СРОК | U29: =(U28-U23)/365 -> 6.7534247
B30: ВЛОЖЕНИЯ В СТРОИТЕЛЬСТВО | H30: =IFERROR(J30/$G$18*1000000,0) -> 185503.48 | I30: =IFERROR(J30/$H$18*1000000,0) -> 292990.25 | J30: ='DB1'!J30+'DB2'!J30 -> 38984.146 | L30: ОБЪЕМ ФИНАНСИРОВАНИЯ
B31: ПРОЕКТИРОВАНИЕ (К+П+РД) | F31: =H31 -> 7310.4316 | G31: м2 S общ. | H31: =IFERROR(J31/$G$18*1000000,0) -> 7310.4316 | I31: =IFERROR(J31/$H$18*1000000,0) -> 11546.334 | J31: ='DB1'!J31+'DB2'!J31 -> 1536.3104 | L31: ВХОД | O31: млн. руб. | P31: ='DB1'!P31+'DB2'!P31 -> 0 | R31: РЕЗУЛЬТАТ
B32: СОГЛАСОВАНИЯ | F32: =H32 -> 1000 | G32: м2 S общ. | H32: =IFERROR(J32/$G$18*1000000,0) -> 1000 | I32: =IFERROR(J32/$H$18*1000000,0) -> 1579.4327 | J32: ='DB1'!J32+'DB2'!J32 -> 210.15318 | L32: ДО РНС | O32: млн. руб. | P32: ='DB1'!P32+'DB2'!P32 -> 9723.0277 | U32: млн. руб.
B33: СМР жилье | F33: 137000 | G33: м2 S общ. | H33: =IFERROR(J33/(G18)*1000000,0) -> 137000 | I33: =IFERROR(J33/($H$8+$H$9+$H$11+$H$16)*1000000,0) -> 216382.27 | J33: ='DB1'!J33+'DB2'!J33 -> 28790.985 | L33: ПРОЕКТНОЕ ФИН-ИЕ (без учета реф бриджа) | O33: млн. руб. | P33: ='DB1'!P33+'DB2'!P33 -> 50955.882 | R33: ДОХОДЫ | U33: ='DB1'!U33+'DB2'!U33 -> 78746.093
B34: СМР офисы | F34: =H34 -> 0 | G34: м2 S общ. | H34: =IFERROR(J34/($G$10+$G$17)*1000000,0) -> 0 | I34: =IFERROR(J34/($H$10+$H$17)*1000000,0) -> 0 | J34: ='DB1'!J34+'DB2'!J34 -> 0 | L34: % и КОМИСИИ банка | O34: млн. руб. | P34: ='DB1'!P34+'DB2'!P34 -> 10379.811 | R34: РАСХОДЫ НА ПРОДАЖУ | U34: ='DB1'!U34+'DB2'!U34 -> -5999.3951
B35: СМР ТЦ | F35: =H35 -> 0 | G35: м2 S общ. | H35: =IFERROR(J35/$G$12*1000000,0) -> 0 | I35: =IFERROR(J35/$H$12*1000000,0) -> 0 | J35: ='DB1'!J35+'DB2'!J35 -> 0 | M35: бридж | O35: млн. руб. | P35: ='DB1'!P35+'DB2'!P35 -> 1452.0383 | R35: ИНВЕСТИЦИИ | U35: ='DB1'!U35+'DB2'!U35 -> -47750.706
B36: СМР соц. объектов (компенсация) | F36: =H36 -> 20790.73 | G36: м2 Sобщ. | H36: =IFERROR(J36/(G18)*1000000,0) -> 20790.73 | I36: =IFERROR(J36/(H18)*1000000,0) -> 32837.558 | J36: ='DB1'!J36+'DB2'!J36 -> 4369.2379 | M36: проектное фин-ие | O36: млн. руб. | P36: ='DB1'!P36+'DB2'!P36 -> 8624.3786 | R36: ПРОЦЕНТЫ | U36: ='DB1'!U36+'DB2'!U36 -> -10772.116
B37: ОТДЕЛКА жилье | F37: =I37 -> 0 | G37: м2 Sпол. | H37: =IFERROR(J37/($G$8+$G$9)*1000000,0) -> 0 | I37: =IFERROR(J37/($H$8+$H$9)*1000000,0) -> 0 | J37: ='DB1'!J37+'DB2'!J37 -> 0 | M37: комиссии банка | O37: млн. руб. | P37: ='DB1'!P37+'DB2'!P37 -> 303.39455 | R37: НАЛОГИ | U37: ='DB1'!U37+'DB2'!U37 -> -4878.3251
B38: ='DB1'!B38 -> СОДЕРЖАНИЕ ПЛОЩАДКИ | F38: =H38 -> 770.14386 | G38: м2 S общ. | H38: =IFERROR(J38/$G$18*1000000,0) -> 770.14386 | I38: =IFERROR(J38/$H$18*1000000,0) -> 1216.3904 | J38: ='DB1'!J38+'DB2'!J39 -> 161.84818 | L38: АКЦИОНЕРВНЫЕ ЗАЙМЫ | R38: ПРИБЫЛЬ ( в т ч SF МРГ) | U38: ='DB1'!U38+'DB2'!U38 -> 9345.5509
B39: СЕТИ | F39: 5500 | G39: м2 Sобщ. | H39: =IFERROR(J39/$G$18*1000000,0) -> 5500 | I39: =IFERROR(J39/$H$18*1000000,0) -> 8686.8796 | J39: ='DB1'!J39+'DB2'!J38 -> 1155.8425 | L39: СТАВКА ЗАЙМА | N39: 0.01 | P39: =P22+N39 -> 0.21 | R39: МАРЖИНАЛЬНОСТЬ до Н/О | U39: =(U38-CF!E146)/U33 -> 0.17534919
B40: МОНИТОРИНГИ | F40: =H40 -> 2500 | G40: м2 Sобщ. | H40: =IFERROR(J40/$G$18*1000000,0) -> 2500 | I40: =IFERROR(J40/$H$18*1000000,0) -> 3948.5816 | J40: ='DB1'!J40+'DB2'!J40 -> 525.38294 | L40: ТЕЛО ЗАЙМА | O40: млн. руб. | P40: ='DB1'!P40+'DB2'!P40 -> 596.3444 | R40: МАРЖ-СТЬ после Н/О | U40: =U38/U33 -> 0.11867955
B41: УПРАВЛЕНИЕ ПРОЕКТОМ | D41: =J41/(DETAILS!F361*3) -> 20.824864 | E41: млн. в мес. | F41: 0.04 | G41: % от расходов | H41: =IFERROR(J41/$G$18*1000000,0) -> 7134.7493 | I41: =IFERROR(J41/$H$18*1000000,0) -> 11268.856 | J41: ='DB1'!J41+'DB2'!J41 -> 1499.3902 | K41: =(J43+J53-U36-J50-J41)*3.5% -> 2172.7256 | L41: % | O41: млн. руб. | P41: ='DB1'!P41+'DB2'!P41 -> 392.30429 | R41: IRR ПРОЕКТА (pre-tax) | U41: =IFERROR(POWER((1+IRR(CF!F95:BM95,0.01)),4)-1,0) -> 0.1755044
B42: НЕПРЕДВИДЕННЫЕ РАСХОДЫ | F42: =J42/SUM(J31:J40) -> 0.02 | G42: % от расходов | H42: =IFERROR(J42/$G$18*1000000,0) -> 3497.4261 | I42: =IFERROR(J42/$H$18*1000000,0) -> 5523.949 | J42: ='DB1'!J42+'DB2'!J42 -> 734.9952 | K42: =J41/(J43+J53-U36-J50-J41) -> 0.024153376 | L42: ПРОЦЕНТЫ | N42: =IFERROR(P42/$G$18*1000000,0) -> 51258.401 | O42: =IFERROR(P42/$H$18*1000000,0) -> 80959.192 | P42: =-U36 -> 10772.116 | R42: IRR ИНВЕСТОРА | U42: =IFERROR(POWER((1+IRR(CF!F190:BM190,0.01)),4)-1,0) -> 0.63323675
B43: ИНВЕСТИЦИИ | H43: =IFERROR(J43/$G$18*1000000,0) -> 227218.58 | I43: =IFERROR(J43/$H$18*1000000,0) -> 358876.44 | J43: =SUM(J22,J24,J30) -> 47750.706 | R43: LLSR | U43: =(-U33-U37)/(U36-P33) -> 1.1966655
R44: PV | S44: =((1+T44)^(1/4))-1 -> 0.046635139 | T44: 0.2 | U44: =NPV(S44,CF!F190:BM190) -> 1866.4393
B45: РАСХОДЫ НА ПРОДАЖУ
H46: руб./S общ. | I46: руб./S пол. | J46: млн.руб. | L46: ЗУ | R46: ДОХОДЫ УПРАВЛЯЮЩЕГО
B47: АХР | F47: 2 | G47: млн. р. в кв. | H47: =J47/$G$18*1000000 -> 756.59099 | I47: =J47/$H$18*1000000 -> 1194.9845 | J47: ='DB1'!J47+'DB2'!J47 -> 159 | U47: млн. руб.
B48: РЕКЛАМА И МАРКЕТИНГ | F48: 0.03 | G48: % от выручки | H48: =J48/$G$18*1000000 -> 11241.242 | I48: =J48/$H$18*1000000 -> 17754.785 | J48: ='DB1'!J48+'DB2'!J48 -> 2362.3828 | L48: КАДАСТРОВЫЙ НОМЕР | P48: 77:02:0019010:102 | R48: =B41 -> УПРАВЛЕНИЕ ПРОЕКТОМ | U48: ='DB1'!U48+'DB2'!U48 -> 1499.3902
B49: БРОКЕРИДЖ | F49: 0.03 | G49: % от выручки | H49: =J49/$G$18*1000000 -> 11241.242 | I49: =J49/$H$18*1000000 -> 17754.785 | J49: ='DB1'!J49+'DB2'!J49 -> 2362.3828 | L49: ВИД ПРАВА | P49: АРЕНДА | R49: =B50 -> УПРАВЛЕНИЕ ПРОДАЖАМИ | U49: ='DB1'!U49+'DB2'!U49 -> 944.95311
B50: УПРАВЛЕНИЕ ПРОДАЖАМИ | F50: 0.012 | G50: % от выручки | H50: =J50/$G$18*1000000 -> 4496.4969 | I50: =J50/$H$18*1000000 -> 7101.9141 | J50: ='DB1'!J50+'DB2'!J50 -> 944.95311 | L50: АРЕНДА / НАЛОГ ЗУ после ввода | O50: кв. | P50: 2 | R50: ПРИВЛЕЧЕНИЕ КРЕДИТА | U50: ='DB1'!U50+'DB2'!U50 -> 0
B51: РЕГИСТРАЦИЯ ДОГОВОРОВ | F51: 30000 | G51: руб./лот | H51: =J51/$G$18*1000000 -> 657.02811 | I51: =J51/$H$18*1000000 -> 1037.7316 | J51: ='DB1'!J51+'DB2'!J51 -> 138.07654 | L51: ПЛОЩАДЬ ЗУ | O51: м2 | P51: ='DB1'!P51+'DB2'!P51 -> 47620 | R51: FINDERS FEE | U51: ='DB1'!U51+'DB2'!U51 -> 0
B52: АРЕНДА / НАЛОГ ЗУ | H52: =J52/$G$18*1000000 -> 155.12455 | I52: =J52/$H$18*1000000 -> 245.00877 | J52: ='DB1'!J52+'DB2'!J52 -> 32.599916 | L52: УДЕЛЬНАЯ ТЕКУЩАЯ КС | O52: тыс. руб. | P52: =1098511881.06/50873 -> 21593.22 | R52: SF | T52: =U52/U38 -> 0.05 | U52: ='DB1'!U52+'DB2'!U52 -> 467.27754
B53: РАСХОДЫ | H53: =J53/$G$18*1000000 -> 28547.725 | I53: =J53/$H$18*1000000 -> 45089.209 | J53: =SUM(J47:J52) -> 5999.3951 | U53: =SUM(U48:U52) -> 2911.6209
B65: ЧУВСТВИТЕЛЬНОСТЬ
B66: ПРИБЫЛИ к ср. цене квартир и СМР
C68: =C69-$F$69 -> -30 | D68: =D69-$F$69 -> -20 | E68: =E69-$F$69 -> -10 | F68: =F69-$F$69 -> 0 | G68: =G69-$F$69 -> 10 | H68: =H69-$F$69 -> 20 | I68: =I69-$F$69 -> 30
B69: =U38 -> 9345.5509 | C69: 600 | D69: 610 | E69: 620 | F69: 630 | G69: 640 | H69: 650 | I69: 660
A70: =B70-$B$73 -> -20550 | B70: =$B$73/100*85 -> 116450 | C70: 11258.366 | D70: 12120.21 | E70: 12980.405 | F70: 13842.045 | G70: 14698.96 | H70: 15554.878 | I70: 16408.934
A71: =B71-$B$73 -> -13700 | B71: =$B$73/100*90 -> 123300 | C71: 9752.9948 | D71: 10628.718 | E71: 11499.204 | F71: 12360.998 | G71: 13219.699 | H71: 14083.309 | I71: 14940.239
A72: =B72-$B$73 -> -6850 | B72: =$B$73/100*95 -> 130150 | C72: 8232.5896 | D72: 9108.4118 | E72: 9989.2673 | F72: 10865.862 | G72: 11738.342 | H72: 12601.161 | I72: 13460.189
A73: =B73-$B$73 -> 0 | B73: 137000 | C73: 6704.1061 | D73: 7590.7019 | E73: 8469.8146 | F73: 9345.5509 | G73: 10225.534 | H73: 11103.004 | I73: 11976.375
A74: =B74-$B$73 -> 6850 | B74: =$B$73*1.05 -> 143850 | C74: 4635.6902 | D74: 5622.5591 | E74: 6941.0095 | F74: 7827.3105 | G74: 8707.0246 | H74: 9582.6798 | I74: 10461.796
A75: =B75-$B$73 -> 13700 | B75: =$B$73*1.1 -> 150700 | C75: 2857.5736 | D75: 3868.9041 | E75: 4873.3627 | F75: 5858.8513 | G75: 7177.8879 | H75: 8063.9002 | I75: 8944.22
A76: =B76-$B$73 -> 20550 | B76: =$B$73*1.15 -> 157550 | C76: 1077.9971 | D76: 2087.4075 | E76: 3095.3509 | F76: 4107.7892 | G76: 5111.0043 | H76: 6095.1201 | I76: 7414.7427
B82: ПРИБЫЛИ к соотношению ПЛОЩАДИ ОЧЕРЕДЕЙ а ПЛОЩАДИ ЗУ
B84: ='МАСТЕР ПЛАН'!$AA$31*B85 -> 59380.755 | C84: ='МАСТЕР ПЛАН'!$AA$31*C85 -> 55987.569 | D84: ='МАСТЕР ПЛАН'!$AA$31*D85 -> 67863.72 | E84: ='МАСТЕР ПЛАН'!$AA$31*E85 -> 84829.65 | F84: ='МАСТЕР ПЛАН'!$AA$31*F85 -> 93312.615 | G84: ='МАСТЕР ПЛАН'!$AA$31*G85 -> 106885.36 | H84: ='МАСТЕР ПЛАН'!$AA$31*H85 -> 118761.51
B85: 0.35 | C85: 0.33 | D85: 0.4 | E85: 0.5 | F85: 0.55 | G85: 0.63 | H85: 0.7 | I85: 1 оч
A86: =U38 -> 9345.5509 | B86: 9345.5509 | C86: 9345.5509 | D86: 9345.5509 | E86: 9345.5509 | F86: 9345.5509 | G86: 9345.5509 | H86: 9345.5509
B87: =1-B85 -> 0.65 | C87: =1-C85 -> 0.67 | D87: =1-D85 -> 0.6 | E87: =1-E85 -> 0.5 | F87: =1-F85 -> 0.45 | G87: =1-G85 -> 0.37 | H87: =1-H85 -> 0.3 | I87: 2 оч
B88: ='МАСТЕР ПЛАН'!$AA$31*B87 -> 110278.54 | C88: ='МАСТЕР ПЛАН'!$AA$31*C87 -> 113671.73 | D88: ='МАСТЕР ПЛАН'!$AA$31*D87 -> 101795.58 | E88: ='МАСТЕР ПЛАН'!$AA$31*E87 -> 84829.65 | F88: ='МАСТЕР ПЛАН'!$AA$31*F87 -> 76346.685 | G88: ='МАСТЕР ПЛАН'!$AA$31*G87 -> 62773.941 | H88: ='МАСТЕР ПЛАН'!$AA$31*H87 -> 50897.79
B93: PRESENT VALUE к соотношению ПЛОЩАДИ ОЧЕРЕДЕЙ а ПЛОЩАДИ ЗУ
B95: ='МАСТЕР ПЛАН'!$AA$31*B96 -> 50897.79 | C95: ='МАСТЕР ПЛАН'!$AA$31*C96 -> 55987.569 | D95: ='МАСТЕР ПЛАН'!$AA$31*D96 -> 67863.72 | E95: ='МАСТЕР ПЛАН'!$AA$31*E96 -> 84829.65 | F95: ='МАСТЕР ПЛАН'!$AA$31*F96 -> 93312.615 | G95: ='МАСТЕР ПЛАН'!$AA$31*G96 -> 101795.58 | H95: ='МАСТЕР ПЛАН'!$AA$31*H96 -> 118761.51
B96: 0.3 | C96: 0.33 | D96: 0.4 | E96: 0.5 | F96: 0.55 | G96: 0.6 | H96: 0.7 | I96: 1 оч
A97: =U44 -> 1866.4393 | B97: 1866.4393 | C97: 1866.4393 | D97: 1866.4393 | E97: 1866.4393 | F97: 1866.4393 | G97: 1866.4393 | H97: 1866.4393
B98: =1-B96 -> 0.7 | C98: =1-C96 -> 0.67 | D98: =1-D96 -> 0.6 | E98: =1-E96 -> 0.5 | F98: =1-F96 -> 0.45 | G98: =1-G96 -> 0.4 | H98: =1-H96 -> 0.3 | I98: 2 оч
B99: ='МАСТЕР ПЛАН'!$AA$31*B98 -> 118761.51 | C99: ='МАСТЕР ПЛАН'!$AA$31*C98 -> 113671.73 | D99: ='МАСТЕР ПЛАН'!$AA$31*D98 -> 101795.58 | E99: ='МАСТЕР ПЛАН'!$AA$31*E98 -> 84829.65 | F99: ='МАСТЕР ПЛАН'!$AA$31*F98 -> 76346.685 | G99: ='МАСТЕР ПЛАН'!$AA$31*G98 -> 67863.72 | H99: ='МАСТЕР ПЛАН'!$AA$31*H98 -> 50897.79
B106: 1 оч | C106: 2 оч
B107: 0.5 | C107: =1-B107 -> 0.5
B108: =U38 -> 9345.5509

Sheet DB1
B2: ПРОЕКТ | C2: =DB!C2 -> КАСАТКИНА | E2: ОЧЕРЕДЬ | F2: 1 | G2: ЗУ | H2: =P48 -> 77:02:0019010:102 | L2: ПЛОЩАДЬ ЗУ | M2: =P51/10000 -> 2.544 | O2: ПЛОТНОСТЬ | P2: =DB!P2 -> 35000 | Q2: АДРЕС | R2: =DB!R2 -> ул. КАСАТКИНА, ВЛ. 7 | U2: =DB!U2 -> 45826
B5: ТЭПы | F5: стены = | G5: =DB!$G$5 -> 0.07 | L5: ДОХОДЫ
F6: ГНС | G6: ОБЩАЯ ПЛОЩАДЬ | H6: ПОЛЕЗНАЯ ПЛОЩАДЬ | I6: LF, % | J6: КОЛ-ВО | P6: ЦЕНА → | Q6: ЦЕНА ← | R6: СРЕДНЯЯ ЦЕНА | S6: ДОХОД, млн. руб. | T6: % | U6: ОБЪЕМ ПРОДАЖ, в кв.
B7: НАЗЕМНАЯ ЧАСТЬ | E7: S лота | F7: =F8+F11 -> 96326 | G7: =SUM(G8:G14) -> 89583.18 | H7: =SUM(H8:H14) -> 62942.716 | I7: =IFERROR(1-H7/G7,"") -> 0.29738243 | L7: =B7 -> НАЗЕМНАЯ ЧАСТЬ | M7: старт | N7: % пост. | O7: дисконт
A8: ЖИЛАЯ | B8: КВАРТИРЫ | D8: =F8/$F$7 -> 0.94764861 | E8: =DB!E8 -> 53 | F8: =IF('МАСТЕР ПЛАН'!$AE$2=TRUE,'МАСТЕР ПЛАН'!AB5,IF('МАСТЕР ПЛАН'!$AE$11=TRUE,'МАСТЕР ПЛАН'!AB14,IF('МАСТЕР ПЛАН'!$AE$19=TRUE,'МАСТЕР ПЛАН'!AB22,IF('МАСТЕР ПЛАН'!$AE$28=TRUE,'МАСТЕР ПЛАН'!AB31,0)))) -> 91283.2 | G8: =F8*(1-$G$5) -> 84893.376 | H8: =G8*(1-I8) -> 59425.363 | I8: =DB!$I8 -> 0.3 | J8: =IFERROR(ROUND(H8/E8,0),0) -> 1121 | L8: =B8 -> КВАРТИРЫ | M8: =$U$25 -> 46296 | N8: 0.7 | O8: -0.17 | P8: =_xlfn.MINIFS('CF1'!$F17:$AS17,'CF1'!$F8:$AS8,">0") -> 522.9 | Q8: =_xlfn.MAXIFS('CF1'!$F17:$AS17,'CF1'!$F8:$AS8,">0") -> 698.37097 | R8: =DB!R8 -> 630 | S8: ='CF1'!E26 -> 37437.979 | T8: =S8/$S$18 -> 0.87891604 | U8: 3000
A9: ЖИЛАЯ | B9: АПАРТАМЕНТЫ | D9: =F9/$F$7 -> 0 | E9: 60 | G9: =F9*(1-$G$5) -> 0 | H9: =G9*(1-I9) -> 0 | I9: =DB!$I9 -> 0 | J9: =IFERROR(ROUND(H9/E9,0),0) -> 0 | L9: =B9 -> АПАРТАМЕНТЫ | M9: =$U$25 -> 46296 | N9: 0.7 | P9: =_xlfn.MINIFS('CF1'!$F18:$AS18,'CF1'!$F9:$AS9,">0") -> 0 | Q9: =_xlfn.MAXIFS('CF1'!$F18:$AS18,'CF1'!$F9:$AS9,">0") -> 0 | S9: ='CF1'!E27 -> 0 | T9: =S9/$S$18 -> 0
A10: НЕЖИЛАЯ | B10: ОФИСЫ | D10: =F10/$F$7 -> 0 | E10: 100 | G10: =F10*(1-$G$5) -> 0 | H10: =G10*(1-I10) -> 0 | I10: =DB!$I10 -> 0 | J10: =IFERROR(ROUND(H10/E10,0),0) -> 0 | L10: =B10 -> ОФИСЫ | M10: =$U$25 -> 46296 | N10: 0.7 | P10: =_xlfn.MINIFS('CF1'!$F19:$AS19,'CF1'!$F10:$AS10,">0") -> 0 | Q10: =_xlfn.MAXIFS('CF1'!$F19:$AS19,'CF1'!$F10:$AS10,">0") -> 0 | S10: ='CF1'!E28 -> 0 | T10: =S10/$S$18 -> 0
A11: ТОРГОВЛЯ | B11: РИТЕЙЛ | D11: =F11/$F$7 -> 0.05235139 | E11: 100 | F11: =IF('МАСТЕР ПЛАН'!$AE$2=TRUE,'МАСТЕР ПЛАН'!AB6,IF('МАСТЕР ПЛАН'!$AE$11=TRUE,'МАСТЕР ПЛАН'!AB15,IF('МАСТЕР ПЛАН'!$AE$19=TRUE,'МАСТЕР ПЛАН'!AB23,IF('МАСТЕР ПЛАН'!$AE$28=TRUE,'МАСТЕР ПЛАН'!AB32,0)))) -> 5042.8 | G11: =F11*(1-$G$5) -> 4689.804 | H11: =G11*(1-I11) -> 3517.353 | I11: =DB!$I11 -> 0.25 | J11: =IFERROR(ROUND(H11/E11,0),0) -> 35 | L11: =B11 -> РИТЕЙЛ | M11: =DB!$M$11 -> 1 | N11: 1 | O11: =Q11/P11-1 -> 0 | P11: =_xlfn.MINIFS('CF1'!$F20:$AS20,'CF1'!$F11:$AS11,">0") -> 700 | Q11: =_xlfn.MAXIFS('CF1'!$F20:$AS20,'CF1'!$F11:$AS11,">0") -> 700 | R11: 700 | S11: ='CF1'!E29 -> 2462.1471 | T11: =S11/$S$18 -> 0.057802815
A12: ТОРГОВЛЯ | B12: ТЦ | D12: =F12/$F$7 -> 0 | E12: 100 | G12: =F12*(1-$G$5) -> 0 | H12: =G12*(1-I12) -> 0 | I12: =DB!$I12 -> 0 | J12: =IFERROR(ROUND(H12/E12,0),0) -> 0 | L12: =B12 -> ТЦ | M12: =DB!$M$12 -> 0 | P12: =_xlfn.MINIFS('CF1'!$F21:$AS21,'CF1'!$F12:$AS12,">0") -> 0 | Q12: =_xlfn.MAXIFS('CF1'!$F21:$AS21,'CF1'!$F12:$AS12,">0") -> 0 | S12: ='CF1'!E30 -> 0 | T12: =S12/$S$18 -> 0
A13: ='TS1'!B68 -> СОЦИАЛКА | B13: ШКОЛА | C13: мест | G13: =F13*(1-$G$5) -> 0 | L13: =B13 -> ШКОЛА
A14: =A13 -> СОЦИАЛКА | B14: ДОУ | C14: мест | G14: =F14*(1-$G$5) -> 0 | L14: =B14 -> ДОУ
B15: ПОДЗЕМНАЯ ЧАСТЬ | D15: S общ. | E15: S пол. | G15: =G16 -> 23960 | H15: =H16 -> 8985 | L15: =B15 -> ПОДЗЕМНАЯ ЧАСТЬ
B16: ПАРКИНГ ЖИЛЬЕ | C16: =J16/J8 -> 0.53434434 | D16: =DB!D16 -> 40 | E16: =DB!E16 -> 15 | G16: =J16*D16 -> 23960 | H16: =J16*E16 -> 8985 | J16: =ROUNDUP((J8*2.1*0.257*0.9)*1.1,0) -> 599 | L16: =B16 -> ПАРКИНГ ЖИЛЬЕ | N16: =DB!N16 -> 0.7 | P16: =_xlfn.MINIFS('CF1'!$F22:$AS22,'CF1'!$F13:$AS13,">0") -> 4500 | Q16: =_xlfn.MAXIFS('CF1'!$F22:$AS22,'CF1'!$F13:$AS13,">0") -> 4500 | R16: 4500 | S16: ='CF1'!E31 -> 2695.5 | T16: =S16/$S$18 -> 0.063281145
B17: ПАРКИНГ ОФИС | C17: =DB!C17 -> 0 | D17: =DB!D17 -> 0 | E17: =DB!E17 -> 0 | G17: =J17*D17 -> 0 | H17: =J17*E17 -> 0 | J17: =IFERROR(ROUND(J10*C17,0),0) -> 0 | L17: =B17 -> ПАРКИНГ ОФИС | P17: =_xlfn.MINIFS('CF1'!$F23:$AS23,'CF1'!$F14:$AS14,">0") -> 0 | Q17: =_xlfn.MAXIFS('CF1'!$F23:$AS23,'CF1'!$F14:$AS14,">0") -> 0 | S17: ='CF1'!E32 -> 0 | T17: =S17/$S$18 -> 0
B18: ПЛОЩАДИ | F18: =F7 -> 96326 | G18: =G15+G7 -> 113543.18 | H18: =SUM(H7,H15) -> 71927.716 | I18: =I7 -> 0.29738243 | L18: ДОХОДЫ | S18: =SUM(S8:S17) -> 42595.626
B20: ИНВЕСТИЦИИ | L20: ФИНАНСИРОВАНИЕ | R20: СРОКИ
H21: руб./S общ. | I21: руб./S пол. | J21: млн.руб. | L21: КРЕДИТ | U21: кв.
B22: ВХОД | F22: =J22/M2 -> 1303.0054 | G22: за Га | H22: =IFERROR(J22/$G$18*1000000,0) -> 29194.583 | I22: =IFERROR(J22/$H$18*1000000,0) -> 46085.792 | J22: =-SUMIFS(DETAILS!$I$138:$I$146,DETAILS!$C$138:$C$146,'DB1'!F2)/10^6 -> 3314.8458 | L22: СТАВКИ | P22: ='TS1'!J85 -> 0.2 | R22: НАЧАЛО РАСЧЕТОВ | U22: =DB!U22 -> 45017
B23: FINDERS FEE | G23: % от входа | H23: =IFERROR(J23/$G$18*1000000,0) -> 0 | I23: =IFERROR(J23/$H$18*1000000,0) -> 0 | J23: =F23*J22 -> 0 | L23: СТАВКА бридж | N23: =DB!N23 -> 0.05 | P23: =P22+N23 -> 0.25 | R23: НАЧАЛО ПРОЕКТА | U23: =DB!U23 -> 45748
B24: ЗЕМЕЛЬНО-ПРАВОВЫЕ ВОПРОСЫ | H24: =J24/$G$18*1000000 -> 25151.91 | I24: =IFERROR(J24/$H$18*1000000,0) -> 39704.136 | J24: =SUM(J25:J29) -> 2855.8278 | L24: СТАВКА проектное фин-ие | N24: =DB!N24 -> 0.038 | P24: =P22+N24 -> 0.238 | R24: СРОК ИРД | U24: 6
B25: ВРИ | C25: =IF(D25>0,"со скидкой",0) -> 0 | D25: ='TS1'!E76 -> 0 | H25: =IFERROR(J25/$G$18*1000000,0) -> 40131.177 | I25: =IFERROR(J25/$H$18*1000000,0) -> 63350.009 | J25: ='TS1'!E77/10^6 -> 4556.6214 | L25: СТАВКА под эскроу | P25: =DB!P25 -> 0.038 | R25: РНС | U25: =EOMONTH(_xlfn.MINIFS('TS1'!$F$17:$AS$17,'TS1'!$F$25:$AS$25,">0"),-3)+1 -> 46296
B26: ЛЬГОТА | H26: =IFERROR(J26/$G$18*1000000,0) -> -40131.177 | I26: =IFERROR(J26/$H$18*1000000,0) -> -63350.009 | J26: =-'TS1'!C81/10^6 -> -4556.6214 | L26: КОМИССИИ | R26: СРОК СМР | U26: 12
B27: ПОКУПКА ЛЬГОТЫ | H27: =IFERROR(J27/$G$18*1000000,0) -> 24078.706 | I27: =IFERROR(J27/$H$18*1000000,0) -> 38010.005 | J27: ='TS1'!AA113+'TS1'!AC113 -> 2733.9729 | L27: РЕЗЕРВИРОВАНИЕ в банке | O27: =(P31+P32+P33)*P27 -> 166.85488 | P27: 0.005 | R27: РНВ | U27: =_xlfn.MINIFS('TS1'!$F$17:$AS$17,'TS1'!$F$16:$AS$16,'DB1'!R27) -> 47391
B28: РАССРОЧКА ВРИ | H28: =IFERROR(J28/$G$18*1000000,0) -> 0 | I28: =IFERROR(J28/$H$18*1000000,0) -> 0 | J28: ='TS1'!N67 -> 0 | L28: БРОКЕРИДЖ МРГ бридж | O28: =(P31+P32)*P28 -> 0 | P28: 0 | R28: ОКОНЧАНИЕ ПРОДАЖ | U28: =_xlfn.MAXIFS('TS1'!$F$36:$AS$36,'TS1'!$F$38:$AS$38,">0") -> 48121
B29: АРЕНДА ЗУ/НАЛОГ ЗУ | F29: =P49 -> АРЕНДА | H29: =IFERROR(J29/$G$18*1000000,0) -> 1073.2036 | I29: =IFERROR(J29/$H$18*1000000,0) -> 1694.1306 | J29: =-'CF1'!E62 -> 121.85494 | L29: БРОКЕРИДЖ МРГ проектное фин-ие | O29: =(P33+P32)*P29 -> 0 | R29: СРОК | U29: =(U28-U23)/365 -> 6.5013699
B30: ВЛОЖЕНИЯ В СТРОИТЕЛЬСТВО | H30: =IFERROR(J30/$G$18*1000000,0) -> 167175.27 | I30: =IFERROR(J30/$H$18*1000000,0) -> 263898.44 | J30: =SUM(J31:J42) -> 18981.612 | L30: ОБЪЕМ ФИНАНСИРОВАНИЯ
B31: ПРОЕКТИРОВАНИЕ (К+П+РД) | F31: 8000 | G31: м2 S общ. | H31: =IFERROR(J31/$G$18*1000000,0) -> 8000 | I31: =IFERROR(J31/$H$18*1000000,0) -> 12628.587 | J31: =$G$18*F31/10^6 -> 908.34544 | L31: ВХОД | O31: млн. руб. | P31: =-'CF1'!F60 -> 0 | R31: РЕЗУЛЬТАТ
B32: СОГЛАСОВАНИЯ | F32: 1000 | G32: м2 S общ. | H32: =IFERROR(J32/$G$18*1000000,0) -> 1000 | I32: =IFERROR(J32/$H$18*1000000,0) -> 1578.5734 | J32: =$G$18*F32/10^6 -> 113.54318 | L32: ДО РНС | O32: млн. руб. | P32: =-SUMIFS('CF1'!$F$50:$BM$50,'CF1'!$F$5:$BM$5,"<"&(EOMONTH('DB1'!U25,2)))-SUMIFS('CF1'!$F$59:$BM$59,'CF1'!$F$5:$BM$5,"<"&(EOMONTH('DB1'!U25,2)))-P31 -> 6630.9834 | U32: млн. руб.
B33: СМР жилье | D33: ДГП | E33: =-DETAILS!G288 -> 126510.6 | F33: =DB!F33 -> 137000 | G33: м2 S общ. | H33: =IFERROR(J33/($G$8+$G$9+$G$11+$G$16)*1000000,0) -> 137000 | I33: =IFERROR(J33/($H$8+$H$9+$H$11+$H$16)*1000000,0) -> 216264.56 | J33: =($G$16+$G$11+$G$9+$G$8)*F33/10^6 -> 15555.416 | L33: ПРОЕКТНОЕ ФИН-ИЕ (без учета реф бриджа) | O33: млн. руб. | P33: =-SUMIFS('CF1'!$F$50:$BM$50,'CF1'!$F$5:$BM$5,"<="&'DB1'!U27)-SUMIFS('CF1'!$F$59:$BM$59,'CF1'!$F$5:$BM$5,"<="&'DB1'!U27)-P31 -> 26739.992 | R33: ДОХОДЫ | U33: ='CF1'!E34 -> 42595.626
B34: СМР офисы | F34: 0 | G34: м2 S общ. | H34: =IFERROR(J34/($G$10+$G$17)*1000000,0) -> 0 | I34: =IFERROR(J34/($H$10+$H$17)*1000000,0) -> 0 | J34: =($G$10+$G$17)*F34/10^6 -> 0 | L34: % и КОМИСИИ банка | O34: млн. руб. | P34: ='CF1'!E90+'CF1'!E92+'CF1'!E98+'CF1'!E100+O27 -> 6741.8259 | R34: РАСХОДЫ НА ПРОДАЖУ | U34: ='CF1'!E50 -> -3239.0461
B35: СМР ТЦ | F35: 0 | G35: м2 S общ. | H35: =IFERROR(J35/$G$12*1000000,0) -> 0 | I35: =IFERROR(J35/$H$12*1000000,0) -> 0 | J35: =$G$12*F35/10^6 -> 0 | M35: бридж | O35: млн. руб. | P35: ='CF1'!E90+'CF1'!E92 -> 1068.6792 | R35: ИНВЕСТИЦИИ | U35: ='CF1'!E59 -> -25152.286
B36: СМР соц. объектов (компенсация) | F36: 0 | G36: м2 Sобщ. | H36: =IFERROR(J36/($G$7+$G$15)*1000000,0) -> 2593.5845 | I36: =IFERROR(J36/($H$8+$H$9+$H$11+$H$16)*1000000,0) -> 4094.1635 | J36: =-'CF1'!E68 -> 294.48383 | M36: проектное фин-ие | O36: млн. руб. | P36: ='CF1'!E98+'CF1'!E100 -> 5506.2918 | R36: ПРОЦЕНТЫ | U36: ='CF1'!E85+'CF1'!E91+'CF1'!E93+'CF1'!E99+'CF1'!E101+'CF1'!E104 -> -6991.9295
B37: ОТДЕЛКА жилье | F37: 0 | G37: м2 Sпол. | H37: =IFERROR(J37/($G$8+$G$9)*1000000,0) -> 0 | I37: =IFERROR(J37/($H$8+$H$9)*1000000,0) -> 0 | J37: =($H$8+$H$9)*F37/10^6 -> 0 | M37: комиссии банка | O37: млн. руб. | P37: ='CF1'!E103 -> 166.85488 | R37: НАЛОГИ | U37: ='CF1'!E111 -> -2244.3118
B38: СОДЕРЖАНИЕ ПЛОЩАДКИ | F38: 1000 | G38: м2 S общ. | H38: =IFERROR(J38/$G$18*1000000,0) -> 1000 | I38: =IFERROR(J38/$H$18*1000000,0) -> 1578.5734 | J38: =$G$18*F38/10^6 -> 113.54318 | L38: АКЦИОНЕРВНЫЕ ЗАЙМЫ | R38: ПРИБЫЛЬ ( в т ч SF МРГ) | U38: =SUM(U33:U37) -> 4968.0526
B39: СЕТИ | F39: =DB!F39 -> 5500 | G39: м2 Sобщ. | H39: =IFERROR(J39/$G$18*1000000,0) -> 5500 | I39: =IFERROR(J39/$H$18*1000000,0) -> 8682.1537 | J39: =$G$18*F39/10^6 -> 624.48749 | L39: СТАВКА ЗАЙМА | N39: 0.01 | P39: =P22+N39 -> 0.21 | R39: МАРЖИНАЛЬНОСТЬ до Н/О | U39: =(U38-'CF1'!E127)/U33 -> 0.16324891
B40: МОНИТОРИНГИ | D40: =MIN('CF1'!$F$72:$BM$72)/-3 -> 6.329691 | E40: млн. в мес. | F40: 2500 | G40: м2 Sобщ. | H40: =IFERROR(J40/$G$18*1000000,0) -> 2500 | I40: =IFERROR(J40/$H$18*1000000,0) -> 3946.4335 | J40: =$G$18*F40/10^6 -> 283.85795 | L40: ТЕЛО ЗАЙМА | O40: млн. руб. | P40: ='CF1'!E81 -> 382.3901 | R40: МАРЖ-СТЬ после Н/О | U40: =U38/U33 -> 0.11663293
B41: УПРАВЛЕНИЕ ПРОЕКТОМ | D41: =J41/('TS1'!D33*3) -> 12.1677 | E41: млн. в мес. | F41: =DB!F41 -> 0.04 | G41: % от расходов | H41: =IFERROR(J41/$G$18*1000000,0) -> 6429.8182 | I41: =IFERROR(J41/$H$18*1000000,0) -> 10149.94 | J41: =SUM($J$31:$J$40,J42)*$F41 -> 730.06201 | K41: =(J43+J53-U36-J50-J41)*3.5% -> 1194.9718 | L41: % | O41: млн. руб. | P41: ='CF1'!E84 -> 250.10365 | R41: IRR ПРОЕКТА (pre-tax) | U41: =IFERROR(POWER((1+IRR('CF1'!F76:BM76,0.01)),4)-1,0) -> 0.17185456
B42: НЕПРЕДВИДЕННЫЕ РАСХОДЫ | F42: 0.02 | G42: % от расходов | H42: =IFERROR(J42/$G$18*1000000,0) -> 3151.8717 | I42: =IFERROR(J42/$H$18*1000000,0) -> 4975.4608 | J42: =SUM($J$31:$J$40)*$F42 -> 357.87353 | K42: =J41/(J43+J53-U36-J50-J41) -> 0.021383074 | L42: ПРОЦЕНТЫ | N42: =P42/$G$18*1000000 -> 61579.476 | O42: =P42/$H$18*1000000 -> 97207.723 | P42: =-U36 -> 6991.9295 | R42: IRR ИНВЕСТОРА | U42: =IFERROR(POWER((1+IRR('CF1'!F171:BM171,0.01)),4)-1,0) -> 0.59770527
B43: ИНВЕСТИЦИИ | H43: =IFERROR(J43/$G$18*1000000,0) -> 221521.77 | I43: =IFERROR(J43/$H$18*1000000,0) -> 349688.37 | J43: =SUM(J22,J24,J30) -> 25152.286 | R43: LLSR | U43: =(-U33-U37)/(U36-P33) -> 1.1962353
B45: РАСХОДЫ НА ПРОДАЖУ
H46: руб./S общ. | I46: руб./S пол. | J46: млн.руб. | L46: ЗУ | R46: ДОХОДЫ УПРАВЛЯЮЩЕГО
B47: АХР | F47: 3 | G47: млн. р. в кв. | H47: =J47/$G$18*1000000 -> 686.96332 | I47: =J47/$H$18*1000000 -> 1084.422 | J47: =-'CF1'!$E$56 -> 78 | U47: млн. руб.
B48: РЕКЛАМА И МАРКЕТИНГ | F48: =DB!F48 -> 0.03 | G48: % от выручки | H48: =J48/$G$18*1000000 -> 11254.474 | I48: =J48/$H$18*1000000 -> 17766.014 | J48: =-'CF1'!$E$53 -> 1277.8688 | L48: КАДАСТРОВЫЙ НОМЕР | P48: =DB!$P$48 -> 77:02:0019010:102 | R48: =B41 -> УПРАВЛЕНИЕ ПРОЕКТОМ | U48: =J41 -> 730.06201
B49: БРОКЕРИДЖ | F49: =DB!F49 -> 0.03 | G49: % от выручки | H49: =J49/$G$18*1000000 -> 11254.474 | I49: =J49/$H$18*1000000 -> 17766.014 | J49: =-'CF1'!E51 -> 1277.8688 | L49: ВИД ПРАВА | N49: с | O49: 45748 | P49: АРЕНДА | R49: =B50 -> УПРАВЛЕНИЕ ПРОДАЖАМИ | U49: =J50 -> 511.14751
B50: УПРАВЛЕНИЕ ПРОДАЖАМИ | F50: 0.012 | G50: % от выручки | H50: =J50/$G$18*1000000 -> 4501.7896 | I50: =J50/$H$18*1000000 -> 7106.4054 | J50: =-'CF1'!$E$52 -> 511.14751 | L50: АРЕНДА / НАЛОГ ЗУ после ввода | O50: кв. | P50: =DB!P50 -> 2 | R50: ПРИВЛЕЧЕНИЕ КРЕДИТА | U50: =O28+O29 -> 0
B51: РЕГИСТРАЦИЯ ДОГОВОРОВ | F51: 30000 | G51: руб./лот | H51: =J51/$G$18*1000000 -> 675.91169 | I51: =J51/$H$18*1000000 -> 1066.9762 | J51: =-'CF1'!E55 -> 76.745163 | L51: ПЛОЩАДЬ ЗУ | O51: м2 | P51: =IF('МАСТЕР ПЛАН'!AE2=TRUE,'МАСТЕР ПЛАН'!AB8,IF('МАСТЕР ПЛАН'!AE11=TRUE,'МАСТЕР ПЛАН'!AB17,IF('МАСТЕР ПЛАН'!AE19=TRUE,'МАСТЕР ПЛАН'!AB25,IF('МАСТЕР ПЛАН'!AE28=TRUE,'МАСТЕР ПЛАН'!AA34*'МАСТЕР ПЛАН'!AB29,)))) -> 25440 | R51: FINDERS FEE | U51: =J23 -> 0
B52: АРЕНДА / НАЛОГ ЗУ | H52: =J52/$G$18*1000000 -> 153.38509 | I52: =J52/$H$18*1000000 -> 242.12963 | J52: =-'CF1'!E54 -> 17.415831 | L52: УДЕЛЬНАЯ ТЕКУЩАЯ КС | O52: руб. | P52: =DB!P52 -> 21593.22 | R52: SF | T52: 0.05 | U52: =U38*T52 -> 248.40263
B53: РАСХОДЫ | H53: =J53/$G$18*1000000 -> 28526.998 | I53: =J53/$H$18*1000000 -> 45031.96 | J53: =SUM(J47:J52) -> 3239.0461 | U53: =SUM(U48:U52) -> 1489.6122

Sheet DB2
B2: ПРОЕКТ | C2: =DB!C2 -> КАСАТКИНА | E2: ОЧЕРЕДЬ | F2: 2 | G2: ЗУ | H2: =P48 -> 77:02:0019010:102 | L2: ПЛОЩАДЬ ЗУ | M2: =P51/10000 -> 2.218 | O2: ПЛОТНОСТЬ | P2: =DB!P2 -> 35000 | Q2: АДРЕС | R2: =DB!R2 -> ул. КАСАТКИНА, ВЛ. 7 | U2: =DB!U2 -> 45826
B5: ТЭПы | F5: стены = | G5: =DB!$G$5 -> 0.07 | L5: ДОХОДЫ
F6: ГНС | G6: ОБЩАЯ ПЛОЩАДЬ | H6: ПОЛЕЗНАЯ ПЛОЩАДЬ | I6: LF, % | J6: КОЛ-ВО | P6: ЦЕНА → | Q6: ЦЕНА ← | R6: СРЕДНЯЯ ЦЕНА | S6: ДОХОД, млн. руб. | T6: % | U6: ОБЪЕМ ПРОДАЖ, в кв.
B7: НАЗЕМНАЯ ЧАСТЬ | E7: S лота | F7: =F8+F11 -> 81817.2 | G7: =SUM(G8:G14) -> 76089.996 | H7: =SUM(H8:H14) -> 53433.401 | I7: =IFERROR(1-H7/G7,"") -> 0.2977605 | L7: =B7 -> НАЗЕМНАЯ ЧАСТЬ | M7: старт | N7: % пост. | O7: дисконт
A8: ЖИЛАЯ | B8: КВАРТИРЫ | C8: =ROUND(J8*2.1,0) -> 2016 | D8: =F8/F7 -> 0.95520991 | E8: =DB!E8 -> 53 | F8: =IF('МАСТЕР ПЛАН'!$AE$2=TRUE,'МАСТЕР ПЛАН'!AC5,IF('МАСТЕР ПЛАН'!$AE$11=TRUE,'МАСТЕР ПЛАН'!AC14,IF('МАСТЕР ПЛАН'!$AE$19=TRUE,'МАСТЕР ПЛАН'!AC22,IF('МАСТЕР ПЛАН'!$AE$28=TRUE,'МАСТЕР ПЛАН'!AC31,0)))) -> 78152.6 | G8: =F8*(1-$G$5) -> 72681.918 | H8: =G8*(1-I8) -> 50877.343 | I8: =DB!$I8 -> 0.3 | J8: =IFERROR(ROUND(H8/E8,0),0) -> 960 | L8: =B8 -> КВАРТИРЫ | M8: =$U$25 -> 46661 | N8: 0.7 | O8: -0.17 | P8: =_xlfn.MINIFS('CF2'!$F17:$AS17,'CF2'!$F8:$AS8,">0") -> 522.9 | Q8: =_xlfn.MAXIFS('CF2'!$F17:$AS17,'CF2'!$F8:$AS8,">0") -> 710.55666 | R8: ='DB1'!R8 -> 630 | S8: ='CF2'!E26 -> 32052.726 | T8: =S8/$S$18 -> 0.88664763 | U8: 3000
A9: ЖИЛАЯ | B9: АПАРТАМЕНТЫ | D9: =F9/$F$7 -> 0 | E9: 60 | G9: =F9*(1-$G$5) -> 0 | H9: =G9*(1-I9) -> 0 | I9: =DB!$I9 -> 0 | J9: =IFERROR(ROUND(H9/E9,0),0) -> 0 | L9: =B9 -> АПАРТАМЕНТЫ | M9: =$U$25 -> 46661 | N9: 0.7 | P9: =_xlfn.MINIFS('CF2'!$F18:$AS18,'CF2'!$F9:$AS9,">0") -> 0 | Q9: =_xlfn.MAXIFS('CF2'!$F18:$AS18,'CF2'!$F9:$AS9,">0") -> 0 | S9: ='CF2'!E27 -> 0 | T9: =S9/$S$18 -> 0
A10: НЕЖИЛАЯ | B10: ОФИСЫ | D10: =F10/$F$7 -> 0 | E10: 100 | G10: =F10*(1-$G$5) -> 0 | H10: =G10*(1-I10) -> 0 | I10: =DB!$I10 -> 0 | J10: =IFERROR(ROUND(H10/E10,0),0) -> 0 | L10: =B10 -> ОФИСЫ | M10: =$U$25 -> 46661 | N10: 0.7 | P10: =_xlfn.MINIFS('CF2'!$F19:$AS19,'CF2'!$F10:$AS10,">0") -> 0 | Q10: =_xlfn.MAXIFS('CF2'!$F19:$AS19,'CF2'!$F10:$AS10,">0") -> 0 | S10: ='CF2'!E28 -> 0 | T10: =S10/$S$18 -> 0
A11: ТОРГОВЛЯ | B11: РИТЕЙЛ | D11: =F11/F7 -> 0.044790093 | E11: 100 | F11: =IF('МАСТЕР ПЛАН'!$AE$2=TRUE,'МАСТЕР ПЛАН'!AC6,IF('МАСТЕР ПЛАН'!$AE$11=TRUE,'МАСТЕР ПЛАН'!AC15,IF('МАСТЕР ПЛАН'!$AE$19=TRUE,'МАСТЕР ПЛАН'!AC23,IF('МАСТЕР ПЛАН'!$AE$28=TRUE,'МАСТЕР ПЛАН'!AC32,0)))) -> 3664.6 | G11: =F11*(1-$G$5) -> 3408.078 | H11: =G11*(1-I11) -> 2556.0585 | I11: =DB!$I11 -> 0.25 | J11: =IFERROR(ROUND(H11/E11,0),0) -> 26 | L11: =B11 -> РИТЕЙЛ | M11: =DB!$M$11 -> 1 | N11: 1 | O11: =Q11/P11-1 -> 0 | P11: =_xlfn.MINIFS('CF2'!$F20:$AS20,'CF2'!$F11:$AS11,">0") -> 700 | Q11: =_xlfn.MAXIFS('CF2'!$F20:$AS20,'CF2'!$F11:$AS11,">0") -> 700 | R11: 700 | S11: ='CF2'!E29 -> 1789.2409 | T11: =S11/$S$18 -> 0.04949427
A12: ТОРГОВЛЯ | B12: ТЦ | D12: =F12/$F$7 -> 0 | E12: 100 | G12: =F12*(1-$G$5) -> 0 | H12: =G12*(1-I12) -> 0 | I12: =DB!$I12 -> 0 | J12: =IFERROR(ROUND(H12/E12,0),0) -> 0 | L12: =B12 -> ТЦ | M12: =DB!$M$12 -> 0 | P12: =_xlfn.MINIFS('CF2'!$F21:$AS21,'CF2'!$F12:$AS12,">0") -> 0 | Q12: =_xlfn.MAXIFS('CF2'!$F21:$AS21,'CF2'!$F12:$AS12,">0") -> 0 | S12: ='CF2'!E30 -> 0 | T12: =S12/$S$18 -> 0
A13: ='TS2'!B68 -> СОЦИАЛКА | B13: ШКОЛА | C13: мест | D13: 1000 | G13: =F13*(1-$G$5) -> 0 | L13: =B13 -> ШКОЛА
A14: =A13 -> СОЦИАЛКА | B14: ДОУ | C14: мест | G14: =F14*(1-$G$5) -> 0 | L14: =B14 -> ДОУ
B15: ПОДЗЕМНАЯ ЧАСТЬ | D15: S общ. | E15: S пол. | G15: =G16 -> 20520 | H15: =H16 -> 7695 | L15: =B15 -> ПОДЗЕМНАЯ ЧАСТЬ
B16: ПАРКИНГ ЖИЛЬЕ | C16: =J16/J8 -> 0.534375 | D16: =DB!D16 -> 40 | E16: =DB!E16 -> 15 | G16: =J16*D16 -> 20520 | H16: =J16*E16 -> 7695 | J16: =ROUNDUP((J8*2.1*0.257*0.9)*1.1,0) -> 513 | L16: =B16 -> ПАРКИНГ ЖИЛЬЕ | N16: =DB!N16 -> 0.7 | P16: =_xlfn.MINIFS('CF2'!$F22:$AS22,'CF2'!$F13:$AS13,">0") -> 4500 | Q16: =_xlfn.MAXIFS('CF2'!$F22:$AS22,'CF2'!$F13:$AS13,">0") -> 4500 | R16: ='DB1'!R16 -> 4500 | S16: ='CF2'!E31 -> 2308.5 | T16: =S16/$S$18 -> 0.063858097
B17: ПАРКИНГ ОФИС | C17: =DB!C17 -> 0 | D17: =DB!D17 -> 0 | E17: =DB!E17 -> 0 | G17: =J17*D17 -> 0 | H17: =J17*E17 -> 0 | J17: =IFERROR(ROUND(J10*C17,0),0) -> 0 | L17: =B17 -> ПАРКИНГ ОФИС | P17: =_xlfn.MINIFS('CF2'!$F23:$AS23,'CF2'!$F14:$AS14,">0") -> 0 | Q17: =_xlfn.MAXIFS('CF2'!$F23:$AS23,'CF2'!$F14:$AS14,">0") -> 0 | S17: ='CF2'!E32 -> 0 | T17: =S17/$S$18 -> 0
B18: ПЛОЩАДИ | F18: =F7 -> 81817.2 | G18: =G15+G7 -> 96609.996 | H18: =SUM(H7,H15) -> 61128.401 | I18: =I7 -> 0.2977605 | L18: ДОХОДЫ | S18: =SUM(S8:S17) -> 36150.467
B20: ИНВЕСТИЦИИ | L20: ФИНАНСИРОВАНИЕ | R20: СРОКИ
H21: руб./S общ. | I21: руб./S пол. | J21: млн.руб. | L21: КРЕДИТ | U21: кв.
B22: ВХОД | F22: =J22/M2 -> 237.37601 | G22: за Га | H22: =IFERROR(J22/$G$18*1000000,0) -> 5449.7466 | I22: =IFERROR(J22/$H$18*1000000,0) -> 8613.0177 | J22: =-SUMIFS(DETAILS!$I$138:$I$146,DETAILS!$C$138:$C$146,'DB2'!F2)/10^6 -> 526.5 | L22: СТАВКИ | P22: ='TS2'!J85 -> 0.2 | R22: НАЧАЛО РАСЧЕТОВ | U22: =DB!U22 -> 45017
B23: FINDERS FEE | G23: % от входа | H23: =IFERROR(J23/$G$18*1000000,0) -> 0 | I23: =IFERROR(J23/$H$18*1000000,0) -> 0 | J23: =F23*J22 -> 0 | L23: СТАВКА бридж | N23: =DB!N23 -> 0.05 | P23: =P22+N23 -> 0.25 | R23: НАЧАЛО ПРОЕКТА | U23: =DB!U23 -> 45748
B24: ЗЕМЕЛЬНО-ПРАВОВЫЕ ВОПРОСЫ | H24: =J24/$G$18*1000000 -> 21420.005 | I24: =IFERROR(J24/$H$18*1000000,0) -> 33853.111 | J24: =SUM(J25:J29) -> 2069.3866 | L24: СТАВКА проектное фин-ие | N24: =DB!N24 -> 0.038 | P24: =P22+N24 -> 0.238 | R24: СРОК ИРД | U24: =5+4+1 -> 10
B25: ВРИ | C25: =IF(D25>0,"со скидкой",0) -> 0 | D25: ='TS2'!E76 -> 0 | H25: =IFERROR(J25/$G$18*1000000,0) -> 40386.325 | I25: =IFERROR(J25/$H$18*1000000,0) -> 63828.312 | J25: ='TS2'!E77/10^6 -> 3901.7227 | L25: СТАВКА под эскроу | P25: =DB!P25 -> 0.038 | R25: РНС | U25: =EOMONTH(_xlfn.MINIFS('TS2'!$F$17:$AS$17,'TS2'!$F$25:$AS$25,">0"),-3)+1 -> 46661
B26: ЛЬГОТА | H26: =IFERROR(J26/$G$18*1000000,0) -> -40386.325 | I26: =IFERROR(J26/$H$18*1000000,0) -> -63828.312 | J26: =-'TS2'!C81/10^6 -> -3901.7227 | L26: КОМИССИИ | R26: СРОК СМР | U26: 12
B27: ПОКУПКА ЛЬГОТЫ | H27: =IFERROR(J27/$G$18*1000000,0) -> 20239.333 | I27: =IFERROR(J27/$H$18*1000000,0) -> 31987.126 | J27: ='TS2'!AA113+'TS2'!AC113 -> 1955.3219 | L27: РЕЗЕРВИРОВАНИЕ в банке | O27: =(P31+P32+P33)*P27 -> 136.53967 | P27: 0.005 | R27: РНВ | U27: =_xlfn.MINIFS('TS2'!$F$17:$AS$17,'TS2'!$F$16:$AS$16,'DB2'!R27) -> 47756
B28: РАССРОЧКА ВРИ | H28: =IFERROR(J28/$G$18*1000000,0) -> 0 | I28: =IFERROR(J28/$H$18*1000000,0) -> 0 | J28: ='TS2'!N67 -> 0 | L28: БРОКЕРИДЖ МРГ бридж | O28: =(P31+P32)*P28 -> 0 | P28: 0 | R28: ОКОНЧАНИЕ ПРОДАЖ | U28: =_xlfn.MAXIFS('TS2'!$F$36:$AS$36,'TS2'!$F$38:$AS$38,">0") -> 48213
B29: АРЕНДА ЗУ/НАЛОГ ЗУ | F29: =P49 -> АРЕНДА | H29: =IFERROR(J29/$G$18*1000000,0) -> 1180.6715 | I29: =IFERROR(J29/$H$18*1000000,0) -> 1865.9849 | J29: =-'CF2'!E62 -> 114.06467 | L29: БРОКЕРИДЖ МРГ проектное фин-ие | O29: =(P33+P32)*P29 -> 0 | R29: СРОК | U29: =(U28-U23)/365 -> 6.7534247
B30: ВЛОЖЕНИЯ В СТРОИТЕЛЬСТВО | H30: =IFERROR(J30/$G$18*1000000,0) -> 207044.14 | I30: =IFERROR(J30/$H$18*1000000,0) -> 327221.6 | J30: =SUM(J31:J42) -> 20002.533 | L30: ОБЪЕМ ФИНАНСИРОВАНИЯ
B31: ПРОЕКТИРОВАНИЕ (П+РД) | F31: 6500 | G31: м2 S общ. | H31: =IFERROR(J31/$G$18*1000000,0) -> 6500 | I31: =IFERROR(J31/$H$18*1000000,0) -> 10272.884 | J31: =$G$18*F31/10^6 -> 627.96497 | L31: ВХОД | O31: млн. руб. | P31: =-'CF2'!F60 -> 0 | R31: РЕЗУЛЬТАТ
B32: СОГЛАСОВАНИЯ | F32: 1000 | G32: м2 S общ. | H32: =IFERROR(J32/$G$18*1000000,0) -> 1000 | I32: =IFERROR(J32/$H$18*1000000,0) -> 1580.4437 | J32: =$G$18*F32/10^6 -> 96.609996 | L32: ДО РНС | O32: млн. руб. | P32: =-SUMIFS('CF2'!$F$50:$BM$50,'CF2'!$F$5:$BM$5,"<"&(EOMONTH('DB2'!U25,2)))-SUMIFS('CF2'!$F$59:$BM$59,'CF2'!$F$5:$BM$5,"<"&(EOMONTH('DB2'!U25,2)))-P31 -> 3092.0443 | U32: млн. руб.
B33: СМР жилье | D33: ДГП | E33: =-DETAILS!G308 -> 128357 | F33: =DB!F33 -> 137000 | G33: м2 S общ. | H33: =IFERROR(J33/($G$8+$G$9+$G$11+$G$16)*1000000,0) -> 137000 | I33: =IFERROR(J33/($H$8+$H$9+$H$11+$H$16)*1000000,0) -> 216520.79 | J33: =($G$16+$G$11+$G$9+$G$8)*F33/10^6 -> 13235.569 | L33: ПРОЕКТНОЕ ФИН-ИЕ (без учета реф бриджа) | O33: млн. руб. | P33: =-SUMIFS('CF2'!$F$50:$BM$50,'CF2'!$F$5:$BM$5,"<="&'DB2'!U27)-SUMIFS('CF2'!$F$59:$BM$59,'CF2'!$F$5:$BM$5,"<="&'DB2'!U27)-P31 -> 24215.89 | R33: ДОХОДЫ | U33: ='CF2'!E34 -> 36150.467
B34: СМР офисы | F34: 0 | G34: м2 S общ. | H34: =IFERROR(J34/($G$10+$G$17)*1000000,0) -> 0 | I34: =IFERROR(J34/($H$10+$H$17)*1000000,0) -> 0 | J34: =($G$10+$G$17)*F34/10^6 -> 0 | L34: % и КОМИСИИ банка | O34: млн. руб. | P34: ='CF2'!E90+'CF2'!E92+'CF2'!E98+'CF2'!E100+O27 -> 3637.9856 | R34: РАСХОДЫ НА ПРОДАЖУ | U34: ='CF2'!E50 -> -2760.3491
B35: СМР ТЦ | F35: 0 | G35: м2 S общ. | H35: =IFERROR(J35/$G$12*1000000,0) -> 0 | I35: =IFERROR(J35/$H$12*1000000,0) -> 0 | J35: =$G$12*F35/10^6 -> 0 | M35: бридж | O35: млн. руб. | P35: ='CF2'!E90+'CF2'!E92 -> 383.35912 | R35: ИНВЕСТИЦИИ | U35: ='CF2'!E59 -> -22598.42
B36: СМР соц. объектов (компенсация) | F36: 0 | G36: м2 Sобщ. | H36: =IFERROR(J36/($G$7+$G$15)*1000000,0) -> 42177.355 | I36: =IFERROR(J36/($H$8+$H$9+$H$11+$H$16)*1000000,0) -> 66658.935 | J36: =-'CF2'!E68 -> 4074.7541 | M36: проектное фин-ие | O36: млн. руб. | P36: ='CF2'!E98+'CF2'!E100 -> 3118.0868 | R36: ПРОЦЕНТЫ | U36: ='CF2'!E85+'CF2'!E91+'CF2'!E93+'CF2'!E99+'CF2'!E101+'CF2'!E104 -> -3780.1862
B37: ОТДЕЛКА жилье | F37: 0 | G37: м2 Sпол. | H37: =IFERROR(J37/($G$8+$G$9)*1000000,0) -> 0 | I37: =IFERROR(J37/($H$8+$H$9)*1000000,0) -> 0 | J37: =($H$8+$H$9)*F37/10^6 -> 0 | M37: комиссии банка | O37: млн. руб. | P37: ='CF2'!E103 -> 136.53967 | R37: НАЛОГИ | U37: ='CF2'!E111 -> -2634.0133
B38: СЕТИ | F38: =DB!F39 -> 5500 | G38: м2 Sобщ. | H38: =IFERROR(J38/$G$18*1000000,0) -> 5500 | I38: =IFERROR(J38/$H$18*1000000,0) -> 8692.4403 | J38: =$G$18*F38/10^6 -> 531.35498 | L38: АКЦИОНЕРВНЫЕ ЗАЙМЫ | R38: ПРИБЫЛЬ ( в т ч SF МРГ) | U38: =SUM(U33:U37) -> 4377.4982
B39: СОДЕРЖАНИЕ ПЛОЩАДКИ | F39: 500 | G39: м2 S общ. | H39: =IFERROR(J39/$G$18*1000000,0) -> 500 | I39: =IFERROR(J39/$H$18*1000000,0) -> 790.22185 | J39: =$G$18*F39/10^6 -> 48.304998 | L39: СТАВКА ЗАЙМА | N39: 0.01 | P39: =P22+N39 -> 0.21 | R39: МАРЖИНАЛЬНОСТЬ до Н/О | U39: =(U38-'CF2'!E127)/U33 -> 0.1896068
B40: МОНИТОРИНГИ | D40: =MIN('CF2'!$F$72:$BM$72)/-3 -> 5.2442305 | E40: млн. в мес. | F40: 2500 | G40: м2 Sобщ. | H40: =IFERROR(J40/$G$18*1000000,0) -> 2500 | I40: =IFERROR(J40/$H$18*1000000,0) -> 3951.1092 | J40: =$G$18*F40/10^6 -> 241.52499 | L40: ТЕЛО ЗАЙМА | O40: млн. руб. | P40: ='CF2'!E81 -> 213.9543 | R40: МАРЖ-СТЬ после Н/О | U40: =U38/U33 -> 0.12109106
B41: УПРАВЛЕНИЕ ПРОЕКТОМ | D41: =J41/('TS2'!D33*3) -> 10.685114 | E41: млн. в мес. | F41: =DB!F41 -> 0.04 | G41: % от расходов | H41: =IFERROR(J41/$G$18*1000000,0) -> 7963.2361 | I41: =IFERROR(J41/$H$18*1000000,0) -> 12585.446 | J41: =SUM($J$31:$J$40,J42)*$F41 -> 769.32821 | K41: =(J43+J53-U36-J50-J41)*3.5% -> 977.75375 | L41: % | O41: млн. руб. | P41: ='CF2'!E84 -> 142.20064 | R41: IRR ПРОЕКТА (pre-tax) | U41: =POWER((1+IRR('CF2'!F76:BM76,0.01)),4)-1 -> 0.18141414
B42: НЕПРЕДВИДЕННЫЕ РАСХОДЫ | F42: 0.02 | G42: % от расходов | H42: =IFERROR(J42/$G$18*1000000,0) -> 3903.5471 | I42: =IFERROR(J42/$H$18*1000000,0) -> 6169.3364 | J42: =SUM($J$31:$J$40)*$F42 -> 377.12167 | K42: =J41/(J43+J53-U36-J50-J41) -> 0.02753913 | L42: ПРОЦЕНТЫ | N42: =P42/$G$18*1000000 -> 39128.314 | O42: =P42/$H$18*1000000 -> 61840.097 | P42: =-U36 -> 3780.1862 | R42: IRR ИНВЕСТОРА | U42: =IFERROR(POWER((1+IRR('CF2'!F171:BM171,0.01)),4)-1,0) -> 0.68880863
B43: ИНВЕСТИЦИИ | H43: =IFERROR(J43/$G$18*1000000,0) -> 233913.89 | I43: =IFERROR(J43/$H$18*1000000,0) -> 369687.73 | J43: =SUM(J22,J24,J30) -> 22598.42 | R43: LLSR | U43: =(-U33-U37)/(U36-P33) -> 1.197184 | W43: 0.85
U44: ='DB1'!U43 -> 1.1962353
B45: РАСХОДЫ НА ПРОДАЖУ
H46: руб./S общ. | I46: руб./S пол. | J46: млн.руб. | L46: ЗУ | R46: ДОХОДЫ УПРАВЛЯЮЩЕГО
B47: АХР | F47: 3 | G47: млн. р. в кв. | H47: =J47/$G$18*1000000 -> 838.42256 | I47: =J47/$H$18*1000000 -> 1325.0796 | J47: =-'CF2'!$E$56 -> 81 | U47: млн. руб.
B48: РЕКЛАМА И МАРКЕТИНГ | F48: =DB!F48 -> 0.03 | G48: % от выручки | H48: =J48/$G$18*1000000 -> 11225.691 | I48: =J48/$H$18*1000000 -> 17741.573 | J48: =-'CF2'!$E$53 -> 1084.514 | L48: КАДАСТРОВЫЙ НОМЕР | P48: =DB!$P$48 -> 77:02:0019010:102 | R48: =B41 -> УПРАВЛЕНИЕ ПРОЕКТОМ | U48: =J41 -> 769.32821
B49: БРОКЕРИДЖ | F49: =DB!F49 -> 0.03 | G49: % от выручки | H49: =J49/$G$18*1000000 -> 11225.691 | I49: =J49/$H$18*1000000 -> 17741.573 | J49: =-'CF2'!E51 -> 1084.514 | L49: ВИД ПРАВА | N49: с | O49: 45748 | P49: АРЕНДА | R49: =B50 -> УПРАВЛЕНИЕ ПРОДАЖАМИ | U49: =J50 -> 433.8056
B50: УПРАВЛЕНИЕ ПРОДАЖАМИ | F50: 0.012 | G50: % от выручки | H50: =J50/$G$18*1000000 -> 4490.2766 | I50: =J50/$H$18*1000000 -> 7096.6293 | J50: =-'CF2'!$E$52 -> 433.8056 | L50: АРЕНДА / НАЛОГ ЗУ после ввода | O50: кв. | P50: =DB!P50 -> 2 | R50: ПРИВЛЕЧЕНИЕ КРЕДИТА | U50: =O28+O29 -> 0
B51: РЕГИСТРАЦИЯ ДОГОВОРОВ | F51: 30000 | G51: руб./лот | H51: =J51/$G$18*1000000 -> 634.83474 | I51: =J51/$H$18*1000000 -> 1003.3206 | J51: =-'CF2'!E55 -> 61.331381 | L51: ПЛОЩАДЬ ЗУ | O51: м2 | P51: =IF('МАСТЕР ПЛАН'!AE2=TRUE,'МАСТЕР ПЛАН'!AC8,IF('МАСТЕР ПЛАН'!AE11=TRUE,'МАСТЕР ПЛАН'!AC17,IF('МАСТЕР ПЛАН'!AE19=TRUE,'МАСТЕР ПЛАН'!AC25,IF('МАСТЕР ПЛАН'!AE28=TRUE,'МАСТЕР ПЛАН'!AA34*'МАСТЕР ПЛАН'!AC29,0)))) -> 22180 | R51: FINDERS FEE | U51: =J23 -> 0
B52: АРЕНДА / НАЛОГ ЗУ | H52: =J52/$G$18*1000000 -> 157.16888 | I52: =J52/$H$18*1000000 -> 248.39657 | J52: =-'CF2'!E54 -> 15.184085 | L52: УДЕЛЬНАЯ ТЕКУЩАЯ КС | O52: руб. | P52: =DB!P52 -> 21593.22 | R52: SF | T52: 0.05 | U52: =U38*T52 -> 218.87491
B53: РАСХОДЫ | H53: =J53/$G$18*1000000 -> 28572.086 | I53: =J53/$H$18*1000000 -> 45156.572 | J53: =SUM(J47:J52) -> 2760.3491 | U53: =SUM(U48:U52) -> 1422.0087

Sheet CF
B2: CF проекта
B4: 1 оч | F4: ='CF1'!F4 | G4: ='CF1'!G4 | H4: ='CF1'!H4 | I4: ='CF1'!I4 | J4: ='CF1'!J4 | K4: ='CF1'!K4 | L4: ='CF1'!L4 | M4: ='CF1'!M4 | ... BM4: ='CF1'!BM4 -> 0
B5: 2 оч | F5: ='CF2'!F3 | G5: ='CF2'!G3 | H5: ='CF2'!H3 | I5: ='CF2'!I3 | J5: ='CF2'!J3 | K5: ='CF2'!K3 | L5: ='CF2'!L3 | M5: ='CF2'!M3 | ... BM5: ='CF2'!BM3
B6: СТАТЬЯ | E6: ВСЕГО | F6: =EOMONTH('DB1'!$U$22,2) -> 45107 | G6: =EOMONTH(F6,3) -> 45199 | H6: =EOMONTH(G6,3) -> 45291 | I6: =EOMONTH(H6,3) -> 45382 | J6: =EOMONTH(I6,3) -> 45473 | K6: =EOMONTH(J6,3) -> 45565 | L6: =EOMONTH(K6,3) -> 45657 | M6: =EOMONTH(L6,3) -> 45747 | N6: =EOMONTH(M6,3) -> 45838 | ... BM6: =EOMONTH(BL6,3) -> 50495
F7: =CONCATENATE(IF(MONTH(F6)<=3,"1",IF(MONTH(F6)<=6,"2",IF(MONTH(F6)<=9,"3","4"))),"Q",YEAR(F6)) -> 2Q2023 | G7: =CONCATENATE(IF(MONTH(G6)<=3,"1",IF(MONTH(G6)<=6,"2",IF(MONTH(G6)<=9,"3","4"))),"Q",YEAR(G6)) -> 3Q2023 | H7: =CONCATENATE(IF(MONTH(H6)<=3,"1",IF(MONTH(H6)<=6,"2",IF(MONTH(H6)<=9,"3","4"))),"Q",YEAR(H6)) -> 4Q2023 | I7: =CONCATENATE(IF(MONTH(I6)<=3,"1",IF(MONTH(I6)<=6,"2",IF(MONTH(I6)<=9,"3","4"))),"Q",YEAR(I6)) -> 1Q2024 | J7: =CONCATENATE(IF(MONTH(J6)<=3,"1",IF(MONTH(J6)<=6,"2",IF(MONTH(J6)<=9,"3","4"))),"Q",YEAR(J6)) -> 2Q2024 | K7: =CONCATENATE(IF(MONTH(K6)<=3,"1",IF(MONTH(K6)<=6,"2",IF(MONTH(K6)<=9,"3","4"))),"Q",YEAR(K6)) -> 3Q2024 | L7: =CONCATENATE(IF(MONTH(L6)<=3,"1",IF(MONTH(L6)<=6,"2",IF(MONTH(L6)<=9,"3","4"))),"Q",YEAR(L6)) -> 4Q2024 | M7: =CONCATENATE(IF(MONTH(M6)<=3,"1",IF(MONTH(M6)<=6,"2",IF(MONTH(M6)<=9,"3","4"))),"Q",YEAR(M6)) -> 1Q2025 | ... BM7: =CONCATENATE(IF(MONTH(BM6)<=3,"1",IF(MONTH(BM6)<=6,"2",IF(MONTH(BM6)<=9,"3","4"))),"Q",YEAR(BM6)) -> 1Q2038
B8: КОНТРАКТАЦИЯ | D8: м2
B9: ='DB1'!B8 -> КВАРТИРЫ | D9: м2 | E9: =SUM(F9:BM9) -> 110302.71 | F9: =F10+F11 -> 0 | G9: =G10+G11 -> 0 | H9: =H10+H11 -> 0 | I9: =I10+I11 -> 0 | J9: =J10+J11 -> 0 | K9: =K10+K11 -> 0 | L9: =L10+L11 -> 0 | M9: =M10+M11 -> 0 | ... BM9: =BM10+BM11 -> 0
C10: 1 оч | D10: м2 | E10: =SUM(F10:BM10) -> 59425.363 | F10: ='CF1'!F8 -> 0 | G10: ='CF1'!G8 -> 0 | H10: ='CF1'!H8 -> 0 | I10: ='CF1'!I8 -> 0 | J10: ='CF1'!J8 -> 0 | K10: ='CF1'!K8 -> 0 | L10: ='CF1'!L8 -> 0 | M10: ='CF1'!M8 -> 0 | ... BM10: ='CF1'!BM8 -> 0
C11: 2 оч | D11: м2 | E11: =SUM(F11:BM11) -> 50877.343 | F11: ='CF2'!F8 -> 0 | G11: ='CF2'!G8 -> 0 | H11: ='CF2'!H8 -> 0 | I11: ='CF2'!I8 -> 0 | J11: ='CF2'!J8 -> 0 | K11: ='CF2'!K8 -> 0 | L11: ='CF2'!L8 -> 0 | M11: ='CF2'!M8 -> 0 | ... BM11: ='CF2'!BM8 -> 0
B12: ='DB1'!B9 -> АПАРТАМЕНТЫ | D12: м2 | E12: =SUM(F12:BM12) -> 0 | V12: ='CF2'!V9 -> 0
B13: ='DB1'!B10 -> ОФИСЫ | D13: м2 | E13: =SUM(F13:BM13) -> 0 | V13: ='CF2'!V10 -> 0
B14: ='DB1'!B11 -> РИТЕЙЛ | D14: м2 | E14: =SUM(F14:BM14) -> 6073.4115 | F14: =F15+F16 -> 0 | G14: =G15+G16 -> 0 | H14: =H15+H16 -> 0 | I14: =I15+I16 -> 0 | J14: =J15+J16 -> 0 | K14: =K15+K16 -> 0 | L14: =L15+L16 -> 0 | M14: =M15+M16 -> 0 | ... BM14: =BM15+BM16 -> 0
C15: 1 оч | D15: м2 | E15: =SUM(F15:BM15) -> 3517.353 | F15: ='CF1'!F11 -> 0 | G15: ='CF1'!G11 -> 0 | H15: ='CF1'!H11 -> 0 | I15: ='CF1'!I11 -> 0 | J15: ='CF1'!J11 -> 0 | K15: ='CF1'!K11 -> 0 | L15: ='CF1'!L11 -> 0 | M15: ='CF1'!M11 -> 0 | ... BM15: ='CF1'!BM11 -> 0
C16: 2 оч | D16: м2 | E16: =SUM(F16:BM16) -> 2556.0585 | F16: ='CF2'!F11 -> 0 | G16: ='CF2'!G11 -> 0 | H16: ='CF2'!H11 -> 0 | I16: ='CF2'!I11 -> 0 | J16: ='CF2'!J11 -> 0 | K16: ='CF2'!K11 -> 0 | L16: ='CF2'!L11 -> 0 | M16: ='CF2'!M11 -> 0 | ... BM16: ='CF2'!BM11 -> 0
B17: ='DB1'!B12 -> ТЦ | D17: м2 | E17: =SUM(F17:BM17) -> 0
B18: ='DB1'!B16 -> ПАРКИНГ ЖИЛЬЕ | D18: шт. | E18: =SUM(F18:BM18) -> 1112 | F18: =F19+F20 -> 0 | G18: =G19+G20 -> 0 | H18: =H19+H20 -> 0 | I18: =I19+I20 -> 0 | J18: =J19+J20 -> 0 | K18: =K19+K20 -> 0 | L18: =L19+L20 -> 0 | M18: =M19+M20 -> 0 | ... BM18: =BM19+BM20 -> 0
C19: 1 оч | D19: шт. | E19: =SUM(F19:BM19) -> 599 | F19: ='CF1'!F13 -> 0 | G19: ='CF1'!G13 -> 0 | H19: ='CF1'!H13 -> 0 | I19: ='CF1'!I13 -> 0 | J19: ='CF1'!J13 -> 0 | K19: ='CF1'!K13 -> 0 | L19: ='CF1'!L13 -> 0 | M19: ='CF1'!M13 -> 0 | ... BM19: ='CF1'!BM13 -> 0
C20: 2 оч | D20: шт. | E20: =SUM(F20:BM20) -> 513 | F20: ='CF2'!F13 -> 0 | G20: ='CF2'!G13 -> 0 | H20: ='CF2'!H13 -> 0 | I20: ='CF2'!I13 -> 0 | J20: ='CF2'!J13 -> 0 | K20: ='CF2'!K13 -> 0 | L20: ='CF2'!L13 -> 0 | M20: ='CF2'!M13 -> 0 | ... BM20: ='CF2'!BM13 -> 0
B21: ='DB1'!B17 -> ПАРКИНГ ОФИС | D21: шт. | E21: =SUM(F21:BM21) -> 0
B23: ЦЕНЫ | D23: тыс. руб. | E23: =IFERROR(E38/E8*1000,0) -> 0
B24: =B9 -> КВАРТИРЫ | D24: тыс. руб. | E24: =IFERROR(E39/E9*1000,0) -> 630 | F24: =IFERROR(F39/F9,0)*1000 -> 0 | G24: =IFERROR(G39/G9,0)*1000 -> 0 | H24: =IFERROR(H39/H9,0)*1000 -> 0 | I24: =IFERROR(I39/I9,0)*1000 -> 0 | J24: =IFERROR(J39/J9,0)*1000 -> 0 | K24: =IFERROR(K39/K9,0)*1000 -> 0 | L24: =IFERROR(L39/L9,0)*1000 -> 0 | M24: =IFERROR(M39/M9,0)*1000 -> 0 | ... BM24: =IFERROR(BM39/BM9,0)*1000 -> 0
C25: 1 оч | D25: тыс. руб. | E25: =IFERROR(E40/E10*1000,0) -> 630 | F25: ='CF1'!F17 -> 0 | G25: ='CF1'!G17 -> 0 | H25: ='CF1'!H17 -> 0 | I25: ='CF1'!I17 -> 0 | J25: ='CF1'!J17 -> 0 | K25: ='CF1'!K17 -> 0 | L25: ='CF1'!L17 -> 0 | M25: ='CF1'!M17 -> 0 | ... BM25: ='CF1'!BM17 -> 0
C26: 2 оч | D26: тыс. руб. | E26: =IFERROR(E41/E11*1000,0) -> 630 | F26: ='CF2'!F17 -> 0 | G26: ='CF2'!G17 -> 0 | H26: ='CF2'!H17 -> 0 | I26: ='CF2'!I17 -> 0 | J26: ='CF2'!J17 -> 0 | K26: ='CF2'!K17 -> 0 | L26: ='CF2'!L17 -> 0 | M26: ='CF2'!M17 -> 0 | ... BM26: ='CF2'!BM17 -> 0
B27: =B12 -> АПАРТАМЕНТЫ | D27: тыс. руб. | E27: =IFERROR(E42/E12*1000,0) -> 0
B28: =B13 -> ОФИСЫ | D28: тыс. руб. | E28: =IFERROR(E43/E13*1000,0) -> 0
B29: =B14 -> РИТЕЙЛ | D29: тыс. руб. | E29: =IFERROR(E44/E14*1000,0) -> 700 | F29: =IFERROR(F44/F14,0)*1000 -> 0 | G29: =IFERROR(G44/G14,0)*1000 -> 0 | H29: =IFERROR(H44/H14,0)*1000 -> 0 | I29: =IFERROR(I44/I14,0)*1000 -> 0 | J29: =IFERROR(J44/J14,0)*1000 -> 0 | K29: =IFERROR(K44/K14,0)*1000 -> 0 | L29: =IFERROR(L44/L14,0)*1000 -> 0 | M29: =IFERROR(M44/M14,0)*1000 -> 0 | ... BM29: =IFERROR(BM44/BM14,0)*1000 -> 0
C30: 1 оч | D30: тыс. руб. | E30: =IFERROR(E45/E15*1000,0) -> 700 | F30: ='CF1'!F20 -> 0 | G30: ='CF1'!G20 -> 0 | H30: ='CF1'!H20 -> 0 | I30: ='CF1'!I20 -> 0 | J30: ='CF1'!J20 -> 0 | K30: ='CF1'!K20 -> 0 | L30: ='CF1'!L20 -> 0 | M30: ='CF1'!M20 -> 0 | ... BM30: ='CF1'!BM20 -> 0
C31: 2 оч | D31: тыс. руб. | E31: =IFERROR(E46/E16*1000,0) -> 700 | F31: ='CF2'!F20 -> 0 | G31: ='CF2'!G20 -> 0 | H31: ='CF2'!H20 -> 0 | I31: ='CF2'!I20 -> 0 | J31: ='CF2'!J20 -> 0 | K31: ='CF2'!K20 -> 0 | L31: ='CF2'!L20 -> 0 | M31: ='CF2'!M20 -> 0 | ... BM31: ='CF2'!BM20 -> 0
B32: =B17 -> ТЦ | D32: тыс. руб. | E32: =IFERROR(E47/E17*1000,0) -> 0
B33: =B18 -> ПАРКИНГ ЖИЛЬЕ | D33: тыс. руб. | E33: =IFERROR(E48/E18*1000,0) -> 4500 | F33: =IFERROR(F48/F18,0)*1000 -> 0 | G33: =IFERROR(G48/G18,0)*1000 -> 0 | H33: =IFERROR(H48/H18,0)*1000 -> 0 | I33: =IFERROR(I48/I18,0)*1000 -> 0 | J33: =IFERROR(J48/J18,0)*1000 -> 0 | K33: =IFERROR(K48/K18,0)*1000 -> 0 | L33: =IFERROR(L48/L18,0)*1000 -> 0 | M33: =IFERROR(M48/M18,0)*1000 -> 0 | ... BM33: =IFERROR(BM48/BM18,0)*1000 -> 0
C34: 1 оч | D34: тыс. руб. | E34: =IFERROR(E49/E19*1000,0) -> 4500 | F34: ='CF1'!F22 -> 0 | G34: ='CF1'!G22 -> 0 | H34: ='CF1'!H22 -> 0 | I34: ='CF1'!I22 -> 0 | J34: ='CF1'!J22 -> 0 | K34: ='CF1'!K22 -> 0 | L34: ='CF1'!L22 -> 0 | M34: ='CF1'!M22 -> 0 | ... BM34: ='CF1'!BM22 -> 0
C35: 2 оч | D35: тыс. руб. | E35: =IFERROR(E50/E20*1000,0) -> 4500 | F35: ='CF2'!F22 -> 0 | G35: ='CF2'!G22 -> 0 | H35: ='CF2'!H22 -> 0 | I35: ='CF2'!I22 -> 0 | J35: ='CF2'!J22 -> 0 | K35: ='CF2'!K22 -> 0 | L35: ='CF2'!L22 -> 0 | M35: ='CF2'!M22 -> 0 | ... BM35: ='CF2'!BM22 -> 0
B36: =B21 -> ПАРКИНГ ОФИС | D36: тыс. руб. | E36: =IFERROR(E51/E21*1000,0) -> 0
B38: КОНТРАКТАЦИЯ | D38: млн. руб. | E38: =SUM(F38:BM38) -> 78746.093 | F38: =SUM(F39,F44,F48) -> 0 | G38: =SUM(G39,G44,G48) -> 0 | H38: =SUM(H39,H44,H48) -> 0 | I38: =SUM(I39,I44,I48) -> 0 | J38: =SUM(J39,J44,J48) -> 0 | K38: =SUM(K39,K44,K48) -> 0 | L38: =SUM(L39,L44,L48) -> 0 | M38: =SUM(M39,M44,M48) -> 0 | ... BM38: =SUM(BM39,BM44,BM48) -> 0
B39: =B24 -> КВАРТИРЫ | D39: млн. руб. | E39: =SUM(F39:BM39) -> 69490.705 | F39: =F40+F41 -> 0 | G39: =G40+G41 -> 0 | H39: =H40+H41 -> 0 | I39: =I40+I41 -> 0 | J39: =J40+J41 -> 0 | K39: =K40+K41 -> 0 | L39: =L40+L41 -> 0 | M39: =M40+M41 -> 0 | ... BM39: =BM40+BM41 -> 0
C40: 1 оч | D40: млн. руб. | E40: =SUM(F40:BM40) -> 37437.979 | F40: ='CF1'!F26 -> 0 | G40: ='CF1'!G26 -> 0 | H40: ='CF1'!H26 -> 0 | I40: ='CF1'!I26 -> 0 | J40: ='CF1'!J26 -> 0 | K40: ='CF1'!K26 -> 0 | L40: ='CF1'!L26 -> 0 | M40: ='CF1'!M26 -> 0 | ... BM40: ='CF1'!BM26 -> 0
C41: 2 оч | D41: млн. руб. | E41: =SUM(F41:BM41) -> 32052.726 | F41: ='CF2'!F26 -> 0 | G41: ='CF2'!G26 -> 0 | H41: ='CF2'!H26 -> 0 | I41: ='CF2'!I26 -> 0 | J41: ='CF2'!J26 -> 0 | K41: ='CF2'!K26 -> 0 | L41: ='CF2'!L26 -> 0 | M41: ='CF2'!M26 -> 0 | ... BM41: ='CF2'!BM26 -> 0
B42: =B27 -> АПАРТАМЕНТЫ | D42: млн. руб. | E42: =SUM(F42:BM42) -> 0 | F42: =F12*F27/10^3 -> 0 | G42: =G12*G27/10^3 -> 0 | H42: =H12*H27/10^3 -> 0 | I42: =I12*I27/10^3 -> 0 | J42: =J12*J27/10^3 -> 0 | K42: =K12*K27/10^3 -> 0 | L42: =L12*L27/10^3 -> 0 | M42: =M12*M27/10^3 -> 0 | ... BM42: =BM12*BM27/10^3 -> 0
B43: =B28 -> ОФИСЫ | D43: млн. руб. | E43: =SUM(F43:BM43) -> 0 | F43: =F13*F28/10^3 -> 0 | G43: =G13*G28/10^3 -> 0 | H43: =H13*H28/10^3 -> 0 | I43: =I13*I28/10^3 -> 0 | J43: =J13*J28/10^3 -> 0 | K43: =K13*K28/10^3 -> 0 | L43: =L13*L28/10^3 -> 0 | M43: =M13*M28/10^3 -> 0 | ... BM43: =BM13*BM28/10^3 -> 0
B44: =B29 -> РИТЕЙЛ | D44: млн. руб. | E44: =SUM(F44:BM44) -> 4251.388 | F44: =F45+F46 -> 0 | G44: =G45+G46 -> 0 | H44: =H45+H46 -> 0 | I44: =I45+I46 -> 0 | J44: =J45+J46 -> 0 | K44: =K45+K46 -> 0 | L44: =L45+L46 -> 0 | M44: =M45+M46 -> 0 | ... BM44: =BM45+BM46 -> 0
C45: 1 оч | D45: млн. руб. | E45: =SUM(F45:BM45) -> 2462.1471 | F45: ='CF1'!F29 -> 0 | G45: ='CF1'!G29 -> 0 | H45: ='CF1'!H29 -> 0 | I45: ='CF1'!I29 -> 0 | J45: ='CF1'!J29 -> 0 | K45: ='CF1'!K29 -> 0 | L45: ='CF1'!L29 -> 0 | M45: ='CF1'!M29 -> 0 | ... BM45: ='CF1'!BM29 -> 0
C46: 2 оч | D46: млн. руб. | E46: =SUM(F46:BM46) -> 1789.2409 | F46: ='CF2'!F29 -> 0 | G46: ='CF2'!G29 -> 0 | H46: ='CF2'!H29 -> 0 | I46: ='CF2'!I29 -> 0 | J46: ='CF2'!J29 -> 0 | K46: ='CF2'!K29 -> 0 | L46: ='CF2'!L29 -> 0 | M46: ='CF2'!M29 -> 0 | ... BM46: ='CF2'!BM29 -> 0
B47: =B32 -> ТЦ | D47: млн. руб. | E47: =SUM(F47:BM47) -> 0 | F47: =F17*F32/10^3 -> 0 | G47: =G17*G32/10^3 -> 0 | H47: =H17*H32/10^3 -> 0 | I47: =I17*I32/10^3 -> 0 | J47: =J17*J32/10^3 -> 0 | K47: =K17*K32/10^3 -> 0 | L47: =L17*L32/10^3 -> 0 | M47: =M17*M32/10^3 -> 0 | ... BM47: =BM17*BM32/10^3 -> 0
B48: =B33 -> ПАРКИНГ ЖИЛЬЕ | D48: млн. руб. | E48: =SUM(F48:BM48) -> 5004 | F48: =F49+F50 -> 0 | G48: =G49+G50 -> 0 | H48: =H49+H50 -> 0 | I48: =I49+I50 -> 0 | J48: =J49+J50 -> 0 | K48: =K49+K50 -> 0 | L48: =L49+L50 -> 0 | M48: =M49+M50 -> 0 | ... BM48: =BM49+BM50 -> 0
C49: 1 оч | D49: млн. руб. | E49: =SUM(F49:BM49) -> 2695.5 | F49: ='CF1'!F31 -> 0 | G49: ='CF1'!G31 -> 0 | H49: ='CF1'!H31 -> 0 | I49: ='CF1'!I31 -> 0 | J49: ='CF1'!J31 -> 0 | K49: ='CF1'!K31 -> 0 | L49: ='CF1'!L31 -> 0 | M49: ='CF1'!M31 -> 0 | ... BM49: ='CF1'!BM31 -> 0
C50: 2 оч | D50: млн. руб. | E50: =SUM(F50:BM50) -> 2308.5 | F50: ='CF2'!F31 -> 0 | G50: ='CF2'!G31 -> 0 | H50: ='CF2'!H31 -> 0 | I50: ='CF2'!I31 -> 0 | J50: ='CF2'!J31 -> 0 | K50: ='CF2'!K31 -> 0 | L50: ='CF2'!L31 -> 0 | M50: ='CF2'!M31 -> 0 | ... BM50: ='CF2'!BM31 -> 0
B51: =B36 -> ПАРКИНГ ОФИС | D51: млн. руб. | E51: =SUM(F51:BM51) -> 0 | F51: =F21*F36/10^3 -> 0 | G51: =G21*G36/10^3 -> 0 | H51: =H21*H36/10^3 -> 0 | I51: =I21*I36/10^3 -> 0 | J51: =J21*J36/10^3 -> 0 | K51: =K21*K36/10^3 -> 0 | L51: =L21*L36/10^3 -> 0 | M51: =M21*M36/10^3 -> 0 | ... BM51: =BM21*BM36/10^3 -> 0
B53: ПОСТУПЛЕНИЯ (до РнВ на эскроу) | D53: млн. руб. | E53: =SUM(F53:BM53) -> 78746.093 | F53: ='CF1'!F34+'CF2'!F34 -> 0 | G53: ='CF1'!G34+'CF2'!G34 -> 0 | H53: ='CF1'!H34+'CF2'!H34 -> 0 | I53: ='CF1'!I34+'CF2'!I34 -> 0 | J53: ='CF1'!J34+'CF2'!J34 -> 0 | K53: ='CF1'!K34+'CF2'!K34 -> 0 | L53: ='CF1'!L34+'CF2'!L34 -> 0 | M53: ='CF1'!M34+'CF2'!M34 -> 0 | ... BM53: ='CF1'!BM34+'CF2'!BM34 -> 0
B54: =B39 -> КВАРТИРЫ | D54: млн. руб. | E54: =SUM(F54:BM54) -> 69490.705 | F54: =F55+F56 -> 0 | G54: =G55+G56 -> 0 | H54: =H55+H56 -> 0 | I54: =I55+I56 -> 0 | J54: =J55+J56 -> 0 | K54: =K55+K56 -> 0 | L54: =L55+L56 -> 0 | M54: =M55+M56 -> 0 | ... BM54: =BM55+BM56 -> 0
C55: 1 оч | D55: млн. руб. | E55: =SUM(F55:BM55) -> 37437.979 | F55: ='CF1'!F35 -> 0 | G55: ='CF1'!G35 -> 0 | H55: ='CF1'!H35 -> 0 | I55: ='CF1'!I35 -> 0 | J55: ='CF1'!J35 -> 0 | K55: ='CF1'!K35 -> 0 | L55: ='CF1'!L35 -> 0 | M55: ='CF1'!M35 -> 0 | ... BM55: ='CF1'!BM35 -> 0
C56: 2 оч | D56: млн. руб. | E56: =SUM(F56:BM56) -> 32052.726 | F56: ='CF2'!F35 -> 0 | G56: ='CF2'!G35 -> 0 | H56: ='CF2'!H35 -> 0 | I56: ='CF2'!I35 -> 0 | J56: ='CF2'!J35 -> 0 | K56: ='CF2'!K35 -> 0 | L56: ='CF2'!L35 -> 0 | M56: ='CF2'!M35 -> 0 | ... BM56: ='CF2'!BM35 -> 0
B57: =B42 -> АПАРТАМЕНТЫ | D57: млн. руб. | E57: =SUM(F57:BM57) -> 0 | G57: =(G42*'DB1'!$N9+SUM($F42:F42)-SUM(CF!$F57:F57)) -> 0 | H57: =(H42*'DB1'!$N9+SUM($F42:G42)-SUM(CF!$F57:G57)) -> 0 | I57: =(I42*'DB1'!$N9+SUM($F42:H42)-SUM(CF!$F57:H57)) -> 0 | J57: =(J42*'DB1'!$N9+SUM($F42:I42)-SUM(CF!$F57:I57)) -> 0 | K57: =(K42*'DB1'!$N9+SUM($F42:J42)-SUM(CF!$F57:J57)) -> 0 | L57: =(L42*'DB1'!$N9+SUM($F42:K42)-SUM(CF!$F57:K57)) -> 0 | M57: =(M42*'DB1'!$N9+SUM($F42:L42)-SUM(CF!$F57:L57)) -> 0 | N57: =(N42*'DB1'!$N9+SUM($F42:M42)-SUM(CF!$F57:M57)) -> 0 | ... BM57: =(BM42*'DB1'!$N9+SUM($F42:BL42)-SUM(CF!$F57:BL57)) -> 0
B58: =B43 -> ОФИСЫ | D58: млн. руб. | E58: =SUM(F58:BM58) -> 0 | G58: =(G43*'DB1'!$N10+SUM($F43:F43)-SUM(CF!$F58:F58)) -> 0 | H58: =(H43*'DB1'!$N10+SUM($F43:G43)-SUM(CF!$F58:G58)) -> 0 | I58: =(I43*'DB1'!$N10+SUM($F43:H43)-SUM(CF!$F58:H58)) -> 0 | J58: =(J43*'DB1'!$N10+SUM($F43:I43)-SUM(CF!$F58:I58)) -> 0 | K58: =(K43*'DB1'!$N10+SUM($F43:J43)-SUM(CF!$F58:J58)) -> 0 | L58: =(L43*'DB1'!$N10+SUM($F43:K43)-SUM(CF!$F58:K58)) -> 0 | M58: =(M43*'DB1'!$N10+SUM($F43:L43)-SUM(CF!$F58:L58)) -> 0 | N58: =(N43*'DB1'!$N10+SUM($F43:M43)-SUM(CF!$F58:M58)) -> 0 | ... BM58: =(BM43*'DB1'!$N10+SUM($F43:BL43)-SUM(CF!$F58:BL58)) -> 0
B59: =B44 -> РИТЕЙЛ | D59: млн. руб. | E59: =SUM(F59:BM59) -> 4251.388 | F59: =F60+F61 -> 0 | G59: =G60+G61 -> 0 | H59: =H60+H61 -> 0 | I59: =I60+I61 -> 0 | J59: =J60+J61 -> 0 | K59: =K60+K61 -> 0 | L59: =L60+L61 -> 0 | M59: =M60+M61 -> 0 | ... BM59: =BM60+BM61 -> 0
C60: 1 оч | D60: млн. руб. | E60: =SUM(F60:BM60) -> 2462.1471 | F60: ='CF1'!F44 -> 0 | G60: ='CF1'!G44 -> 0 | H60: ='CF1'!H44 -> 0 | I60: ='CF1'!I44 -> 0 | J60: ='CF1'!J44 -> 0 | K60: ='CF1'!K44 -> 0 | L60: ='CF1'!L44 -> 0 | M60: ='CF1'!M44 -> 0 | ... BM60: ='CF1'!BM44 -> 0
C61: 2 оч | D61: млн. руб. | E61: =SUM(F61:BM61) -> 1789.2409 | F61: ='CF2'!F44 -> 0 | G61: ='CF2'!G44 -> 0 | H61: ='CF2'!H44 -> 0 | I61: ='CF2'!I44 -> 0 | J61: ='CF2'!J44 -> 0 | K61: ='CF2'!K44 -> 0 | L61: ='CF2'!L44 -> 0 | M61: ='CF2'!M44 -> 0 | ... BM61: ='CF2'!BM44 -> 0
B62: =B47 -> ТЦ | D62: млн. руб. | E62: =SUM(F62:BM62) -> 0
B63: =B48 -> ПАРКИНГ ЖИЛЬЕ | D63: млн. руб. | E63: =SUM(F63:BM63) -> 5004 | F63: =F64+F65 -> 0 | G63: =G64+G65 -> 0 | H63: =H64+H65 -> 0 | I63: =I64+I65 -> 0 | J63: =J64+J65 -> 0 | K63: =K64+K65 -> 0 | L63: =L64+L65 -> 0 | M63: =M64+M65 -> 0 | ... BM63: =BM64+BM65 -> 0
C64: 1 оч | D64: млн. руб. | E64: =SUM(F64:BM64) -> 2695.5 | F64: ='CF1'!F46 -> 0 | G64: ='CF1'!G46 -> 0 | H64: ='CF1'!H46 -> 0 | I64: ='CF1'!I46 -> 0 | J64: ='CF1'!J46 -> 0 | K64: ='CF1'!K46 -> 0 | L64: ='CF1'!L46 -> 0 | M64: ='CF1'!M46 -> 0 | ... BM64: ='CF1'!BM46 -> 0
C65: 2 оч | D65: млн. руб. | E65: =SUM(F65:BM65) -> 2308.5 | F65: ='CF2'!F31 -> 0 | G65: ='CF2'!G31 -> 0 | H65: ='CF2'!H31 -> 0 | I65: ='CF2'!I31 -> 0 | J65: ='CF2'!J31 -> 0 | K65: ='CF2'!K31 -> 0 | L65: ='CF2'!L31 -> 0 | M65: ='CF2'!M31 -> 0 | ... BM65: ='CF2'!BM31 -> 0
B66: =B51 -> ПАРКИНГ ОФИС | D66: млн. руб. | E66: =SUM(F66:BM66) -> 0
B69: РАСХОДЫ | D69: млн. руб. | E69: =SUM(F69:BM69) -> -5999.3951 | F69: =SUM(F72:F75) -> -0.18152286 | G69: =SUM(G70:G75) -> -0.55836329 | H69: =SUM(H70:H75) -> -0.28357 | I69: =SUM(I70:I75) -> -0.29047 | J69: =SUM(J70:J75) -> -0.33547 | K69: =SUM(K70:K75) -> -0.3448 | L69: =SUM(L70:L75) -> -0.63933562 | M69: =SUM(M70:M75) -> -0.68848 | N69: =SUM(N70:N75) -> -5.5783842 | ... BM69: =SUM(BM70:BM75) -> 0
B70: БРОКЕРИДЖ | D70: млн. руб. | E70: =SUM(G70:BM70) -> -2362.3828 | F70: ='CF1'!F51+'CF2'!F51 -> 0 | G70: ='CF1'!G51+'CF2'!G51 -> 0 | H70: ='CF1'!H51+'CF2'!H51 -> 0 | I70: ='CF1'!I51+'CF2'!I51 -> 0 | J70: ='CF1'!J51+'CF2'!J51 -> 0 | K70: ='CF1'!K51+'CF2'!K51 -> 0 | L70: ='CF1'!L51+'CF2'!L51 -> 0 | M70: ='CF1'!M51+'CF2'!M51 -> 0 | ... BM70: ='CF1'!BM51+'CF2'!BM51 -> 0
B71: УПРАВЛЕНИЕ ПРОДАЖАМИ | D71: млн. руб. | E71: =SUM(G71:BM71) -> -944.95311 | F71: ='CF1'!F52+'CF2'!F52 -> 0 | G71: ='CF1'!G52+'CF2'!G52 -> 0 | H71: ='CF1'!H52+'CF2'!H52 -> 0 | I71: ='CF1'!I52+'CF2'!I52 -> 0 | J71: ='CF1'!J52+'CF2'!J52 -> 0 | K71: ='CF1'!K52+'CF2'!K52 -> 0 | L71: ='CF1'!L52+'CF2'!L52 -> 0 | M71: ='CF1'!M52+'CF2'!M52 -> 0 | ... BM71: ='CF1'!BM52+'CF2'!BM52 -> 0
B72: РЕКЛАМА И МАРКЕТИНГ | D72: млн. руб. | E72: =SUM(F72:BM72) -> -2362.3828 | F72: ='CF1'!F53+'CF2'!F53 -> 0 | G72: ='CF1'!G53+'CF2'!G53 -> 0 | H72: ='CF1'!H53+'CF2'!H53 -> 0 | I72: ='CF1'!I53+'CF2'!I53 -> 0 | J72: ='CF1'!J53+'CF2'!J53 -> 0 | K72: ='CF1'!K53+'CF2'!K53 -> 0 | L72: ='CF1'!L53+'CF2'!L53 -> 0 | M72: ='CF1'!M53+'CF2'!M53 -> 0 | ... BM72: ='CF1'!BM53+'CF2'!BM53 -> 0
B73: АРЕНДА ЗУ/НАЛОГ ЗУ | D73: млн. руб. | E73: =SUM(F73:BM73) -> -32.599916 | F73: ='CF1'!F54+'CF2'!F54 -> 0 | G73: ='CF1'!G54+'CF2'!G54 -> 0 | H73: ='CF1'!H54+'CF2'!H54 -> 0 | I73: ='CF1'!I54+'CF2'!I54 -> 0 | J73: ='CF1'!J54+'CF2'!J54 -> 0 | K73: ='CF1'!K54+'CF2'!K54 -> 0 | L73: ='CF1'!L54+'CF2'!L54 -> 0 | M73: ='CF1'!M54+'CF2'!M54 -> 0 | ... BM73: ='CF1'!BM54+'CF2'!BM54 -> 0
B74: РЕГИСТРАЦИЯ ДОГОВОРОВ | D74: млн. руб. | E74: =SUM(F74:BM74) -> -138.07654 | F74: ='CF1'!F55+'CF2'!F55 -> 0 | G74: ='CF1'!G55+'CF2'!G55 -> 0 | H74: ='CF1'!H55+'CF2'!H55 -> 0 | I74: ='CF1'!I55+'CF2'!I55 -> 0 | J74: ='CF1'!J55+'CF2'!J55 -> 0 | K74: ='CF1'!K55+'CF2'!K55 -> 0 | L74: ='CF1'!L55+'CF2'!L55 -> 0 | M74: ='CF1'!M55+'CF2'!M55 -> 0 | ... BM74: ='CF1'!BM55+'CF2'!BM55 -> 0
B75: АХР | D75: млн. руб. | E75: =SUM(F75:BM75) -> -159 | F75: ='CF1'!F56+'CF2'!F56 -> -0.18152286 | G75: ='CF1'!G56+'CF2'!G56 -> -0.55836329 | H75: ='CF1'!H56+'CF2'!H56 -> -0.28357 | I75: ='CF1'!I56+'CF2'!I56 -> -0.29047 | J75: ='CF1'!J56+'CF2'!J56 -> -0.33547 | K75: ='CF1'!K56+'CF2'!K56 -> -0.3448 | L75: ='CF1'!L56+'CF2'!L56 -> -0.63933562 | M75: ='CF1'!M56+'CF2'!M56 -> -0.68848 | ... BM75: ='CF1'!BM56+'CF2'!BM56 -> 0
B78: ИНВЕСТИЦИИ | D78: млн. руб. | E78: =SUM(F78:BM78) -> -47750.706 | F78: =SUM(F79:F93) -> 0 | G78: =SUM(G79:G93) -> 0 | H78: =SUM(H79:H93) -> 0 | I78: =SUM(I79:I93) -> 0 | J78: =SUM(J79:J93) -> 0 | K78: =SUM(K79:K93) -> 0 | L78: =SUM(L79:L93) -> 0 | M78: =SUM(M79:M93) -> 0 | ... BM78: =SUM(BM79:BM93) -> 0
B79: ВХОД | D79: млн. руб. | E79: =SUM(F79:BM79) -> -3841.3458 | F79: ='CF1'!F60+'CF2'!F60 -> 0 | G79: ='CF1'!G60+'CF2'!G60 -> 0 | H79: ='CF1'!H60+'CF2'!H60 -> 0 | I79: ='CF1'!I60+'CF2'!I60 -> 0 | J79: ='CF1'!J60+'CF2'!J60 -> 0 | K79: ='CF1'!K60+'CF2'!K60 -> 0 | L79: ='CF1'!L60+'CF2'!L60 -> 0 | M79: ='CF1'!M60+'CF2'!M60 -> 0 | ... BM79: ='CF1'!BM60+'CF2'!BM60 -> 0
B80: ВРИ | D80: млн. руб. | E80: =SUM(F80:BM80) -> -4689.2948 | F80: ='CF1'!F61+'CF2'!F61 -> 0 | G80: ='CF1'!G61+'CF2'!G61 -> 0 | H80: ='CF1'!H61+'CF2'!H61 -> 0 | I80: ='CF1'!I61+'CF2'!I61 -> 0 | J80: ='CF1'!J61+'CF2'!J61 -> 0 | K80: ='CF1'!K61+'CF2'!K61 -> 0 | L80: ='CF1'!L61+'CF2'!L61 -> 0 | M80: ='CF1'!M61+'CF2'!M61 -> 0 | ... BM80: ='CF1'!BM61+'CF2'!BM61 -> 0
B81: АРЕНДА ЗУ/ПРОЧИЕ РАБОТЫ ПО ЗУ | D81: млн. руб. | E81: =SUM(F81:BM81) -> -235.91962 | F81: ='CF1'!F62+'CF2'!F62 -> 0 | G81: ='CF1'!G62+'CF2'!G62 -> 0 | H81: ='CF1'!H62+'CF2'!H62 -> 0 | I81: ='CF1'!I62+'CF2'!I62 -> 0 | J81: ='CF1'!J62+'CF2'!J62 -> 0 | K81: ='CF1'!K62+'CF2'!K62 -> 0 | L81: ='CF1'!L62+'CF2'!L62 -> 0 | M81: ='CF1'!M62+'CF2'!M62 -> 0 | ... BM81: ='CF1'!BM62+'CF2'!BM62 -> 0
B82: ='DB1'!B31 -> ПРОЕКТИРОВАНИЕ (К+П+РД) | D82: млн. руб. | E82: =SUM(F82:BM82) -> -1536.3104 | F82: ='CF1'!F63+'CF2'!F63 -> 0 | G82: ='CF1'!G63+'CF2'!G63 -> 0 | H82: ='CF1'!H63+'CF2'!H63 -> 0 | I82: ='CF1'!I63+'CF2'!I63 -> 0 | J82: ='CF1'!J63+'CF2'!J63 -> 0 | K82: ='CF1'!K63+'CF2'!K63 -> 0 | L82: ='CF1'!L63+'CF2'!L63 -> 0 | M82: ='CF1'!M63+'CF2'!M63 -> 0 | ... BM82: ='CF1'!BM63+'CF2'!BM63 -> 0
B83: ='DB1'!B32 -> СОГЛАСОВАНИЯ | D83: млн. руб. | E83: =SUM(F83:BM83) -> -210.15318 | F83: ='CF1'!F64+'CF2'!F64 -> 0 | G83: ='CF1'!G64+'CF2'!G64 -> 0 | H83: ='CF1'!H64+'CF2'!H64 -> 0 | I83: ='CF1'!I64+'CF2'!I64 -> 0 | J83: ='CF1'!J64+'CF2'!J64 -> 0 | K83: ='CF1'!K64+'CF2'!K64 -> 0 | L83: ='CF1'!L64+'CF2'!L64 -> 0 | M83: ='CF1'!M64+'CF2'!M64 -> 0 | ... BM83: ='CF1'!BM64+'CF2'!BM64 -> 0
B84: ='DB1'!B33 -> СМР жилье | D84: млн. руб. | E84: =SUM(F84:BM84) -> -28790.985 | F84: ='CF1'!F65+'CF2'!F65 -> 0 | G84: ='CF1'!G65+'CF2'!G65 -> 0 | H84: ='CF1'!H65+'CF2'!H65 -> 0 | I84: ='CF1'!I65+'CF2'!I65 -> 0 | J84: ='CF1'!J65+'CF2'!J65 -> 0 | K84: ='CF1'!K65+'CF2'!K65 -> 0 | L84: ='CF1'!L65+'CF2'!L65 -> 0 | M84: ='CF1'!M65+'CF2'!M65 -> 0 | ... BM84: ='CF1'!BM65+'CF2'!BM65 -> 0
B85: ='DB1'!B34 -> СМР офисы | D85: млн. руб. | E85: =SUM(F85:BM85) -> 0 | F85: ='CF1'!F66+'CF2'!F66 -> 0 | G85: ='CF1'!G66+'CF2'!G66 -> 0 | H85: ='CF1'!H66+'CF2'!H66 -> 0 | I85: ='CF1'!I66+'CF2'!I66 -> 0 | J85: ='CF1'!J66+'CF2'!J66 -> 0 | K85: ='CF1'!K66+'CF2'!K66 -> 0 | L85: ='CF1'!L66+'CF2'!L66 -> 0 | M85: ='CF1'!M66+'CF2'!M66 -> 0 | ... BM85: ='CF1'!BM66+'CF2'!BM66 -> 0
B86: ='DB1'!B35 -> СМР ТЦ | D86: млн. руб. | E86: =SUM(F86:BM86) -> 0 | F86: ='CF1'!F67+'CF2'!F67 -> 0 | G86: ='CF1'!G67+'CF2'!G67 -> 0 | H86: ='CF1'!H67+'CF2'!H67 -> 0 | I86: ='CF1'!I67+'CF2'!I67 -> 0 | J86: ='CF1'!J67+'CF2'!J67 -> 0 | K86: ='CF1'!K67+'CF2'!K67 -> 0 | L86: ='CF1'!L67+'CF2'!L67 -> 0 | M86: ='CF1'!M67+'CF2'!M67 -> 0 | ... BM86: ='CF1'!BM67+'CF2'!BM67 -> 0
B87: ='DB1'!B36 -> СМР соц. объектов (компенсация) | D87: млн. руб. | E87: =SUM(F87:BM87) -> -4369.2379 | F87: ='CF1'!F68+'CF2'!F68 -> 0 | G87: ='CF1'!G68+'CF2'!G68 -> 0 | H87: ='CF1'!H68+'CF2'!H68 -> 0 | I87: ='CF1'!I68+'CF2'!I68 -> 0 | J87: ='CF1'!J68+'CF2'!J68 -> 0 | K87: ='CF1'!K68+'CF2'!K68 -> 0 | L87: ='CF1'!L68+'CF2'!L68 -> 0 | M87: ='CF1'!M68+'CF2'!M68 -> 0 | ... BM87: ='CF1'!BM68+'CF2'!BM68 -> 0
B88: ОТДЕЛКА | D88: млн. руб. | E88: =SUM(F88:BM88) -> 0 | F88: ='CF1'!F69+'CF2'!F69 -> 0 | G88: ='CF1'!G69+'CF2'!G69 -> 0 | H88: ='CF1'!H69+'CF2'!H69 -> 0 | I88: ='CF1'!I69+'CF2'!I69 -> 0 | J88: ='CF1'!J69+'CF2'!J69 -> 0 | K88: ='CF1'!K69+'CF2'!K69 -> 0 | L88: ='CF1'!L69+'CF2'!L69 -> 0 | M88: ='CF1'!M69+'CF2'!M69 -> 0 | ... BM88: ='CF1'!BM69+'CF2'!BM69 -> 0
B89: ='DB1'!B38 -> СОДЕРЖАНИЕ ПЛОЩАДКИ | D89: млн. руб. | E89: =SUM(F89:BM89) -> -161.84818 | F89: ='CF1'!F71+'CF2'!F71 -> 0 | G89: ='CF1'!G71+'CF2'!G71 -> 0 | H89: ='CF1'!H71+'CF2'!H71 -> 0 | I89: ='CF1'!I71+'CF2'!I71 -> 0 | J89: ='CF1'!J71+'CF2'!J71 -> 0 | K89: ='CF1'!K71+'CF2'!K71 -> 0 | L89: ='CF1'!L71+'CF2'!L71 -> 0 | M89: ='CF1'!M71+'CF2'!M71 -> 0 | ... BM89: ='CF1'!BM71+'CF2'!BM71 -> 0
B90: СЕТИ | D90: млн. руб. | E90: =SUM(F90:BM90) -> -1155.8425 | F90: ='CF1'!F70+'CF2'!F70 -> 0 | G90: ='CF1'!G70+'CF2'!G70 -> 0 | H90: ='CF1'!H70+'CF2'!H70 -> 0 | I90: ='CF1'!I70+'CF2'!I70 -> 0 | J90: ='CF1'!J70+'CF2'!J70 -> 0 | K90: ='CF1'!K70+'CF2'!K70 -> 0 | L90: ='CF1'!L70+'CF2'!L70 -> 0 | M90: ='CF1'!M70+'CF2'!M70 -> 0 | ... BM90: ='CF1'!BM70+'CF2'!BM70 -> 0
B91: МОНИТОРИНГИ | D91: млн. руб. | E91: =SUM(F91:BM91) -> -525.38294 | F91: ='CF1'!F72+'CF2'!F72 -> 0 | G91: ='CF1'!G72+'CF2'!G72 -> 0 | H91: ='CF1'!H72+'CF2'!H72 -> 0 | I91: ='CF1'!I72+'CF2'!I72 -> 0 | J91: ='CF1'!J72+'CF2'!J72 -> 0 | K91: ='CF1'!K72+'CF2'!K72 -> 0 | L91: ='CF1'!L72+'CF2'!L72 -> 0 | M91: ='CF1'!M72+'CF2'!M72 -> 0 | ... BM91: ='CF1'!BM72+'CF2'!BM72 -> 0
B92: УПРАВЛЕНИЕ ПРОЕКТОМ + FINDERS FEE | D92: млн. руб. | E92: =SUM(F92:BM92) -> -1499.3902 | F92: ='CF1'!F73+'CF2'!F73 -> 0 | G92: ='CF1'!G73+'CF2'!G73 -> 0 | H92: ='CF1'!H73+'CF2'!H73 -> 0 | I92: ='CF1'!I73+'CF2'!I73 -> 0 | J92: ='CF1'!J73+'CF2'!J73 -> 0 | K92: ='CF1'!K73+'CF2'!K73 -> 0 | L92: ='CF1'!L73+'CF2'!L73 -> 0 | M92: ='CF1'!M73+'CF2'!M73 -> 0 | ... BM92: ='CF1'!BM73+'CF2'!BM73 -> 0
B93: НЕПРЕДВИДЕННЫЕ РАСХОДЫ | D93: млн. руб. | E93: =SUM(F93:BM93) -> -734.9952 | F93: ='CF1'!F74+'CF2'!F74 -> 0 | G93: ='CF1'!G74+'CF2'!G74 -> 0 | H93: ='CF1'!H74+'CF2'!H74 -> 0 | I93: ='CF1'!I74+'CF2'!I74 -> 0 | J93: ='CF1'!J74+'CF2'!J74 -> 0 | K93: ='CF1'!K74+'CF2'!K74 -> 0 | L93: ='CF1'!L74+'CF2'!L74 -> 0 | M93: ='CF1'!M74+'CF2'!M74 -> 0 | ... BM93: ='CF1'!BM74+'CF2'!BM74 -> 0
B95: ПОТОК ПРОЕКТА | D95: млн. руб. | E95: =SUM(F95:BM95) -> 24995.992 | F95: =F53+F69+F78 -> -0.18152286 | G95: =G53+G69+G78 -> -0.55836329 | H95: =H53+H69+H78 -> -0.28357 | I95: =I53+I69+I78 -> -0.29047 | J95: =J53+J69+J78 -> -0.33547 | K95: =K53+K69+K78 -> -0.3448 | L95: =L53+L69+L78 -> -0.63933562 | M95: =M53+M69+M78 -> -0.68848 | ... BM95: =BM53+BM69+BM78 -> 0
B98: ФИНАНСИРОВАНИЕ | D98: млн. руб. | E98: =SUM(F98:BM98) -> -10772.116 | F98: =SUM(F100:F101,F104,F106:F107,F114:F115,F110,F112,F120,F118,F123,F125:F126) -> 0.2 | G98: =SUM(G100:G101,G104,G106:G107,G114:G115,G110,G112,G120,G118,G123,G125:G126) -> 0.6 | H98: =SUM(H100:H101,H104,H106:H107,H114:H115,H110,H112,H120,H118,H123,H125:H126) -> 0.6 | I98: =SUM(I100:I101,I104,I106:I107,I114:I115,I110,I112,I120,I118,I123,I125:I126) -> 0.3 | J98: =SUM(J100:J101,J104,J106:J107,J114:J115,J110,J112,J120,J118,J123,J125:J126) -> 0 | K98: =SUM(K100:K101,K104,K106:K107,K114:K115,K110,K112,K120,K118,K123,K125:K126) -> 0.8 | L98: =SUM(L100:L101,L104,L106:L107,L114:L115,L110,L112,L120,L118,L123,L125:L126) -> 0.6 | M98: =SUM(M100:M101,M104,M106:M107,M114:M115,M110,M112,M120,M118,M123,M125:M126) -> 1.07 | ... BM98: =SUM(BM100:BM101,BM104,BM106:BM107,BM114:BM115,BM110,BM112,BM120,BM118,BM123,BM125:BM126) -> 0
B99: АФ | D99: млн. руб. | E99: =SUM(F99:BM99) -> 0 | F99: ='CF1'!F80+'CF2'!F80 -> 0 | G99: ='CF1'!G80+'CF2'!G80 -> 0 | H99: ='CF1'!H80+'CF2'!H80 -> 0 | I99: ='CF1'!I80+'CF2'!I80 -> 0 | J99: ='CF1'!J80+'CF2'!J80 -> 0 | K99: ='CF1'!K80+'CF2'!K80 -> 0 | L99: ='CF1'!L80+'CF2'!L80 -> 0 | M99: ='CF1'!M80+'CF2'!M80 -> 0 | ... BM99: ='CF1'!BM80+'CF2'!BM80 -> 0
C100: ПОСТУПЛЕНИЕ | D100: млн. руб. | E100: =SUM(F100:BM100) -> 596.3444 | F100: ='CF1'!F81+'CF2'!F81 -> 0.2 | G100: ='CF1'!G81+'CF2'!G81 -> 0.6 | H100: ='CF1'!H81+'CF2'!H81 -> 0.6 | I100: ='CF1'!I81+'CF2'!I81 -> 0.3 | J100: ='CF1'!J81+'CF2'!J81 -> 0 | K100: ='CF1'!K81+'CF2'!K81 -> 0.8 | L100: ='CF1'!L81+'CF2'!L81 -> 0.6 | M100: ='CF1'!M81+'CF2'!M81 -> 1.07 | ... BM100: ='CF1'!BM81+'CF2'!BM81 -> 0
C101: ПОГАШЕНИЕ | D101: млн. руб. | E101: =SUM(F101:BM101) -> -596.3444 | F101: ='CF1'!F82+'CF2'!F82 -> 0 | G101: ='CF1'!G82+'CF2'!G82 -> 0 | H101: ='CF1'!H82+'CF2'!H82 -> 0 | I101: ='CF1'!I82+'CF2'!I82 -> 0 | J101: ='CF1'!J82+'CF2'!J82 -> 0 | K101: ='CF1'!K82+'CF2'!K82 -> 0 | L101: ='CF1'!L82+'CF2'!L82 -> 0 | M101: ='CF1'!M82+'CF2'!M82 -> 0 | ... BM101: ='CF1'!BM82+'CF2'!BM82 -> 0
B102: % по АФ | D102: млн. руб. | E102: =SUM(F102:BM102) -> 0 | F102: ='CF1'!F83+'CF2'!F83 -> 0 | G102: ='CF1'!G83+'CF2'!G83 -> 0 | H102: ='CF1'!H83+'CF2'!H83 -> 0 | I102: ='CF1'!I83+'CF2'!I83 -> 0 | J102: ='CF1'!J83+'CF2'!J83 -> 0 | K102: ='CF1'!K83+'CF2'!K83 -> 0 | L102: ='CF1'!L83+'CF2'!L83 -> 0 | M102: ='CF1'!M83+'CF2'!M83 -> 0 | ... BM102: ='CF1'!BM83+'CF2'!BM83 -> 0
C103: НАЧИСЛЕНИЕ | D103: млн. руб. | E103: =SUM(F103:BM103) -> 392.30429 | F103: ='CF1'!F84+'CF2'!F84 -> 0.0105 | G103: ='CF1'!G84+'CF2'!G84 -> 0.042 | H103: ='CF1'!H84+'CF2'!H84 -> 0.0735 | I103: ='CF1'!I84+'CF2'!I84 -> 0.08925 | J103: ='CF1'!J84+'CF2'!J84 -> 0.08925 | K103: ='CF1'!K84+'CF2'!K84 -> 0.1375 | L103: ='CF1'!L84+'CF2'!L84 -> 0.1705 | M103: ='CF1'!M84+'CF2'!M84 -> 0.22935 | ... BM103: ='CF1'!BM84+'CF2'!BM84 -> 0
C104: УПЛАТА | D104: млн. руб. | E104: =SUM(F104:BM104) -> -392.30429 | F104: ='CF1'!F85+'CF2'!F85 -> 0 | G104: ='CF1'!G85+'CF2'!G85 -> 0 | H104: ='CF1'!H85+'CF2'!H85 -> 0 | I104: ='CF1'!I85+'CF2'!I85 -> 0 | J104: ='CF1'!J85+'CF2'!J85 -> 0 | K104: ='CF1'!K85+'CF2'!K85 -> 0 | L104: ='CF1'!L85+'CF2'!L85 -> 0 | M104: ='CF1'!M85+'CF2'!M85 -> 0 | ... BM104: ='CF1'!BM85+'CF2'!BM85 -> 0
B105: КРЕДИТ бридж | C105: реф | D105: млн. руб. | E105: =SUM(F105:BM105) -> 0 | F105: ='CF1'!F86+'CF2'!F86 -> 0 | G105: ='CF1'!G86+'CF2'!G86 -> 0 | H105: ='CF1'!H86+'CF2'!H86 -> 0 | I105: ='CF1'!I86+'CF2'!I86 -> 0 | J105: ='CF1'!J86+'CF2'!J86 -> 0 | K105: ='CF1'!K86+'CF2'!K86 -> 0 | L105: ='CF1'!L86+'CF2'!L86 -> 0 | M105: ='CF1'!M86+'CF2'!M86 -> 0 | ... BM105: ='CF1'!BM86+'CF2'!BM86 -> 0
C106: ПОСТУПЛЕНИЕ | D106: млн. руб. | E106: =SUM(F106:BM106) -> 9432.6279 | F106: ='CF1'!F87+'CF2'!F87 -> 0 | G106: ='CF1'!G87+'CF2'!G87 -> 0 | H106: ='CF1'!H87+'CF2'!H87 -> 0 | I106: ='CF1'!I87+'CF2'!I87 -> 0 | J106: ='CF1'!J87+'CF2'!J87 -> 0 | K106: ='CF1'!K87+'CF2'!K87 -> 0 | L106: ='CF1'!L87+'CF2'!L87 -> 0 | M106: ='CF1'!M87+'CF2'!M87 -> 0 | ... BM106: ='CF1'!BM87+'CF2'!BM87 -> 0
C107: ПОГАШЕНИЕ | D107: млн. руб. | E107: =SUM(F107:BM107) -> -9432.6279 | F107: ='CF1'!F88+'CF2'!F88 -> 0 | G107: ='CF1'!G88+'CF2'!G88 -> 0 | H107: ='CF1'!H88+'CF2'!H88 -> 0 | I107: ='CF1'!I88+'CF2'!I88 -> 0 | J107: ='CF1'!J88+'CF2'!J88 -> 0 | K107: ='CF1'!K88+'CF2'!K88 -> 0 | L107: ='CF1'!L88+'CF2'!L88 -> 0 | M107: ='CF1'!M88+'CF2'!M88 -> 0 | ... BM107: ='CF1'!BM88+'CF2'!BM88 -> 0
B108: % КРЕДИТУ бридж | D108: млн. руб. | E108: =SUM(F108:BM108) -> 0 | F108: ='CF1'!F89+'CF2'!F89 -> 0 | G108: ='CF1'!G89+'CF2'!G89 -> 0 | H108: ='CF1'!H89+'CF2'!H89 -> 0 | I108: ='CF1'!I89+'CF2'!I89 -> 0 | J108: ='CF1'!J89+'CF2'!J89 -> 0 | K108: ='CF1'!K89+'CF2'!K89 -> 0 | L108: ='CF1'!L89+'CF2'!L89 -> 0 | M108: ='CF1'!M89+'CF2'!M89 -> 0 | ... BM108: ='CF1'!BM89+'CF2'!BM89 -> 0
C109: НАЧИСЛЕНИЕ | D109: млн. руб. | E109: =SUM(F109:BM109) -> 1297.042 | F109: ='CF1'!F90+'CF2'!F90 -> 0 | G109: ='CF1'!G90+'CF2'!G90 -> 0 | H109: ='CF1'!H90+'CF2'!H90 -> 0 | I109: ='CF1'!I90+'CF2'!I90 -> 0 | J109: ='CF1'!J90+'CF2'!J90 -> 0 | K109: ='CF1'!K90+'CF2'!K90 -> 0 | L109: ='CF1'!L90+'CF2'!L90 -> 0 | M109: ='CF1'!M90+'CF2'!M90 -> 0 | ... BM109: ='CF1'!BM90+'CF2'!BM90 -> 0
C110: УПЛАТА | D110: млн. руб. | E110: =SUM(F110:BM110) -> -1297.042 | F110: ='CF1'!F91+'CF2'!F91 -> 0 | G110: ='CF1'!G91+'CF2'!G91 -> 0 | H110: ='CF1'!H91+'CF2'!H91 -> 0 | I110: ='CF1'!I91+'CF2'!I91 -> 0 | J110: ='CF1'!J91+'CF2'!J91 -> 0 | K110: ='CF1'!K91+'CF2'!K91 -> 0 | L110: ='CF1'!L91+'CF2'!L91 -> 0 | M110: ='CF1'!M91+'CF2'!M91 -> 0 | ... BM110: ='CF1'!BM91+'CF2'!BM91 -> 0
C111: НАЧИСЛЕНИЕ КАП. | D111: млн. руб. | E111: =SUM(F111:BM111) -> 154.99629 | F111: ='CF1'!F92+'CF2'!F92 -> 0 | G111: ='CF1'!G92+'CF2'!G92 -> 0 | H111: ='CF1'!H92+'CF2'!H92 -> 0 | I111: ='CF1'!I92+'CF2'!I92 -> 0 | J111: ='CF1'!J92+'CF2'!J92 -> 0 | K111: ='CF1'!K92+'CF2'!K92 -> 0 | L111: ='CF1'!L92+'CF2'!L92 -> 0 | M111: ='CF1'!M92+'CF2'!M92 -> 0 | ... BM111: ='CF1'!BM92+'CF2'!BM92 -> 0
C112: УПЛАТА КАП. | D112: млн. руб. | E112: =SUM(F112:BM112) -> -154.99629 | F112: ='CF1'!F93+'CF2'!F93 -> 0 | G112: ='CF1'!G93+'CF2'!G93 -> 0 | H112: ='CF1'!H93+'CF2'!H93 -> 0 | I112: ='CF1'!I93+'CF2'!I93 -> 0 | J112: ='CF1'!J93+'CF2'!J93 -> 0 | K112: ='CF1'!K93+'CF2'!K93 -> 0 | L112: ='CF1'!L93+'CF2'!L93 -> 0 | M112: ='CF1'!M93+'CF2'!M93 -> 0 | ... BM112: ='CF1'!BM93+'CF2'!BM93 -> 0
...

Sheet CF1
B2: CF проекта | C2: ОЧЕРЕДЬ | D2: 1
F4: =IF((EOMONTH(F5,-3)+1)='DB1'!$U$25,"РнС",IF('CF1'!F5='DB1'!$U$27,"РнВ","")) | G4: =IF((EOMONTH(G5,-3)+1)='DB1'!$U$25,"РнС",IF('CF1'!G5='DB1'!$U$27,"РнВ","")) | H4: =IF((EOMONTH(H5,-3)+1)='DB1'!$U$25,"РнС",IF('CF1'!H5='DB1'!$U$27,"РнВ","")) | I4: =IF((EOMONTH(I5,-3)+1)='DB1'!$U$25,"РнС",IF('CF1'!I5='DB1'!$U$27,"РнВ","")) | J4: =IF((EOMONTH(J5,-3)+1)='DB1'!$U$25,"РнС",IF('CF1'!J5='DB1'!$U$27,"РнВ","")) | K4: =IF((EOMONTH(K5,-3)+1)='DB1'!$U$25,"РнС",IF('CF1'!K5='DB1'!$U$27,"РнВ","")) | L4: =IF((EOMONTH(L5,-3)+1)='DB1'!$U$25,"РнС",IF('CF1'!L5='DB1'!$U$27,"РнВ","")) | M4: =IF((EOMONTH(M5,-3)+1)='DB1'!$U$25,"РнС",IF('CF1'!M5='DB1'!$U$27,"РнВ","")) | ... AS4: =IF((EOMONTH(AS5,-3)+1)='DB1'!$U$25,"РнС",IF('CF1'!AS5='DB1'!$U$27,"РнВ",""))
B5: СТАТЬЯ | E5: ВСЕГО | F5: =EOMONTH('DB1'!$U$22,2) -> 45107 | G5: =EOMONTH(F5,3) -> 45199 | H5: =EOMONTH(G5,3) -> 45291 | I5: =EOMONTH(H5,3) -> 45382 | J5: =EOMONTH(I5,3) -> 45473 | K5: =EOMONTH(J5,3) -> 45565 | L5: =EOMONTH(K5,3) -> 45657 | M5: =EOMONTH(L5,3) -> 45747 | N5: =EOMONTH(M5,3) -> 45838 | ... BM5: =EOMONTH(BL5,3) -> 50495
F6: =CONCATENATE(IF(MONTH(F5)<=3,"1",IF(MONTH(F5)<=6,"2",IF(MONTH(F5)<=9,"3","4"))),"Q",YEAR(F5)) -> 2Q2023 | G6: =CONCATENATE(IF(MONTH(G5)<=3,"1",IF(MONTH(G5)<=6,"2",IF(MONTH(G5)<=9,"3","4"))),"Q",YEAR(G5)) -> 3Q2023 | H6: =CONCATENATE(IF(MONTH(H5)<=3,"1",IF(MONTH(H5)<=6,"2",IF(MONTH(H5)<=9,"3","4"))),"Q",YEAR(H5)) -> 4Q2023 | I6: =CONCATENATE(IF(MONTH(I5)<=3,"1",IF(MONTH(I5)<=6,"2",IF(MONTH(I5)<=9,"3","4"))),"Q",YEAR(I5)) -> 1Q2024 | J6: =CONCATENATE(IF(MONTH(J5)<=3,"1",IF(MONTH(J5)<=6,"2",IF(MONTH(J5)<=9,"3","4"))),"Q",YEAR(J5)) -> 2Q2024 | K6: =CONCATENATE(IF(MONTH(K5)<=3,"1",IF(MONTH(K5)<=6,"2",IF(MONTH(K5)<=9,"3","4"))),"Q",YEAR(K5)) -> 3Q2024 | L6: =CONCATENATE(IF(MONTH(L5)<=3,"1",IF(MONTH(L5)<=6,"2",IF(MONTH(L5)<=9,"3","4"))),"Q",YEAR(L5)) -> 4Q2024 | M6: =CONCATENATE(IF(MONTH(M5)<=3,"1",IF(MONTH(M5)<=6,"2",IF(MONTH(M5)<=9,"3","4"))),"Q",YEAR(M5)) -> 1Q2025 | ... BM6: =CONCATENATE(IF(MONTH(BM5)<=3,"1",IF(MONTH(BM5)<=6,"2",IF(MONTH(BM5)<=9,"3","4"))),"Q",YEAR(BM5)) -> 1Q2038
B7: КОНТРАКТАЦИЯ | D7: м2
B8: ='DB1'!B8 -> КВАРТИРЫ | D8: м2 | E8: =SUM(F8:BM8) -> 59425.363 | F8: ='TS1'!F40 -> 0 | G8: ='TS1'!G40 -> 0 | H8: ='TS1'!H40 -> 0 | I8: ='TS1'!I40 -> 0 | J8: ='TS1'!J40 -> 0 | K8: ='TS1'!K40 -> 0 | L8: ='TS1'!L40 -> 0 | M8: ='TS1'!M40 -> 0 | ... BM8: ='TS1'!BM40 -> 0
B9: ='DB1'!B9 -> АПАРТАМЕНТЫ | D9: м2 | E9: =SUM(F9:BM9) -> 0 | F9: ='TS1'!F44 -> 0 | G9: ='TS1'!G44 -> 0 | H9: ='TS1'!H44 -> 0 | I9: ='TS1'!I44 -> 0 | J9: ='TS1'!J44 -> 0 | K9: ='TS1'!K44 -> 0 | L9: ='TS1'!L44 -> 0 | M9: ='TS1'!M44 -> 0 | ... BM9: ='TS1'!BM44 -> 0
B10: ='DB1'!B10 -> ОФИСЫ | D10: м2 | E10: =SUM(F10:BM10) -> 0 | F10: ='TS1'!F46 -> 0 | G10: ='TS1'!G46 -> 0 | H10: ='TS1'!H46 -> 0 | I10: ='TS1'!I46 -> 0 | J10: ='TS1'!J46 -> 0 | K10: ='TS1'!K46 -> 0 | L10: ='TS1'!L46 -> 0 | M10: ='TS1'!M46 -> 0 | ... BM10: ='TS1'!BM46 -> 0
B11: ='DB1'!B11 -> РИТЕЙЛ | D11: м2 | E11: =SUM(F11:BM11) -> 3517.353 | F11: ='TS1'!F48 -> 0 | G11: ='TS1'!G48 -> 0 | H11: ='TS1'!H48 -> 0 | I11: ='TS1'!I48 -> 0 | J11: ='TS1'!J48 -> 0 | K11: ='TS1'!K48 -> 0 | L11: ='TS1'!L48 -> 0 | M11: ='TS1'!M48 -> 0 | ... BM11: ='TS1'!BM48 -> 0
B12: ='DB1'!B12 -> ТЦ | D12: м2 | E12: =SUM(F12:BM12) -> 0 | F12: ='TS1'!F50 -> 0 | G12: ='TS1'!G50 -> 0 | H12: ='TS1'!H50 -> 0 | I12: ='TS1'!I50 -> 0 | J12: ='TS1'!J50 -> 0 | K12: ='TS1'!K50 -> 0 | L12: ='TS1'!L50 -> 0 | M12: ='TS1'!M50 -> 0 | ... BM12: ='TS1'!BM50 -> 0
B13: ='DB1'!B16 -> ПАРКИНГ ЖИЛЬЕ | D13: шт. | E13: =SUM(F13:BM13) -> 599 | F13: ='TS1'!F52 -> 0 | G13: ='TS1'!G52 -> 0 | H13: ='TS1'!H52 -> 0 | I13: ='TS1'!I52 -> 0 | J13: ='TS1'!J52 -> 0 | K13: ='TS1'!K52 -> 0 | L13: ='TS1'!L52 -> 0 | M13: ='TS1'!M52 -> 0 | ... BM13: ='TS1'!BM52 -> 0
B14: ='DB1'!B17 -> ПАРКИНГ ОФИС | D14: шт. | E14: =SUM(F14:BM14) -> 0 | F14: ='TS1'!F54 -> 0 | G14: ='TS1'!G54 -> 0 | H14: ='TS1'!H54 -> 0 | I14: ='TS1'!I54 -> 0 | J14: ='TS1'!J54 -> 0 | K14: ='TS1'!K54 -> 0 | L14: ='TS1'!L54 -> 0 | M14: ='TS1'!M54 -> 0 | ... BM14: ='TS1'!BM54 -> 0
B16: ЦЕНЫ | D16: тыс. руб.
B17: =B8 -> КВАРТИРЫ | D17: тыс. руб. | E17: =IFERROR(E26/E8*1000,0) -> 630 | F17: =IF(F8=0,,IF(F8>0,IF(E17=0,'DB1'!$R$8*(1+'DB1'!$O$8),E17+'DB1'!$R$8*(100%-(1+'DB1'!$O$8))/SUMPRODUCT('TS1'!$F$43:$BM$43,'TS1'!$F$56:$BM$56)),)) -> 0 | G17: =IF(G8=0,,IF(G8>0,IF(F17=0,'DB1'!$R$8*(1+'DB1'!$O$8),F17+'DB1'!$R$8*(100%-(1+'DB1'!$O$8))/SUMPRODUCT('TS1'!$F$43:$BM$43,'TS1'!$F$56:$BM$56)),)) -> 0 | H17: =IF(H8=0,,IF(H8>0,IF(G17=0,'DB1'!$R$8*(1+'DB1'!$O$8),G17+'DB1'!$R$8*(100%-(1+'DB1'!$O$8))/SUMPRODUCT('TS1'!$F$43:$BM$43,'TS1'!$F$56:$BM$56)),)) -> 0 | I17: =IF(I8=0,,IF(I8>0,IF(H17=0,'DB1'!$R$8*(1+'DB1'!$O$8),H17+'DB1'!$R$8*(100%-(1+'DB1'!$O$8))/SUMPRODUCT('TS1'!$F$43:$BM$43,'TS1'!$F$56:$BM$56)),)) -> 0 | J17: =IF(J8=0,,IF(J8>0,IF(I17=0,'DB1'!$R$8*(1+'DB1'!$O$8),I17+'DB1'!$R$8*(100%-(1+'DB1'!$O$8))/SUMPRODUCT('TS1'!$F$43:$BM$43,'TS1'!$F$56:$BM$56)),)) -> 0 | K17: =IF(K8=0,,IF(K8>0,IF(J17=0,'DB1'!$R$8*(1+'DB1'!$O$8),J17+'DB1'!$R$8*(100%-(1+'DB1'!$O$8))/SUMPRODUCT('TS1'!$F$43:$BM$43,'TS1'!$F$56:$BM$56)),)) -> 0 | L17: =IF(L8=0,,IF(L8>0,IF(K17=0,'DB1'!$R$8*(1+'DB1'!$O$8),K17+'DB1'!$R$8*(100%-(1+'DB1'!$O$8))/SUMPRODUCT('TS1'!$F$43:$BM$43,'TS1'!$F$56:$BM$56)),)) -> 0 | M17: =IF(M8=0,,IF(M8>0,IF(L17=0,'DB1'!$R$8*(1+'DB1'!$O$8),L17+'DB1'!$R$8*(100%-(1+'DB1'!$O$8))/SUMPRODUCT('TS1'!$F$43:$BM$43,'TS1'!$F$56:$BM$56)),)) -> 0 | N17: =IF(N8>0,'TS1'!N42,0) -> 0 | O17: =IF(O8>0,'TS1'!O42,0) -> 0 | P17: =IF(P8>0,'TS1'!P42,0) -> 0 | Q17: =IF(Q8>0,'TS1'!Q42,0) -> 0 | R17: =IF(R8>0,'TS1'!R42,0) -> 0 | S17: =IF(S8>0,'TS1'!S42,0) -> 0 | T17: =IF(T8>0,'TS1'!T42,0) -> 522.9 | U17: =IF(U8>0,'TS1'!U42,0) -> 534.28376 | ... BM17: =IF(BM8>0,'TS1'!BM42,0) -> 0
B18: =B9 -> АПАРТАМЕНТЫ | D18: тыс. руб. | E18: =IFERROR(E27/E9*1000,0) -> 0 | F18: =IF(F9=0,,IF(F9>0,IF(E18=0,'DB1'!$R$9*(1+'DB1'!$O$9),E18+'DB1'!$R$9*(100%-(1+'DB1'!$O$9))/SUMPRODUCT('TS1'!$F$45:$BM$45,'TS1'!$F$57:$BM$57)),)) -> 0 | G18: =IF(G9=0,,IF(G9>0,IF(F18=0,'DB1'!$R$9*(1+'DB1'!$O$9),F18+'DB1'!$R$9*(100%-(1+'DB1'!$O$9))/SUMPRODUCT('TS1'!$F$45:$BM$45,'TS1'!$F$57:$BM$57)),)) -> 0 | H18: =IF(H9=0,,IF(H9>0,IF(G18=0,'DB1'!$R$9*(1+'DB1'!$O$9),G18+'DB1'!$R$9*(100%-(1+'DB1'!$O$9))/SUMPRODUCT('TS1'!$F$45:$BM$45,'TS1'!$F$57:$BM$57)),)) -> 0 | I18: =IF(I9=0,,IF(I9>0,IF(H18=0,'DB1'!$R$9*(1+'DB1'!$O$9),H18+'DB1'!$R$9*(100%-(1+'DB1'!$O$9))/SUMPRODUCT('TS1'!$F$45:$BM$45,'TS1'!$F$57:$BM$57)),)) -> 0 | J18: =IF(J9=0,,IF(J9>0,IF(I18=0,'DB1'!$R$9*(1+'DB1'!$O$9),I18+'DB1'!$R$9*(100%-(1+'DB1'!$O$9))/SUMPRODUCT('TS1'!$F$45:$BM$45,'TS1'!$F$57:$BM$57)),)) -> 0 | K18: =IF(K9=0,,IF(K9>0,IF(J18=0,'DB1'!$R$9*(1+'DB1'!$O$9),J18+'DB1'!$R$9*(100%-(1+'DB1'!$O$9))/SUMPRODUCT('TS1'!$F$45:$BM$45,'TS1'!$F$57:$BM$57)),)) -> 0 | L18: =IF(L9=0,,IF(L9>0,IF(K18=0,'DB1'!$R$9*(1+'DB1'!$O$9),K18+'DB1'!$R$9*(100%-(1+'DB1'!$O$9))/SUMPRODUCT('TS1'!$F$45:$BM$45,'TS1'!$F$57:$BM$57)),)) -> 0 | M18: =IF(M9=0,,IF(M9>0,IF(L18=0,'DB1'!$R$9*(1+'DB1'!$O$9),L18+'DB1'!$R$9*(100%-(1+'DB1'!$O$9))/SUMPRODUCT('TS1'!$F$45:$BM$45,'TS1'!$F$57:$BM$57)),)) -> 0 | ... BM18: =IF(BM9=0,,IF(BM9>0,IF(BL18=0,'DB1'!$R$9*(1+'DB1'!$O$9),BL18+'DB1'!$R$9*(100%-(1+'DB1'!$O$9))/SUMPRODUCT('TS1'!$F$45:$BM$45,'TS1'!$F$57:$BM$57)),)) -> 0
B19: =B10 -> ОФИСЫ | D19: тыс. руб. | E19: =IFERROR(E28/E10*1000,0) -> 0 | F19: =IF(F10=0,,IF(F10>0,IF(E19=0,'DB1'!$R$10*(1+'DB1'!$O$10),E19+'DB1'!$R$10*(100%-(1+'DB1'!$O$10))/SUMPRODUCT('TS1'!$F$47:$BM$47,'TS1'!$F$58:$BM$58)),)) -> 0 | G19: =IF(G10=0,,IF(G10>0,IF(F19=0,'DB1'!$R$10*(1+'DB1'!$O$10),F19+'DB1'!$R$10*(100%-(1+'DB1'!$O$10))/SUMPRODUCT('TS1'!$F$47:$BM$47,'TS1'!$F$58:$BM$58)),)) -> 0 | H19: =IF(H10=0,,IF(H10>0,IF(G19=0,'DB1'!$R$10*(1+'DB1'!$O$10),G19+'DB1'!$R$10*(100%-(1+'DB1'!$O$10))/SUMPRODUCT('TS1'!$F$47:$BM$47,'TS1'!$F$58:$BM$58)),)) -> 0 | I19: =IF(I10=0,,IF(I10>0,IF(H19=0,'DB1'!$R$10*(1+'DB1'!$O$10),H19+'DB1'!$R$10*(100%-(1+'DB1'!$O$10))/SUMPRODUCT('TS1'!$F$47:$BM$47,'TS1'!$F$58:$BM$58)),)) -> 0 | J19: =IF(J10=0,,IF(J10>0,IF(I19=0,'DB1'!$R$10*(1+'DB1'!$O$10),I19+'DB1'!$R$10*(100%-(1+'DB1'!$O$10))/SUMPRODUCT('TS1'!$F$47:$BM$47,'TS1'!$F$58:$BM$58)),)) -> 0 | K19: =IF(K10=0,,IF(K10>0,IF(J19=0,'DB1'!$R$10*(1+'DB1'!$O$10),J19+'DB1'!$R$10*(100%-(1+'DB1'!$O$10))/SUMPRODUCT('TS1'!$F$47:$BM$47,'TS1'!$F$58:$BM$58)),)) -> 0 | L19: =IF(L10=0,,IF(L10>0,IF(K19=0,'DB1'!$R$10*(1+'DB1'!$O$10),K19+'DB1'!$R$10*(100%-(1+'DB1'!$O$10))/SUMPRODUCT('TS1'!$F$47:$BM$47,'TS1'!$F$58:$BM$58)),)) -> 0 | M19: =IF(M10=0,,IF(M10>0,IF(L19=0,'DB1'!$R$10*(1+'DB1'!$O$10),L19+'DB1'!$R$10*(100%-(1+'DB1'!$O$10))/SUMPRODUCT('TS1'!$F$47:$BM$47,'TS1'!$F$58:$BM$58)),)) -> 0 | ... BM19: =IF(BM10=0,,IF(BM10>0,IF(BL19=0,'DB1'!$R$10*(1+'DB1'!$O$10),BL19+'DB1'!$R$10*(100%-(1+'DB1'!$O$10))/SUMPRODUCT('TS1'!$F$47:$BM$47,'TS1'!$F$58:$BM$58)),)) -> 0
B20: =B11 -> РИТЕЙЛ | D20: тыс. руб. | E20: =IFERROR(E29/E11*1000,0) -> 700 | F20: =IF(F11>0,'DB1'!$R$11,0) -> 0 | G20: =IF(G11>0,'DB1'!$R$11,0) -> 0 | H20: =IF(H11>0,'DB1'!$R$11,0) -> 0 | I20: =IF(I11>0,'DB1'!$R$11,0) -> 0 | J20: =IF(J11>0,'DB1'!$R$11,0) -> 0 | K20: =IF(K11>0,'DB1'!$R$11,0) -> 0 | L20: =IF(L11>0,'DB1'!$R$11,0) -> 0 | M20: =IF(M11>0,'DB1'!$R$11,0) -> 0 | ... BM20: =IF(BM11>0,'DB1'!$R$11,0) -> 0
B21: =B12 -> ТЦ | D21: тыс. руб. | E21: =IFERROR(E30/E12*1000,0) -> 0 | F21: =IF(F12>0,'DB1'!$R$12,0) -> 0 | G21: =IF(G12>0,'DB1'!$R$12,0) -> 0 | H21: =IF(H12>0,'DB1'!$R$12,0) -> 0 | I21: =IF(I12>0,'DB1'!$R$12,0) -> 0 | J21: =IF(J12>0,'DB1'!$R$12,0) -> 0 | K21: =IF(K12>0,'DB1'!$R$12,0) -> 0 | L21: =IF(L12>0,'DB1'!$R$12,0) -> 0 | M21: =IF(M12>0,'DB1'!$R$12,0) -> 0 | ... BM21: =IF(BM12>0,'DB1'!$R$12,0) -> 0
B22: =B13 -> ПАРКИНГ ЖИЛЬЕ | D22: тыс. руб. | E22: =IFERROR(E31/E13*1000,0) -> 4500 | F22: =IF(F13=0,,IF(F13>0,IF(E22=0,'DB1'!$R$16*(1+'DB1'!$O$16),E22+'DB1'!$R$16*(100%-(1+'DB1'!$O$16))/SUMPRODUCT('TS1'!$F$53:$BM$53,'TS1'!$F$56:$BM$56)),)) -> 0 | G22: =IF(G13=0,,IF(G13>0,IF(F22=0,'DB1'!$R$16*(1+'DB1'!$O$16),F22+'DB1'!$R$16*(100%-(1+'DB1'!$O$16))/SUMPRODUCT('TS1'!$F$53:$BM$53,'TS1'!$F$56:$BM$56)),)) -> 0 | H22: =IF(H13=0,,IF(H13>0,IF(G22=0,'DB1'!$R$16*(1+'DB1'!$O$16),G22+'DB1'!$R$16*(100%-(1+'DB1'!$O$16))/SUMPRODUCT('TS1'!$F$53:$BM$53,'TS1'!$F$56:$BM$56)),)) -> 0 | I22: =IF(I13=0,,IF(I13>0,IF(H22=0,'DB1'!$R$16*(1+'DB1'!$O$16),H22+'DB1'!$R$16*(100%-(1+'DB1'!$O$16))/SUMPRODUCT('TS1'!$F$53:$BM$53,'TS1'!$F$56:$BM$56)),)) -> 0 | J22: =IF(J13=0,,IF(J13>0,IF(I22=0,'DB1'!$R$16*(1+'DB1'!$O$16),I22+'DB1'!$R$16*(100%-(1+'DB1'!$O$16))/SUMPRODUCT('TS1'!$F$53:$BM$53,'TS1'!$F$56:$BM$56)),)) -> 0 | K22: =IF(K13=0,,IF(K13>0,IF(J22=0,'DB1'!$R$16*(1+'DB1'!$O$16),J22+'DB1'!$R$16*(100%-(1+'DB1'!$O$16))/SUMPRODUCT('TS1'!$F$53:$BM$53,'TS1'!$F$56:$BM$56)),)) -> 0 | L22: =IF(L13=0,,IF(L13>0,IF(K22=0,'DB1'!$R$16*(1+'DB1'!$O$16),K22+'DB1'!$R$16*(100%-(1+'DB1'!$O$16))/SUMPRODUCT('TS1'!$F$53:$BM$53,'TS1'!$F$56:$BM$56)),)) -> 0 | M22: =IF(M13=0,,IF(M13>0,IF(L22=0,'DB1'!$R$16*(1+'DB1'!$O$16),L22+'DB1'!$R$16*(100%-(1+'DB1'!$O$16))/SUMPRODUCT('TS1'!$F$53:$BM$53,'TS1'!$F$56:$BM$56)),)) -> 0 | ... BM22: =IF(BM13=0,,IF(BM13>0,IF(BL22=0,'DB1'!$R$16*(1+'DB1'!$O$16),BL22+'DB1'!$R$16*(100%-(1+'DB1'!$O$16))/SUMPRODUCT('TS1'!$F$53:$BM$53,'TS1'!$F$56:$BM$56)),)) -> 0
B23: =B14 -> ПАРКИНГ ОФИС | D23: тыс. руб. | E23: =IFERROR(E32/E14*1000,0) -> 0 | G23: =IF(G14=0,,IF(G14>0,IF(F23=0,'DB1'!$R$17*(1+'DB1'!$O$17),F23+'DB1'!$R$17*(100%-(1+'DB1'!$O$17))/SUMPRODUCT('TS1'!$F$55:$BM$55,'TS1'!$F$58:$BM$58)),))*1000 -> 0 | H23: =IF(H14=0,,IF(H14>0,IF(G23=0,'DB1'!$R$17*(1+'DB1'!$O$17),G23+'DB1'!$R$17*(100%-(1+'DB1'!$O$17))/SUMPRODUCT('TS1'!$F$55:$BM$55,'TS1'!$F$58:$BM$58)),)) -> 0 | I23: =IF(I14=0,,IF(I14>0,IF(H23=0,'DB1'!$R$17*(1+'DB1'!$O$17),H23+'DB1'!$R$17*(100%-(1+'DB1'!$O$17))/SUMPRODUCT('TS1'!$F$55:$BM$55,'TS1'!$F$58:$BM$58)),)) -> 0 | J23: =IF(J14=0,,IF(J14>0,IF(I23=0,'DB1'!$R$17*(1+'DB1'!$O$17),I23+'DB1'!$R$17*(100%-(1+'DB1'!$O$17))/SUMPRODUCT('TS1'!$F$55:$BM$55,'TS1'!$F$58:$BM$58)),)) -> 0 | K23: =IF(K14=0,,IF(K14>0,IF(J23=0,'DB1'!$R$17*(1+'DB1'!$O$17),J23+'DB1'!$R$17*(100%-(1+'DB1'!$O$17))/SUMPRODUCT('TS1'!$F$55:$BM$55,'TS1'!$F$58:$BM$58)),)) -> 0 | L23: =IF(L14=0,,IF(L14>0,IF(K23=0,'DB1'!$R$17*(1+'DB1'!$O$17),K23+'DB1'!$R$17*(100%-(1+'DB1'!$O$17))/SUMPRODUCT('TS1'!$F$55:$BM$55,'TS1'!$F$58:$BM$58)),)) -> 0 | M23: =IF(M14=0,,IF(M14>0,IF(L23=0,'DB1'!$R$17*(1+'DB1'!$O$17),L23+'DB1'!$R$17*(100%-(1+'DB1'!$O$17))/SUMPRODUCT('TS1'!$F$55:$BM$55,'TS1'!$F$58:$BM$58)),)) -> 0 | N23: =IF(N14=0,,IF(N14>0,IF(M23=0,'DB1'!$R$17*(1+'DB1'!$O$17),M23+'DB1'!$R$17*(100%-(1+'DB1'!$O$17))/SUMPRODUCT('TS1'!$F$55:$BM$55,'TS1'!$F$58:$BM$58)),)) -> 0 | O23: =IF(O14=0,,IF(O14>0,IF(N23=0,'DB1'!$R$17*(1+'DB1'!$O$17),N23+'DB1'!$R$17*(100%-(1+'DB1'!$O$17))/SUMPRODUCT('TS1'!$F$55:$BM$55,'TS1'!$F$58:$BM$58)),)) -> 0 | ... BM23: =IF(BM14=0,,IF(BM14>0,IF(BL23=0,'DB1'!$R$17*(1+'DB1'!$O$17),BL23+'DB1'!$R$17*(100%-(1+'DB1'!$O$17))/SUMPRODUCT('TS1'!$F$55:$BM$55,'TS1'!$F$58:$BM$58)),)) -> 0
B25: КОНТРАКТАЦИЯ | D25: млн. руб. | E25: =SUM(F25:BM25) -> 42595.626 | F25: =SUM(F26:F32) -> 0 | G25: =SUM(G26:G32) -> 0 | H25: =SUM(H26:H32) -> 0 | I25: =SUM(I26:I32) -> 0 | J25: =SUM(J26:J32) -> 0 | K25: =SUM(K26:K32) -> 0 | L25: =SUM(L26:L32) -> 0 | M25: =SUM(M26:M32) -> 0 | ... BM25: =SUM(BM26:BM32) -> 0
B26: =B17 -> КВАРТИРЫ | D26: млн. руб. | E26: =SUM(F26:BM26) -> 37437.979 | F26: =F8*F17/10^3 -> 0 | G26: =G8*G17/10^3 -> 0 | H26: =H8*H17/10^3 -> 0 | I26: =I8*I17/10^3 -> 0 | J26: =J8*J17/10^3 -> 0 | K26: =K8*K17/10^3 -> 0 | L26: =L8*L17/10^3 -> 0 | M26: =M8*M17/10^3 -> 0 | ... BM26: =BM8*BM17/10^3 -> 0
B27: =B18 -> АПАРТАМЕНТЫ | D27: млн. руб. | E27: =SUM(F27:BM27) -> 0 | F27: =F9*F18/10^3 -> 0 | G27: =G9*G18/10^3 -> 0 | H27: =H9*H18/10^3 -> 0 | I27: =I9*I18/10^3 -> 0 | J27: =J9*J18/10^3 -> 0 | K27: =K9*K18/10^3 -> 0 | L27: =L9*L18/10^3 -> 0 | M27: =M9*M18/10^3 -> 0 | ... BM27: =BM9*BM18/10^3 -> 0
B28: =B19 -> ОФИСЫ | D28: млн. руб. | E28: =SUM(F28:BM28) -> 0 | F28: =F10*F19/10^3 -> 0 | G28: =G10*G19/10^3 -> 0 | H28: =H10*H19/10^3 -> 0 | I28: =I10*I19/10^3 -> 0 | J28: =J10*J19/10^3 -> 0 | K28: =K10*K19/10^3 -> 0 | L28: =L10*L19/10^3 -> 0 | M28: =M10*M19/10^3 -> 0 | ... BM28: =BM10*BM19/10^3 -> 0
B29: =B20 -> РИТЕЙЛ | D29: млн. руб. | E29: =SUM(F29:BM29) -> 2462.1471 | F29: =F11*F20/10^3 -> 0 | G29: =G11*G20/10^3 -> 0 | H29: =H11*H20/10^3 -> 0 | I29: =I11*I20/10^3 -> 0 | J29: =J11*J20/10^3 -> 0 | K29: =K11*K20/10^3 -> 0 | L29: =L11*L20/10^3 -> 0 | M29: =M11*M20/10^3 -> 0 | ... BM29: =BM11*BM20/10^3 -> 0
B30: =B21 -> ТЦ | D30: млн. руб. | E30: =SUM(F30:BM30) -> 0 | F30: =F12*F21/10^3 -> 0 | G30: =G12*G21/10^3 -> 0 | H30: =H12*H21/10^3 -> 0 | I30: =I12*I21/10^3 -> 0 | J30: =J12*J21/10^3 -> 0 | K30: =K12*K21/10^3 -> 0 | L30: =L12*L21/10^3 -> 0 | M30: =M12*M21/10^3 -> 0 | ... BM30: =BM12*BM21/10^3 -> 0
B31: =B22 -> ПАРКИНГ ЖИЛЬЕ | D31: млн. руб. | E31: =SUM(F31:BM31) -> 2695.5 | F31: =F13*F22/10^3 -> 0 | G31: =G13*G22/10^3 -> 0 | H31: =H13*H22/10^3 -> 0 | I31: =I13*I22/10^3 -> 0 | J31: =J13*J22/10^3 -> 0 | K31: =K13*K22/10^3 -> 0 | L31: =L13*L22/10^3 -> 0 | M31: =M13*M22/10^3 -> 0 | ... BM31: =BM13*BM22/10^3 -> 0
B32: =B23 -> ПАРКИНГ ОФИС | D32: млн. руб. | E32: =SUM(F32:BM32) -> 0 | F32: =F14*F23/10^3 -> 0 | G32: =G14*G23/10^3 -> 0 | H32: =H14*H23/10^3 -> 0 | I32: =I14*I23/10^3 -> 0 | J32: =J14*J23/10^3 -> 0 | K32: =K14*K23/10^3 -> 0 | L32: =L14*L23/10^3 -> 0 | M32: =M14*M23/10^3 -> 0 | ... BM32: =BM14*BM23/10^3 -> 0
B34: ПОСТУПЛЕНИЯ (до РнВ на эскроу) | D34: млн. руб. | E34: =SUM(F34:BM34) -> 42595.626 | G34: =IF(SUM($E$175:F175)>0,SUM($F$35:G35,$F$42:G42,$F$43:G43,$F$44:G44,$F$45:G45,$F$46:G46,)-SUM(F$34:$F34),0) -> 0 | H34: =IF(SUM($E$175:G175)>0,SUM($F$35:H35,$F$42:H42,$F$43:H43,$F$44:H44,$F$45:H45,$F$46:H46,)-SUM($F$34:G34),0) -> 0 | I34: =IF(SUM($E$175:H175)>0,SUM($F$35:I35,$F$42:I42,$F$43:I43,$F$44:I44,$F$45:I45,$F$46:I46,)-SUM($F$34:H34),0) -> 0 | J34: =IF(SUM($E$175:I175)>0,SUM($F$35:J35,$F$42:J42,$F$43:J43,$F$44:J44,$F$45:J45,$F$46:J46,)-SUM($F$34:I34),0) -> 0 | K34: =IF(SUM($E$175:J175)>0,SUM($F$35:K35,$F$42:K42,$F$43:K43,$F$44:K44,$F$45:K45,$F$46:K46,)-SUM($F$34:J34),0) -> 0 | L34: =IF(SUM($E$175:K175)>0,SUM($F$35:L35,$F$42:L42,$F$43:L43,$F$44:L44,$F$45:L45,$F$46:L46,)-SUM($F$34:K34),0) -> 0 | M34: =IF(SUM($E$175:L175)>0,SUM($F$35:M35,$F$42:M42,$F$43:M43,$F$44:M44,$F$45:M45,$F$46:M46,)-SUM($F$34:L34),0) -> 0 | N34: =IF(SUM($E$175:M175)>0,SUM($F$35:N35,$F$42:N42,$F$43:N43,$F$44:N44,$F$45:N45,$F$46:N46,)-SUM($F$34:M34),0) -> 0 | O34: =IF(SUM($E$175:N175)>0,SUM($F$35:O35,$F$42:O42,$F$43:O43,$F$44:O44,$F$45:O45,$F$46:O46,)-SUM($F$34:N34),0) -> 0 | ... BM34: =IF(SUM($E$175:BL175)>0,SUM($F$35:BM35,$F$42:BM42,$F$43:BM43,$F$44:BM44,$F$45:BM45,$F$46:BM46,)-SUM($F$34:BL34),0) -> 0
B35: =B26 -> КВАРТИРЫ | D35: млн. руб. | E35: =SUM(F35:BM35) -> 37437.979 | G35: =(G26*'DB1'!$N8+SUM($F26:F26)-SUM('CF1'!$F35:F35)) -> 0 | H35: =(H26*'DB1'!$N8+SUM($F26:G26)-SUM('CF1'!$F35:G35)) -> 0 | I35: =(I26*'DB1'!$N8+SUM($F26:H26)-SUM('CF1'!$F35:H35)) -> 0 | J35: =(J26*'DB1'!$N8+SUM($F26:I26)-SUM('CF1'!$F35:I35)) -> 0 | K35: =(K26*'DB1'!$N8+SUM($F26:J26)-SUM('CF1'!$F35:J35)) -> 0 | L35: =(L26*'DB1'!$N8+SUM($F26:K26)-SUM('CF1'!$F35:K35)) -> 0 | M35: =(M26*'DB1'!$N8+SUM($F26:L26)-SUM('CF1'!$F35:L35)) -> 0 | N35: =N39+N41+N26*(1-N36) -> 0 | O35: =O39+O41+O26*(1-O36) -> 0 | P35: =P39+P41+P26*(1-P36) -> 0 | Q35: =Q39+Q41+Q26*(1-Q36) -> 0 | R35: =R39+R41+R26*(1-R36) -> 0 | S35: =S39+S41+S26*(1-S36) -> 0 | T35: =T39+T41+T26*(1-T36) -> 1069.5682 | U35: =U39+U41+U26*(1-U36) -> 1248.8459 | ... AD35: =AD39+AD41+AD26*(1-AD36) -> 2673.1754 | AE35: =(AE26*'DB1'!$N8+SUM($F26:AD26)-SUM('CF1'!$F35:AD35)) -> 1361.0549 | AF35: =(AF26*'DB1'!$N8+SUM($F26:AE26)-SUM('CF1'!$F35:AE35)) -> 2049.8883 | AG35: =(AG26*'DB1'!$N8+SUM($F26:AF26)-SUM('CF1'!$F35:AF35)) -> 2095.1129 | AH35: =(AH26*'DB1'!$N8+SUM($F26:AG26)-SUM('CF1'!$F35:AG35)) -> 2095.1129 | AI35: =(AI26*'DB1'!$N8+SUM($F26:AH26)-SUM('CF1'!$F35:AH35)) -> 2095.1129 | AJ35: =(AJ26*'DB1'!$N8+SUM($F26:AI26)-SUM('CF1'!$F35:AI35)) -> 2095.1129 | AK35: =(AK26*'DB1'!$N8+SUM($F26:AJ26)-SUM('CF1'!$F35:AJ35)) -> 2095.1129 | AL35: =(AL26*'DB1'!$N8+SUM($F26:AK26)-SUM('CF1'!$F35:AK35)) -> 2095.1129 | ... BM35: =(BM26*'DB1'!$N8+SUM($F26:BL26)-SUM('CF1'!$F35:BL35)) -> 0
C36: доля рассрочки | D36: % | S36: 0.5 | T36: 0.5 | U36: 0.4 | V36: 0.4 | W36: 0.4 | X36: 0.4 | Y36: 0.3 | Z36: 0.3 | AA36: 0.3 | AB36: 0.3 | AC36: 0.2 | AD36: 0.2 | AE36: 0.2 | AF36: 0.2
C37: рассрочка | D37: млн. руб. | N37: =N26*N36*N174 -> 0 | O37: =O26*O36*O174 -> 0 | P37: =P26*P36*P174 -> 0 | Q37: =Q26*Q36*Q174 -> 0 | R37: =R26*R36*R174 -> 0 | S37: =S26*S36*S174 -> 0 | T37: =T26*T36*T174 -> 784.35 | U37: =U26*U36*U174 -> 641.14052 | ... AH37: =AH26*AH36*AH174 -> 0
C38: ПВ | D38: % | S38: 0.3 | T38: 0.3 | U38: 0.3 | V38: 0.3 | W38: 0.3 | X38: 0.3 | Y38: 0.3 | Z38: 0.3 | AA38: 0.3 | AB38: 0.3 | AC38: 0.3 | AD38: 0.3 | AE38: 0.3 | AF38: 0.3
C39: ПВ | D39: млн. руб. | N39: =N37*N38 -> 0 | O39: =O37*O38 -> 0 | P39: =P37*P38 -> 0 | Q39: =Q37*Q38 -> 0 | R39: =R37*R38 -> 0 | S39: =S37*S38 -> 0 | T39: =T37*T38 -> 235.305 | U39: =U37*U38 -> 192.34216 | ... AD39: =AD37*AD38 -> 114.61278
C40: остаток | D40: млн. руб. | N40: =N37-N39 -> 0 | O40: =O37-O39 -> 0 | P40: =P37-P39 -> 0 | Q40: =Q37-Q39 -> 0 | R40: =R37-R39 -> 0 | S40: =S37-S39 -> 0 | T40: =T37-T39 -> 549.045 | U40: =U37-U39 -> 448.79836 | ... AD40: =AD37-AD39 -> 267.42981
C41: поступление остатка | D41: млн. руб. | N41: =N40/SUM(N174:$AD$174) -> 0 | O41: =O40/SUM(O174:$AD$174) -> 0 | P41: =P40/SUM(P174:$AD$174) -> 0 | Q41: =Q40/SUM(Q174:$AD$174) -> 0 | R41: =R40/SUM(R174:$AD$174) -> 0 | S41: =S40/SUM(S174:$AD$174) -> 0 | T41: =T40/SUM(T174:$AD$174)+S41 -> 49.913182 | U41: =U40/SUM(U174:$AD$174)+T41 -> 94.793018 | V41: =V40/SUM(V174:$AD$174)+U41 -> 145.72199 | W41: =W40/SUM(W174:$AD$174)+V41 -> 204.21237 | X41: =X40/SUM(X174:$AD$174)+W41 -> 272.42458 | Y41: =Y40/SUM(Y174:$AD$174)+X41 -> 333.30556 | Z41: =Z40/SUM(Z174:$AD$174)+Y41 -> 407.79708 | AA41: =AA40/SUM(AA174:$AD$174)+Z41 -> 502.70443 | ... AD41: =AD40/SUM(AD174:$AD$174)+AC41 -> 1030.3923
B42: =B27 -> АПАРТАМЕНТЫ | D42: млн. руб. | E42: =SUM(F42:BM42) -> 0 | G42: =(G27*'DB1'!$N9+SUM($F27:F27)-SUM('CF1'!$F42:F42)) -> 0 | H42: =(H27*'DB1'!$N9+SUM($F27:G27)-SUM('CF1'!$F42:G42)) -> 0 | I42: =(I27*'DB1'!$N9+SUM($F27:H27)-SUM('CF1'!$F42:H42)) -> 0 | J42: =(J27*'DB1'!$N9+SUM($F27:I27)-SUM('CF1'!$F42:I42)) -> 0 | K42: =(K27*'DB1'!$N9+SUM($F27:J27)-SUM('CF1'!$F42:J42)) -> 0 | L42: =(L27*'DB1'!$N9+SUM($F27:K27)-SUM('CF1'!$F42:K42)) -> 0 | M42: =(M27*'DB1'!$N9+SUM($F27:L27)-SUM('CF1'!$F42:L42)) -> 0 | N42: =(N27*'DB1'!$N9+SUM($F27:M27)-SUM('CF1'!$F42:M42)) -> 0 | ... BM42: =(BM27*'DB1'!$N9+SUM($F27:BL27)-SUM('CF1'!$F42:BL42)) -> 0
B43: =B28 -> ОФИСЫ | D43: млн. руб. | E43: =SUM(F43:BM43) -> 0 | G43: =(G28*'DB1'!$N10+SUM($F28:F28)-SUM('CF1'!$F43:F43)) -> 0 | H43: =(H28*'DB1'!$N10+SUM($F28:G28)-SUM('CF1'!$F43:G43)) -> 0 | I43: =(I28*'DB1'!$N10+SUM($F28:H28)-SUM('CF1'!$F43:H43)) -> 0 | J43: =(J28*'DB1'!$N10+SUM($F28:I28)-SUM('CF1'!$F43:I43)) -> 0 | K43: =(K28*'DB1'!$N10+SUM($F28:J28)-SUM('CF1'!$F43:J43)) -> 0 | L43: =(L28*'DB1'!$N10+SUM($F28:K28)-SUM('CF1'!$F43:K43)) -> 0 | M43: =(M28*'DB1'!$N10+SUM($F28:L28)-SUM('CF1'!$F43:L43)) -> 0 | N43: =(N28*'DB1'!$N10+SUM($F28:M28)-SUM('CF1'!$F43:M43)) -> 0 | ... BM43: =(BM28*'DB1'!$N10+SUM($F28:BL28)-SUM('CF1'!$F43:BL43)) -> 0
B44: =B29 -> РИТЕЙЛ | D44: млн. руб. | E44: =SUM(F44:BM44) -> 2462.1471 | G44: =DETAILS!L12/1000000 -> 0 | H44: =DETAILS!M12/1000000 -> 0 | I44: =DETAILS!N12/1000000 -> 0 | J44: =DETAILS!O12/1000000 -> 0 | K44: =DETAILS!P12/1000000 -> 0 | L44: =DETAILS!Q12/1000000 -> 0 | M44: =DETAILS!R12/1000000 -> 0 | N44: =DETAILS!S12/1000000 -> 0 | ... BM44: =DETAILS!BR12/1000000 -> 0
B45: =B30 -> ТЦ | D45: млн. руб. | E45: =SUM(F45:BM45) -> 0 | G45: =G30*'DB1'!$N$12+SUM($F30:F30)-SUM($F45:F45) -> 0 | H45: =H30*'DB1'!$N$12+SUM($F30:G30)-SUM($F45:G45) -> 0 | I45: =I30*'DB1'!$N$12+SUM($F30:H30)-SUM($F45:H45) -> 0 | J45: =J30*'DB1'!$N$12+SUM($F30:I30)-SUM($F45:I45) -> 0 | K45: =K30*'DB1'!$N$12+SUM($F30:J30)-SUM($F45:J45) -> 0 | L45: =L30*'DB1'!$N$12+SUM($F30:K30)-SUM($F45:K45) -> 0 | M45: =M30*'DB1'!$N$12+SUM($F30:L30)-SUM($F45:L45) -> 0 | N45: =N30*'DB1'!$N$12+SUM($F30:M30)-SUM($F45:M45) -> 0 | ... BM45: =BM30*'DB1'!$N$12+SUM($F30:BL30)-SUM($F45:BL45) -> 0
B46: =B31 -> ПАРКИНГ ЖИЛЬЕ | D46: млн. руб. | E46: =SUM(F46:BM46) -> 2695.5 | G46: =DETAILS!L14/1000000 -> 0 | H46: =DETAILS!M14/1000000 -> 0 | I46: =DETAILS!N14/1000000 -> 0 | J46: =DETAILS!O14/1000000 -> 0 | K46: =DETAILS!P14/1000000 -> 0 | L46: =DETAILS!Q14/1000000 -> 0 | M46: =DETAILS!R14/1000000 -> 0 | N46: =DETAILS!S14/1000000 -> 0 | ... BM46: =DETAILS!BR14/1000000 -> 0
B47: =B32 -> ПАРКИНГ ОФИС | D47: млн. руб. | E47: =SUM(F47:BM47) -> 0 | G47: =G32*'DB1'!$N$17+SUM($F32:F32)-SUM($F47:F47) -> 0 | H47: =H32*'DB1'!$N$17+SUM($F32:G32)-SUM($F47:G47) -> 0 | I47: =I32*'DB1'!$N$17+SUM($F32:H32)-SUM($F47:H47) -> 0 | J47: =J32*'DB1'!$N$17+SUM($F32:I32)-SUM($F47:I47) -> 0 | K47: =K32*'DB1'!$N$17+SUM($F32:J32)-SUM($F47:J47) -> 0 | L47: =L32*'DB1'!$N$17+SUM($F32:K32)-SUM($F47:K47) -> 0 | M47: =M32*'DB1'!$N$17+SUM($F32:L32)-SUM($F47:L47) -> 0 | N47: =N32*'DB1'!$N$17+SUM($F32:M32)-SUM($F47:M47) -> 0 | ... BM47: =BM32*'DB1'!$N$17+SUM($F32:BL32)-SUM($F47:BL47) -> 0
B50: РАСХОДЫ | D50: млн. руб. | E50: =SUM(F50:BM50) -> -3239.0461 | F50: =SUM(F53:F56) -> -0.18152286 | G50: =SUM(G51:G56) -> -0.55836329 | H50: =SUM(H51:H56) -> -0.28357 | I50: =SUM(I51:I56) -> -0.29047 | J50: =SUM(J51:J56) -> -0.33547 | K50: =SUM(K51:K56) -> -0.3448 | L50: =SUM(L51:L56) -> -0.63933562 | M50: =SUM(M51:M56) -> -0.68848 | N50: =SUM(N51:N56) -> -2.5783842 | ... BM50: =SUM(BM51:BM56) -> 0
B51: БРОКЕРИДЖ | D51: млн. руб. | E51: =SUM(G51:BM51) -> -1277.8688 | F51: =DETAILS!K95/1000000 -> 0 | G51: =DETAILS!L95/1000000 -> 0 | H51: =DETAILS!M95/1000000 -> 0 | I51: =DETAILS!N95/1000000 -> 0 | J51: =DETAILS!O95/1000000 -> 0 | K51: =DETAILS!P95/1000000 -> 0 | L51: =DETAILS!Q95/1000000 -> 0 | M51: =DETAILS!R95/1000000 -> 0 | ... BM51: =DETAILS!BR95/1000000 -> 0
B52: УПРАВЛЕНИЕ ПРОДАЖАМИ | D52: млн. руб. | E52: =SUM(G52:BM52) -> -511.14751 | F52: =DETAILS!K96/1000000 -> 0 | G52: =DETAILS!L96/1000000 -> 0 | H52: =DETAILS!M96/1000000 -> 0 | I52: =DETAILS!N96/1000000 -> 0 | J52: =DETAILS!O96/1000000 -> 0 | K52: =DETAILS!P96/1000000 -> 0 | L52: =DETAILS!Q96/1000000 -> 0 | M52: =DETAILS!R96/1000000 -> 0 | ... BM52: =DETAILS!BR96/1000000 -> 0
B53: РЕКЛАМА И МАРКЕТИНГ | D53: млн. руб. | E53: =SUM(F53:BM53) -> -1277.8688 | F53: =SUMIFS(DETAILS!K$107:K$122,DETAILS!$C$107:$C$122,'CF1'!$D$2)/1000000 -> 0 | G53: =SUMIFS(DETAILS!L$107:L$122,DETAILS!$C$107:$C$122,'CF1'!$D$2)/1000000 -> 0 | H53: =SUMIFS(DETAILS!M$107:M$122,DETAILS!$C$107:$C$122,'CF1'!$D$2)/1000000 -> 0 | I53: =SUMIFS(DETAILS!N$107:N$122,DETAILS!$C$107:$C$122,'CF1'!$D$2)/1000000 -> 0 | J53: =SUMIFS(DETAILS!O$107:O$122,DETAILS!$C$107:$C$122,'CF1'!$D$2)/1000000 -> 0 | K53: =SUMIFS(DETAILS!P$107:P$122,DETAILS!$C$107:$C$122,'CF1'!$D$2)/1000000 -> 0 | L53: =SUMIFS(DETAILS!Q$107:Q$122,DETAILS!$C$107:$C$122,'CF1'!$D$2)/1000000 -> 0 | M53: =SUMIFS(DETAILS!R$107:R$122,DETAILS!$C$107:$C$122,'CF1'!$D$2)/1000000 -> 0 | ... BM53: =SUMIFS(DETAILS!BR$107:BR$122,DETAILS!$C$107:$C$122,'CF1'!$D$2)/1000000 -> 0
B54: АРЕНДА ЗУ/НАЛОГ ЗУ | D54: млн. руб. | E54: =SUM(F54:BM54) -> -17.415831 | F54: =SUMIFS(DETAILS!K$269:K$276,DETAILS!$C$269:$C$276,'CF1'!$D$2)/10^6-F62 -> 0 | G54: =SUMIFS(DETAILS!L$269:L$276,DETAILS!$C$269:$C$276,'CF1'!$D$2)/10^6-G62 -> 0 | H54: =SUMIFS(DETAILS!M$269:M$276,DETAILS!$C$269:$C$276,'CF1'!$D$2)/10^6-H62 -> 0 | I54: =SUMIFS(DETAILS!N$269:N$276,DETAILS!$C$269:$C$276,'CF1'!$D$2)/10^6-I62 -> 0 | J54: =SUMIFS(DETAILS!O$269:O$276,DETAILS!$C$269:$C$276,'CF1'!$D$2)/10^6-J62 -> 0 | K54: =SUMIFS(DETAILS!P$269:P$276,DETAILS!$C$269:$C$276,'CF1'!$D$2)/10^6-K62 -> 0 | L54: =SUMIFS(DETAILS!Q$269:Q$276,DETAILS!$C$269:$C$276,'CF1'!$D$2)/10^6-L62 -> 0 | M54: =SUMIFS(DETAILS!R$269:R$276,DETAILS!$C$269:$C$276,'CF1'!$D$2)/10^6-M62 -> 0 | ... BM54: =SUMIFS(DETAILS!BR$269:BR$276,DETAILS!$C$269:$C$276,'CF1'!$D$2)/10^6-BM62 -> 0
B55: РЕГИСТРАЦИЯ ДОГОВОРОВ | D55: млн. руб. | E55: =SUM(F55:BM55) -> -76.745163 | F55: =DETAILS!K98/1000000 -> 0 | G55: =DETAILS!L98/1000000 -> 0 | H55: =DETAILS!M98/1000000 -> 0 | I55: =DETAILS!N98/1000000 -> 0 | J55: =DETAILS!O98/1000000 -> 0 | K55: =DETAILS!P98/1000000 -> 0 | L55: =DETAILS!Q98/1000000 -> 0 | M55: =DETAILS!R98/1000000 -> 0 | ... BM55: =DETAILS!BR98/1000000 -> 0
B56: АХР | D56: млн. руб. | E56: =SUM(F56:BM56) -> -78 | F56: =SUMIFS(DETAILS!K$47:K$93,DETAILS!$C$47:$C$93,1)/1000000 -> -0.18152286 | G56: =SUMIFS(DETAILS!L$47:L$93,DETAILS!$C$47:$C$93,1)/1000000 -> -0.55836329 | H56: =SUMIFS(DETAILS!M$47:M$93,DETAILS!$C$47:$C$93,1)/1000000 -> -0.28357 | I56: =SUMIFS(DETAILS!N$47:N$93,DETAILS!$C$47:$C$93,1)/1000000 -> -0.29047 | J56: =SUMIFS(DETAILS!O$47:O$93,DETAILS!$C$47:$C$93,1)/1000000 -> -0.33547 | K56: =SUMIFS(DETAILS!P$47:P$93,DETAILS!$C$47:$C$93,1)/1000000 -> -0.3448 | L56: =SUMIFS(DETAILS!Q$47:Q$93,DETAILS!$C$47:$C$93,1)/1000000 -> -0.63933562 | M56: =SUMIFS(DETAILS!R$47:R$93,DETAILS!$C$47:$C$93,1)/1000000 -> -0.68848 | ... BM56: =SUMIFS(DETAILS!BR$47:BR$93,DETAILS!$C$47:$C$93,1)/1000000 -> 0
B59: ИНВЕСТИЦИИ | D59: млн. руб. | E59: =SUM(F59:BM59) -> -25152.286 | F59: =SUM(F60:F74) -> 0 | G59: =SUM(G60:G74) -> 0 | H59: =SUM(H60:H74) -> 0 | I59: =SUM(I60:I74) -> 0 | J59: =SUM(J60:J74) -> 0 | K59: =SUM(K60:K74) -> 0 | L59: =SUM(L60:L74) -> 0 | M59: =SUM(M60:M74) -> 0 | ... BM59: =SUM(BM60:BM74) -> 0
B60: ВХОД | D60: млн. руб. | E60: =SUM(F60:BM60) -> -3314.8458 | F60: =SUMIFS(DETAILS!K$138:K$146,DETAILS!$C$138:$C$146,'CF1'!$D$2)/10^6 -> 0 | G60: =SUMIFS(DETAILS!L$138:L$146,DETAILS!$C$138:$C$146,'CF1'!$D$2)/10^6 -> 0 | H60: =SUMIFS(DETAILS!M$138:M$146,DETAILS!$C$138:$C$146,'CF1'!$D$2)/10^6 -> 0 | I60: =SUMIFS(DETAILS!N$138:N$146,DETAILS!$C$138:$C$146,'CF1'!$D$2)/10^6 -> 0 | J60: =SUMIFS(DETAILS!O$138:O$146,DETAILS!$C$138:$C$146,'CF1'!$D$2)/10^6 -> 0 | K60: =SUMIFS(DETAILS!P$138:P$146,DETAILS!$C$138:$C$146,'CF1'!$D$2)/10^6 -> 0 | L60: =SUMIFS(DETAILS!Q$138:Q$146,DETAILS!$C$138:$C$146,'CF1'!$D$2)/10^6 -> 0 | M60: =SUMIFS(DETAILS!R$138:R$146,DETAILS!$C$138:$C$146,'CF1'!$D$2)/10^6 -> 0 | ... BM60: =SUMIFS(DETAILS!BR$138:BR$146,DETAILS!$C$138:$C$146,'CF1'!$D$2)/10^6 -> 0
B61: ВРИ | D61: млн. руб. | E61: =SUM(F61:BM61) -> -2733.9729 | F61: =(DETAILS!K265+DETAILS!K266+DETAILS!K267)/1000000 -> 0 | G61: =(DETAILS!L265+DETAILS!L266+DETAILS!L267)/1000000 -> 0 | H61: =(DETAILS!M265+DETAILS!M266+DETAILS!M267)/1000000 -> 0 | I61: =(DETAILS!N265+DETAILS!N266+DETAILS!N267)/1000000 -> 0 | J61: =(DETAILS!O265+DETAILS!O266+DETAILS!O267)/1000000 -> 0 | K61: =(DETAILS!P265+DETAILS!P266+DETAILS!P267)/1000000 -> 0 | L61: =(DETAILS!Q265+DETAILS!Q266+DETAILS!Q267)/1000000 -> 0 | M61: =(DETAILS!R265+DETAILS!R266+DETAILS!R267)/1000000 -> 0 | ... BM61: =(DETAILS!BR265+DETAILS!BR266+DETAILS!BR267)/1000000 -> 0
B62: АРЕНДА ЗУ/ПРОЧИЕ РАБОТЫ ПО ЗУ | D62: млн. руб. | E62: =SUM(F62:BM62) -> -121.85494 | F62: =SUMIFS(DETAILS!K$269:K$276,DETAILS!$C$269:$C$276,'CF1'!$D$2)/10^6*F174 -> 0 | G62: =SUMIFS(DETAILS!L$269:L$276,DETAILS!$C$269:$C$276,'CF1'!$D$2)/10^6*G174 -> 0 | H62: =SUMIFS(DETAILS!M$269:M$276,DETAILS!$C$269:$C$276,'CF1'!$D$2)/10^6*H174 -> 0 | I62: =SUMIFS(DETAILS!N$269:N$276,DETAILS!$C$269:$C$276,'CF1'!$D$2)/10^6*I174 -> 0 | J62: =SUMIFS(DETAILS!O$269:O$276,DETAILS!$C$269:$C$276,'CF1'!$D$2)/10^6*J174 -> 0 | K62: =SUMIFS(DETAILS!P$269:P$276,DETAILS!$C$269:$C$276,'CF1'!$D$2)/10^6*K174 -> 0 | L62: =SUMIFS(DETAILS!Q$269:Q$276,DETAILS!$C$269:$C$276,'CF1'!$D$2)/10^6*L174 -> 0 | M62: =SUMIFS(DETAILS!R$269:R$276,DETAILS!$C$269:$C$276,'CF1'!$D$2)/10^6*M174 -> 0 | ... BM62: =SUMIFS(DETAILS!BR$269:BR$276,DETAILS!$C$269:$C$276,'CF1'!$D$2)/10^6*BM174 -> 0
B63: ='DB1'!B31 -> ПРОЕКТИРОВАНИЕ (К+П+РД) | D63: млн. руб. | E63: =SUM(F63:BM63) -> -908.34544 | F63: =SUMIFS(DETAILS!K$148:K$222,DETAILS!$C$148:$C$222,'CF1'!$D$2)/10^6 -> 0 | G63: =SUMIFS(DETAILS!L$148:L$222,DETAILS!$C$148:$C$222,'CF1'!$D$2)/10^6 -> 0 | H63: =SUMIFS(DETAILS!M$148:M$222,DETAILS!$C$148:$C$222,'CF1'!$D$2)/10^6 -> 0 | I63: =SUMIFS(DETAILS!N$148:N$222,DETAILS!$C$148:$C$222,'CF1'!$D$2)/10^6 -> 0 | J63: =SUMIFS(DETAILS!O$148:O$222,DETAILS!$C$148:$C$222,'CF1'!$D$2)/10^6 -> 0 | K63: =SUMIFS(DETAILS!P$148:P$222,DETAILS!$C$148:$C$222,'CF1'!$D$2)/10^6 -> 0 | L63: =SUMIFS(DETAILS!Q$148:Q$222,DETAILS!$C$148:$C$222,'CF1'!$D$2)/10^6 -> 0 | M63: =SUMIFS(DETAILS!R$148:R$222,DETAILS!$C$148:$C$222,'CF1'!$D$2)/10^6 -> 0 | ... BM63: =SUMIFS(DETAILS!BR$148:BR$222,DETAILS!$C$148:$C$222,'CF1'!$D$2)/10^6 -> 0
B64: ='DB1'!B32 -> СОГЛАСОВАНИЯ | D64: млн. руб. | E64: =SUM(F64:BM64) -> -113.54318 | F64: =SUMIFS(DETAILS!K$224:K$263,DETAILS!$C$224:$C$263,'CF1'!$D$2)/10^6 -> 0 | G64: =SUMIFS(DETAILS!L$224:L$263,DETAILS!$C$224:$C$263,'CF1'!$D$2)/10^6 -> 0 | H64: =SUMIFS(DETAILS!M$224:M$263,DETAILS!$C$224:$C$263,'CF1'!$D$2)/10^6 -> 0 | I64: =SUMIFS(DETAILS!N$224:N$263,DETAILS!$C$224:$C$263,'CF1'!$D$2)/10^6 -> 0 | J64: =SUMIFS(DETAILS!O$224:O$263,DETAILS!$C$224:$C$263,'CF1'!$D$2)/10^6 -> 0 | K64: =SUMIFS(DETAILS!P$224:P$263,DETAILS!$C$224:$C$263,'CF1'!$D$2)/10^6 -> 0 | L64: =SUMIFS(DETAILS!Q$224:Q$263,DETAILS!$C$224:$C$263,'CF1'!$D$2)/10^6 -> 0 | M64: =SUMIFS(DETAILS!R$224:R$263,DETAILS!$C$224:$C$263,'CF1'!$D$2)/10^6 -> 0 | ... BM64: =SUMIFS(DETAILS!BR$224:BR$263,DETAILS!$C$224:$C$263,'CF1'!$D$2)/10^6 -> 0
B65: ='DB1'!B33 -> СМР жилье | D65: млн. руб. | E65: =SUM(F65:BM65) -> -15555.416 | F65: =SUMIFS(DETAILS!K$288:K$317,DETAILS!$C$288:$C$317,'CF1'!$D$2)/10^6 -> 0 | G65: =SUMIFS(DETAILS!L$288:L$317,DETAILS!$C$288:$C$317,'CF1'!$D$2)/10^6 -> 0 | H65: =SUMIFS(DETAILS!M$288:M$317,DETAILS!$C$288:$C$317,'CF1'!$D$2)/10^6 -> 0 | I65: =SUMIFS(DETAILS!N$288:N$317,DETAILS!$C$288:$C$317,'CF1'!$D$2)/10^6 -> 0 | J65: =SUMIFS(DETAILS!O$288:O$317,DETAILS!$C$288:$C$317,'CF1'!$D$2)/10^6 -> 0 | K65: =SUMIFS(DETAILS!P$288:P$317,DETAILS!$C$288:$C$317,'CF1'!$D$2)/10^6 -> 0 | L65: =SUMIFS(DETAILS!Q$288:Q$317,DETAILS!$C$288:$C$317,'CF1'!$D$2)/10^6 -> 0 | M65: =SUMIFS(DETAILS!R$288:R$317,DETAILS!$C$288:$C$317,'CF1'!$D$2)/10^6 -> 0 | ... BM65: =SUMIFS(DETAILS!BR$288:BR$317,DETAILS!$C$288:$C$317,'CF1'!$D$2)/10^6 -> 0
B66: ='DB1'!B34 -> СМР офисы | D66: млн. руб. | E66: =SUM(F66:BM66) -> 0 | F66: ='DB1'!$J$34*-'TS1'!F25 -> 0 | G66: ='DB1'!$J$34*-'TS1'!G25 -> 0 | H66: ='DB1'!$J$34*-'TS1'!H25 -> 0 | I66: ='DB1'!$J$34*-'TS1'!I25 -> 0 | J66: ='DB1'!$J$34*-'TS1'!J25 -> 0 | K66: ='DB1'!$J$34*-'TS1'!K25 -> 0 | L66: ='DB1'!$J$34*-'TS1'!L25 -> 0 | M66: ='DB1'!$J$34*-'TS1'!M25 -> 0 | ... BM66: ='DB1'!$J$34*-'TS1'!BM25 -> 0
B67: ='DB1'!B35 -> СМР ТЦ | D67: млн. руб. | E67: =SUM(F67:BM67) -> 0 | F67: ='DB1'!$J$35*-'TS1'!F25 -> 0 | G67: ='DB1'!$J$35*-'TS1'!G25 -> 0 | H67: ='DB1'!$J$35*-'TS1'!H25 -> 0 | I67: ='DB1'!$J$35*-'TS1'!I25 -> 0 | J67: ='DB1'!$J$35*-'TS1'!J25 -> 0 | K67: ='DB1'!$J$35*-'TS1'!K25 -> 0 | L67: ='DB1'!$J$35*-'TS1'!L25 -> 0 | M67: ='DB1'!$J$35*-'TS1'!M25 -> 0 | ... BM67: ='DB1'!$J$35*-'TS1'!BM25 -> 0
B68: ='DB1'!B36 -> СМР соц. объектов (компенсация) | D68: млн. руб. | E68: =SUM(F68:BM68) -> -294.48383 | F68: =SUMIFS(DETAILS!K$318:K$324,DETAILS!$C$318:$C$324,'CF1'!$D$2)/10^6 -> 0 | G68: =SUMIFS(DETAILS!L$318:L$324,DETAILS!$C$318:$C$324,'CF1'!$D$2)/10^6 -> 0 | H68: =SUMIFS(DETAILS!M$318:M$324,DETAILS!$C$318:$C$324,'CF1'!$D$2)/10^6 -> 0 | I68: =SUMIFS(DETAILS!N$318:N$324,DETAILS!$C$318:$C$324,'CF1'!$D$2)/10^6 -> 0 | J68: =SUMIFS(DETAILS!O$318:O$324,DETAILS!$C$318:$C$324,'CF1'!$D$2)/10^6 -> 0 | K68: =SUMIFS(DETAILS!P$318:P$324,DETAILS!$C$318:$C$324,'CF1'!$D$2)/10^6 -> 0 | L68: =SUMIFS(DETAILS!Q$318:Q$324,DETAILS!$C$318:$C$324,'CF1'!$D$2)/10^6 -> 0 | M68: =SUMIFS(DETAILS!R$318:R$324,DETAILS!$C$318:$C$324,'CF1'!$D$2)/10^6 -> 0 | ... BM68: =SUMIFS(DETAILS!BR$318:BR$324,DETAILS!$C$318:$C$324,'CF1'!$D$2)/10^6 -> 0
B69: ОТДЕЛКА | D69: млн. руб. | E69: =SUM(F69:BM69) -> 0
B70: СЕТИ | D70: млн. руб. | E70: =SUM(F70:BM70) -> -624.48749 | F70: =SUMIFS(DETAILS!K$326:K$342,DETAILS!$C$326:$C$342,'CF1'!$D$2)/10^6 -> 0 | G70: =SUMIFS(DETAILS!L$326:L$342,DETAILS!$C$326:$C$342,'CF1'!$D$2)/10^6 -> 0 | H70: =SUMIFS(DETAILS!M$326:M$342,DETAILS!$C$326:$C$342,'CF1'!$D$2)/10^6 -> 0 | I70: =SUMIFS(DETAILS!N$326:N$342,DETAILS!$C$326:$C$342,'CF1'!$D$2)/10^6 -> 0 | J70: =SUMIFS(DETAILS!O$326:O$342,DETAILS!$C$326:$C$342,'CF1'!$D$2)/10^6 -> 0 | K70: =SUMIFS(DETAILS!P$326:P$342,DETAILS!$C$326:$C$342,'CF1'!$D$2)/10^6 -> 0 | L70: =SUMIFS(DETAILS!Q$326:Q$342,DETAILS!$C$326:$C$342,'CF1'!$D$2)/10^6 -> 0 | M70: =SUMIFS(DETAILS!R$326:R$342,DETAILS!$C$326:$C$342,'CF1'!$D$2)/10^6 -> 0 | ... BM70: =SUMIFS(DETAILS!BR$326:BR$342,DETAILS!$C$326:$C$342,'CF1'!$D$2)/10^6 -> 0
B71: СОДЕРЖАНИЕ ПЛОЩАДКИ | D71: млн. руб. | E71: =SUM(F71:BM71) -> -113.54318 | F71: =SUMIFS(DETAILS!K$344:K$359,DETAILS!$C$344:$C$359,'CF1'!$D$2)/10^6 -> 0 | G71: =SUMIFS(DETAILS!L$344:L$359,DETAILS!$C$344:$C$359,'CF1'!$D$2)/10^6 -> 0 | H71: =SUMIFS(DETAILS!M$344:M$359,DETAILS!$C$344:$C$359,'CF1'!$D$2)/10^6 -> 0 | I71: =SUMIFS(DETAILS!N$344:N$359,DETAILS!$C$344:$C$359,'CF1'!$D$2)/10^6 -> 0 | J71: =SUMIFS(DETAILS!O$344:O$359,DETAILS!$C$344:$C$359,'CF1'!$D$2)/10^6 -> 0 | K71: =SUMIFS(DETAILS!P$344:P$359,DETAILS!$C$344:$C$359,'CF1'!$D$2)/10^6 -> 0 | L71: =SUMIFS(DETAILS!Q$344:Q$359,DETAILS!$C$344:$C$359,'CF1'!$D$2)/10^6 -> 0 | M71: =SUMIFS(DETAILS!R$344:R$359,DETAILS!$C$344:$C$359,'CF1'!$D$2)/10^6 -> 0 | ... BM71: =SUMIFS(DETAILS!BR$344:BR$359,DETAILS!$C$344:$C$359,'CF1'!$D$2)/10^6 -> 0
B72: МОНИТОРИНГИ | D72: млн. руб. | E72: =SUM(F72:BM72) -> -283.85795 | F72: =SUMIFS(DETAILS!K$373:K$393,DETAILS!$C$373:$C$393,'CF1'!$D$2)/10^6 -> 0 | G72: =SUMIFS(DETAILS!L$373:L$393,DETAILS!$C$373:$C$393,'CF1'!$D$2)/10^6 -> 0 | H72: =SUMIFS(DETAILS!M$373:M$393,DETAILS!$C$373:$C$393,'CF1'!$D$2)/10^6 -> 0 | I72: =SUMIFS(DETAILS!N$373:N$393,DETAILS!$C$373:$C$393,'CF1'!$D$2)/10^6 -> 0 | J72: =SUMIFS(DETAILS!O$373:O$393,DETAILS!$C$373:$C$393,'CF1'!$D$2)/10^6 -> 0 | K72: =SUMIFS(DETAILS!P$373:P$393,DETAILS!$C$373:$C$393,'CF1'!$D$2)/10^6 -> 0 | L72: =SUMIFS(DETAILS!Q$373:Q$393,DETAILS!$C$373:$C$393,'CF1'!$D$2)/10^6 -> 0 | M72: =SUMIFS(DETAILS!R$373:R$393,DETAILS!$C$373:$C$393,'CF1'!$D$2)/10^6 -> 0 | ... BM72: =SUMIFS(DETAILS!BR$373:BR$393,DETAILS!$C$373:$C$393,'CF1'!$D$2)/10^6 -> 0
B73: УПРАВЛЕНИЕ ПРОЕКТОМ + FINDERS FEE | D73: млн. руб. | E73: =SUM(F73:BM73) -> -730.06201 | F73: =SUMIFS(DETAILS!K$362:K$371,DETAILS!$C$362:$C$371,'CF1'!$D$2)/10^6 -> 0 | G73: =SUMIFS(DETAILS!L$362:L$371,DETAILS!$C$362:$C$371,'CF1'!$D$2)/10^6 -> 0 | H73: =SUMIFS(DETAILS!M$362:M$371,DETAILS!$C$362:$C$371,'CF1'!$D$2)/10^6 -> 0 | I73: =SUMIFS(DETAILS!N$362:N$371,DETAILS!$C$362:$C$371,'CF1'!$D$2)/10^6 -> 0 | J73: =SUMIFS(DETAILS!O$362:O$371,DETAILS!$C$362:$C$371,'CF1'!$D$2)/10^6 -> 0 | K73: =SUMIFS(DETAILS!P$362:P$371,DETAILS!$C$362:$C$371,'CF1'!$D$2)/10^6 -> 0 | L73: =SUMIFS(DETAILS!Q$362:Q$371,DETAILS!$C$362:$C$371,'CF1'!$D$2)/10^6 -> 0 | M73: =SUMIFS(DETAILS!R$362:R$371,DETAILS!$C$362:$C$371,'CF1'!$D$2)/10^6 -> 0 | ... BM73: =SUMIFS(DETAILS!BR$362:BR$371,DETAILS!$C$362:$C$371,'CF1'!$D$2)/10^6 -> 0
B74: НЕПРЕДВИДЕННЫЕ РАСХОДЫ | D74: млн. руб. | E74: =SUM(F74:BM74) -> -357.87353 | F74: =SUM(F63:F72)*'DB1'!$F$42 -> 0 | G74: =SUM(G63:G72)*'DB1'!$F$42 -> 0 | H74: =SUM(H63:H72)*'DB1'!$F$42 -> 0 | I74: =SUM(I63:I72)*'DB1'!$F$42 -> 0 | J74: =SUM(J63:J72)*'DB1'!$F$42 -> 0 | K74: =SUM(K63:K72)*'DB1'!$F$42 -> 0 | L74: =SUM(L63:L72)*'DB1'!$F$42 -> 0 | M74: =SUM(M63:M72)*'DB1'!$F$42 -> 0 | ... BM74: =SUM(BM63:BM72)*'DB1'!$F$42 -> 0
B76: ПОТОК ПРОЕКТА | D76: млн. руб. | E76: =SUM(F76:BM76) -> 14204.294 | F76: =F34+F50+F59 -> -0.18152286 | G76: =G34+G50+G59 -> -0.55836329 | H76: =H34+H50+H59 -> -0.28357 | I76: =I34+I50+I59 -> -0.29047 | J76: =J34+J50+J59 -> -0.33547 | K76: =K34+K50+K59 -> -0.3448 | L76: =L34+L50+L59 -> -0.63933562 | M76: =M34+M50+M59 -> -0.68848 | ... BM76: =BM34+BM50+BM59 -> 0
B79: ФИНАНСИРОВАНИЕ | D79: млн. руб. | E79: =SUM(F79:BM79) -> -6991.9295 | F79: =SUM(F81:F82,F85,F87:F88,F95:F96,F91,F93,F101,F99,F104,F106:F107) -> 0.2 | G79: =SUM(G81:G82,G85,G87:G88,G95:G96,G91,G93,G101,G99,G104,G106:G107) -> 0.6 | H79: =SUM(H81:H82,H85,H87:H88,H95:H96,H91,H93,H101,H99,H104,H106:H107) -> 0.6 | I79: =SUM(I81:I82,I85,I87:I88,I95:I96,I91,I93,I101,I99,I104,I106:I107) -> 0.3 | J79: =SUM(J81:J82,J85,J87:J88,J95:J96,J91,J93,J101,J99,J104,J106:J107) -> 0 | K79: =SUM(K81:K82,K85,K87:K88,K95:K96,K91,K93,K101,K99,K104,K106:K107) -> 0.8 | L79: =SUM(L81:L82,L85,L87:L88,L95:L96,L91,L93,L101,L99,L104,L106:L107) -> 0.6 | M79: =SUM(M81:M82,M85,M87:M88,M95:M96,M91,M93,M101,M99,M104,M106:M107) -> 1.07 | ... BM79: =SUM(BM81:BM82,BM85,BM87:BM88,BM95:BM96,BM91,BM93,BM101,BM99,BM104,BM106:BM107) -> 0
B80: АФ | D80: млн. руб. | E80: =SUM(F80:BM80) -> 0
C81: ПОСТУПЛЕНИЕ | D81: млн. руб. | E81: =SUM(F81:BM81) -> 382.3901 | F81: =SUMIFS(DETAILS!K$27:K$36,DETAILS!$C$27:$C$36,'CF1'!$D$2)/10^6 -> 0.2 | G81: =SUMIFS(DETAILS!L$27:L$36,DETAILS!$C$27:$C$36,'CF1'!$D$2)/10^6 -> 0.6 | H81: =SUMIFS(DETAILS!M$27:M$36,DETAILS!$C$27:$C$36,'CF1'!$D$2)/10^6 -> 0.6 | I81: =SUMIFS(DETAILS!N$27:N$36,DETAILS!$C$27:$C$36,'CF1'!$D$2)/10^6 -> 0.3 | J81: =SUMIFS(DETAILS!O$27:O$36,DETAILS!$C$27:$C$36,'CF1'!$D$2)/10^6 -> 0 | K81: =SUMIFS(DETAILS!P$27:P$36,DETAILS!$C$27:$C$36,'CF1'!$D$2)/10^6 -> 0.8 | L81: =SUMIFS(DETAILS!Q$27:Q$36,DETAILS!$C$27:$C$36,'CF1'!$D$2)/10^6 -> 0.6 | M81: =SUMIFS(DETAILS!R$27:R$36,DETAILS!$C$27:$C$36,'CF1'!$D$2)/10^6 -> 1.07 | N81: =-N76+M169 -> 78.2148 | O81: =-O76+N169 -> 133.15042 | P81: =IF(P60<>0,'DB1'!$O$27,0) -> 166.85488 | Q81: =IF(Q60<>0,'DB1'!$O$27,0) -> 0 | R81: =IF(R60<>0,'DB1'!$O$27,0) -> 0 | S81: =IF(S60<>0,'DB1'!$O$27,0) -> 0 | U81: =IF(U60<>0,'DB1'!$O$27,0) -> 0 | V81: =IF(V60<>0,'DB1'!$O$27,0) -> 0 | W81: =IF(W60<>0,'DB1'!$O$27,0) -> 0 | X81: =IF(X60<>0,'DB1'!$O$27,0) -> 0 | Y81: =IF(Y60<>0,'DB1'!$O$27,0) -> 0 | Z81: =IF(Z60<>0,'DB1'!$O$27,0) -> 0 | AA81: =IF(AA60<>0,'DB1'!$O$27,0) -> 0 | AB81: =IF(AB60<>0,'DB1'!$O$27,0) -> 0 | ... BM81: =IF(BM60<>0,'DB1'!$O$27,0) -> 0
C82: ПОГАШЕНИЕ | D82: млн. руб. | E82: =SUM(F82:BM82) -> -382.3901 | P82: =IF(P185>0,IF((SUM($F81:O$82)-P185)>0,-P185,-SUM($F81:O$82)),0) -> 0 | Q82: =IF(Q185>0,IF((SUM($F81:P$82)-Q185)>0,-Q185,-SUM($F81:P$82)),0) -> 0 | R82: =IF(R185>0,IF((SUM($F81:Q$82)-R185)>0,-R185,-SUM($F81:Q$82)),0) -> 0 | S82: =IF(S185>0,IF((SUM($F81:R$82)-S185)>0,-S185,-SUM($F81:R$82)),0) -> 0 | T82: =IF(T185>0,IF((SUM($F81:S$82)-T185)>0,-T185,-SUM($F81:S$82)),0) -> 0 | U82: =IF(U185>0,IF((SUM($F81:T$82)-U185)>0,-U185,-SUM($F81:T$82)),0) -> 0 | V82: =IF(V185>0,IF((SUM($F81:U$82)-V185)>0,-V185,-SUM($F81:U$82)),0) -> 0 | W82: =IF(W185>0,IF((SUM($F81:V$82)-W185)>0,-W185,-SUM($F81:V$82)),0) -> 0 | ... BM82: =IF(BM185>0,IF((SUM($F81:BL$82)-BM185)>0,-BM185,-SUM($F81:BL$82)),0) -> 0
B83: % по АФ | D83: млн. руб. | E83: =SUM(F83:BM83) -> 0
C84: НАЧИСЛЕНИЕ | D84: млн. руб. | E84: =SUM(F84:BM84) -> 250.10365 | F84: =SUM($F81:F$82)*F$197/4 -> 0.0105 | G84: =SUM($F81:G$82)*G$197/4 -> 0.042 | H84: =SUM($F81:H$82)*H$197/4 -> 0.0735 | I84: =SUM($F81:I$82)*I$197/4 -> 0.08925 | J84: =SUM($F81:J$82)*J$197/4 -> 0.08925 | K84: =SUM($F81:K$82)*K$197/4 -> 0.1375 | L84: =SUM($F81:L$82)*L$197/4 -> 0.1705 | M84: =SUM($F81:M$82)*M$197/4 -> 0.22935 | ... BM84: =SUM($F81:BM$82)*BM$197/4 -> 0
C85: УПЛАТА | D85: млн. руб. | E85: =SUM(F85:BM85) -> -250.10365 | N85: =IF(N186>0,IF((SUM($F$84:M85)-N186)>0,-N186,-SUM($F$84:M85)),0) -> -0.84185 | O85: =IF(O186>0,IF((SUM($F$84:N85)-O186)>0,-O186,-SUM($F$84:N85)),0) -> -1.7082529 | P85: =IF(P186>0,IF((SUM($F$84:O85)-P186)>0,-P186,-SUM($F$84:O85)),0) -> 0 | Q85: =IF(Q186>0,IF((SUM($F$84:P85)-Q186)>0,-Q186,-SUM($F$84:P85)),0) -> 0 | R85: =IF(R186>0,IF((SUM($F$84:Q85)-R186)>0,-R186,-SUM($F$84:Q85)),0) -> 0 | S85: =IF(S186>0,IF((SUM($F$84:R85)-S186)>0,-S186,-SUM($F$84:R85)),0) -> 0 | T85: =IF(T186>0,IF((SUM($F$84:S85)-T186)>0,-T186,-SUM($F$84:S85)),0) -> 0 | U85: =IF(U186>0,IF((SUM($F$84:T85)-U186)>0,-U186,-SUM($F$84:T85)),0) -> 0 | ... BM85: =IF(BM186>0,IF((SUM($F$84:BL85)-BM186)>0,-BM186,-SUM($F$84:BL85)),0) -> 0
B86: КРЕДИТ бридж | C86: реф | D86: млн. руб. | E86: =SUM(F86:BM86) -> 0
C87: ПОСТУПЛЕНИЕ | D87: млн. руб. | E87: =SUM(F87:BM87) -> 6417.9983 | F87: =IF(F5<'DB1'!$U$25,IF(-(F178)>0,-F178,0),0) -> 0 | G87: =IF(G5<'DB1'!$U$25,IF(-(G178)>0,-G178,0),0) -> 0 | H87: =IF(H5<'DB1'!$U$25,IF(-(H178)>0,-H178,0),0) -> 0 | I87: =IF(I5<'DB1'!$U$25,IF(-(I178)>0,-I178,0),0) -> 0 | J87: =IF(J5<'DB1'!$U$25,IF(-(J178)>0,-J178,0),0) -> 0 | K87: =IF(K5<'DB1'!$U$25,IF(-(K178)>0,-K178,0),0) -> 0 | L87: =IF(L5<'DB1'!$U$25,IF(-(L178)>0,-L178,0),0) -> 0 | M87: =IF(M5<'DB1'!$U$25,IF(-(M178)>0,-M178,0),0) -> 0 | ... BM87: =IF(BM5<'DB1'!$U$25,IF(-(BM178)>0,-BM178,0),0) -> 0
C88: ПОГАШЕНИЕ | D88: млн. руб. | E88: =SUM(F88:BM88) -> -6417.9983 | N88: =IF(AND($C$86="реф",N$4="РнС"),-SUM($F87:M$88),IF(N178>0,IF((SUM($F87:M$88)-N178)>0,-N178,-SUM($F87:M$88)),0)) -> 0 | O88: =IF(AND($C$86="реф",O$4="РнС"),-SUM($F87:N$88),IF(O178>0,IF((SUM($F87:N$88)-O178)>0,-O178,-SUM($F87:N$88)),0)) -> 0 | P88: =IF(AND($C$86="реф",P$4="РнС"),-SUM($F87:O$88),IF(P178>0,IF((SUM($F87:O$88)-P178)>0,-P178,-SUM($F87:O$88)),0)) -> 0 | Q88: =IF(AND($C$86="реф",Q$4="РнС"),-SUM($F87:P$88),IF(Q178>0,IF((SUM($F87:P$88)-Q178)>0,-Q178,-SUM($F87:P$88)),0)) -> 0 | R88: =IF(AND($C$86="реф",R$4="РнС"),-SUM($F87:Q$88),IF(R178>0,IF((SUM($F87:Q$88)-R178)>0,-R178,-SUM($F87:Q$88)),0)) -> 0 | S88: =IF(AND($C$86="реф",S$4="РнС"),-SUM($F87:R$88),IF(S178>0,IF((SUM($F87:R$88)-S178)>0,-S178,-SUM($F87:R$88)),0)) -> 0 | T88: =IF(AND($C$86="реф",T$4="РнС"),-SUM($F87:S$88),IF(T178>0,IF((SUM($F87:S$88)-T178)>0,-T178,-SUM($F87:S$88)),0)) -> -6417.9983 | U88: =IF(AND($C$86="реф",U$4="РнС"),-SUM($F87:T$88),IF(U178>0,IF((SUM($F87:T$88)-U178)>0,-U178,-SUM($F87:T$88)),0)) -> 0 | ... BM88: =IF(AND($C$86="реф",BM$4="РнС"),-SUM($F87:BL$88),IF(BM178>0,IF((SUM($F87:BL$88)-BM178)>0,-BM178,-SUM($F87:BL$88)),0)) -> 0
B89: % КРЕДИТУ бридж | D89: млн. руб. | E89: =SUM(F89:BM89) -> 0
C90: НАЧИСЛЕНИЕ | D90: млн. руб. | E90: =SUM(F90:BM90) -> 956.83809 | F90: =SUM($F$87:F88)*F$195/4 -> 0 | G90: =SUM($F$87:G88)*G$195/4 -> 0 | H90: =SUM($F$87:H88)*H$195/4 -> 0 | I90: =SUM($F$87:I88)*I$195/4 -> 0 | J90: =SUM($F$87:J88)*J$195/4 -> 0 | K90: =SUM($F$87:K88)*K$195/4 -> 0 | L90: =SUM($F$87:L88)*L$195/4 -> 0 | M90: =SUM($F$87:M88)*M$195/4 -> 0 | ... BM90: =SUM($F$87:BM88)*BM$195/4 -> 0
C91: УПЛАТА | D91: млн. руб. | E91: =SUM(F91:BM91) -> -956.83809 | N91: =IF(AND($C$86="реф",N$4="РнС"),-SUM($F90:M$91),IF(N179>0,IF((SUM($F90:M$91,N90)-N179)>0,-N179,-SUM($F90:M$91)),0)) -> 0 | O91: =IF(AND($C$86="реф",O$4="РнС"),-SUM($F90:N$91),IF(O179>0,IF((SUM($F90:N$91,O90)-O179)>0,-O179,-SUM($F90:N$91)),0)) -> 0 | P91: =IF(AND($C$86="реф",P$4="РнС"),-SUM($F90:O$91),IF(P179>0,IF((SUM($F90:O$91,P90)-P179)>0,-P179,-SUM($F90:O$91)),0)) -> 0 | Q91: =IF(AND($C$86="реф",Q$4="РнС"),-SUM($F90:P$91),IF(Q179>0,IF((SUM($F90:P$91,Q90)-Q179)>0,-Q179,-SUM($F90:P$91)),0)) -> 0 | R91: =IF(AND($C$86="реф",R$4="РнС"),-SUM($F90:Q$91),IF(R179>0,IF((SUM($F90:Q$91,R90)-R179)>0,-R179,-SUM($F90:Q$91)),0)) -> 0 | S91: =IF(AND($C$86="реф",S$4="РнС"),-SUM($F90:R$91),IF(S179>0,IF((SUM($F90:R$91,S90)-S179)>0,-S179,-SUM($F90:R$91)),0)) -> 0 | T91: =IF(AND($C$86="реф",T$4="РнС"),-SUM($F90:S$91),IF(T179>0,IF((SUM($F90:S$91,T90)-T179)>0,-T179,-SUM($F90:S$91)),0)) -> -956.83809 | U91: =IF(AND($C$86="реф",U$4="РнС"),-SUM($F90:T$91),IF(U179>0,IF((SUM($F90:T$91,U90)-U179)>0,-U179,-SUM($F90:T$91)),0)) -> 0 | ... BM91: =IF(AND($C$86="реф",BM$4="РнС"),-SUM($F90:BL$91),IF(BM179>0,IF((SUM($F90:BL$91,BM90)-BM179)>0,-BM179,-SUM($F90:BL$91)),0)) -> 0
C92: НАЧИСЛЕНИЕ КАП. | D92: млн. руб. | E92: =SUM(F92:BM92) -> 111.84112 | F92: =SUM($F$90:F91)*F$195/4 -> 0 | G92: =SUM($F$90:G91)*G$195/4 -> 0 | H92: =SUM($F$90:H91)*H$195/4 -> 0 | I92: =SUM($F$90:I91)*I$195/4 -> 0 | J92: =SUM($F$90:J91)*J$195/4 -> 0 | K92: =SUM($F$90:K91)*K$195/4 -> 0 | L92: =SUM($F$90:L91)*L$195/4 -> 0 | M92: =SUM($F$90:M91)*M$195/4 -> 0 | ... BM92: =SUM($F$90:BM91)*BM$195/4 -> 0
C93: УПЛАТА КАП. | D93: млн. руб. | E93: =SUM(F93:BM93) -> -111.84112 | N93: =IF(AND($C$86="реф",N$4="РнС"),-SUM($F92:M$93),IF(N180>0,IF((SUM($F$92:M93,N92)-N180)>0,-N180,-SUM($F$92:M93)),0)) -> 0 | O93: =IF(AND($C$86="реф",O$4="РнС"),-SUM($F92:N$93),IF(O180>0,IF((SUM($F$92:N93,O92)-O180)>0,-O180,-SUM($F$92:N93)),0)) -> 0 | P93: =IF(AND($C$86="реф",P$4="РнС"),-SUM($F92:O$93),IF(P180>0,IF((SUM($F$92:O93,P92)-P180)>0,-P180,-SUM($F$92:O93)),0)) -> 0 | Q93: =IF(AND($C$86="реф",Q$4="РнС"),-SUM($F92:P$93),IF(Q180>0,IF((SUM($F$92:P93,Q92)-Q180)>0,-Q180,-SUM($F$92:P93)),0)) -> 0 | R93: =IF(AND($C$86="реф",R$4="РнС"),-SUM($F92:Q$93),IF(R180>0,IF((SUM($F$92:Q93,R92)-R180)>0,-R180,-SUM($F$92:Q93)),0)) -> 0 | S93: =IF(AND($C$86="реф",S$4="РнС"),-SUM($F92:R$93),IF(S180>0,IF((SUM($F$92:R93,S92)-S180)>0,-S180,-SUM($F$92:R93)),0)) -> 0 | T93: =IF(AND($C$86="реф",T$4="РнС"),-SUM($F92:S$93),IF(T180>0,IF((SUM($F$92:S93,T92)-T180)>0,-T180,-SUM($F$92:S93)),0)) -> -111.84112 | U93: =IF(AND($C$86="реф",U$4="РнС"),-SUM($F92:T$93),IF(U180>0,IF((SUM($F$92:T93,U92)-U180)>0,-U180,-SUM($F$92:T93)),0)) -> 0 | ... BM93: =IF(AND($C$86="реф",BM$4="РнС"),-SUM($F92:BL$93),IF(BM180>0,IF((SUM($F$92:BL93,BM92)-BM180)>0,-BM180,-SUM($F$92:BL93)),0)) -> 0
B94: КРЕДИТ проектноефин-ие | D94: млн. руб. | E94: =SUM(F94:BM94) -> 0
C95: ПОСТУПЛЕНИЕ | D95: млн. руб. | E95: =SUM(F95:BM95) -> 27595.686 | F95: =IF(F15<'DB1'!$U$25,IF(-(F181)>0,-F181,0),0)+IF(AND($C$86="реф",F$4="РнС"),-SUM(F88,F91,F93),0) -> 0 | G95: =IF(G15<'DB1'!$U$25,IF(-(G181)>0,-G181,0),0)+IF(AND($C$86="реф",G$4="РнС"),-SUM(G88,G91,G93),0) -> 0 | H95: =IF(H15<'DB1'!$U$25,IF(-(H181)>0,-H181,0),0)+IF(AND($C$86="реф",H$4="РнС"),-SUM(H88,H91,H93),0) -> 0 | I95: =IF(I15<'DB1'!$U$25,IF(-(I181)>0,-I181,0),0)+IF(AND($C$86="реф",I$4="РнС"),-SUM(I88,I91,I93),0) -> 0 | J95: =IF(J15<'DB1'!$U$25,IF(-(J181)>0,-J181,0),0)+IF(AND($C$86="реф",J$4="РнС"),-SUM(J88,J91,J93),0) -> 0 | K95: =IF(K15<'DB1'!$U$25,IF(-(K181)>0,-K181,0),0)+IF(AND($C$86="реф",K$4="РнС"),-SUM(K88,K91,K93),0) -> 0 | L95: =IF(L15<'DB1'!$U$25,IF(-(L181)>0,-L181,0),0)+IF(AND($C$86="реф",L$4="РнС"),-SUM(L88,L91,L93),0) -> 0 | M95: =IF(M15<'DB1'!$U$25,IF(-(M181)>0,-M181,0),0)+IF(AND($C$86="реф",M$4="РнС"),-SUM(M88,M91,M93),0) -> 0 | ... BM95: =IF(BM15<'DB1'!$U$25,IF(-(BM181)>0,-BM181,0),0)+IF(AND($C$86="реф",BM$4="РнС"),-SUM(BM88,BM91,BM93),0) -> 0
C96: ПОГАШЕНИЕ | D96: млн. руб. | E96: =SUM(F96:BM96) -> -27595.686 | N96: =IF(N182>0,IF((SUM($F$95:M96)-N182)>0,-N182,-SUM($F$95:M96)),0) -> 0 | O96: =IF(O182>0,IF((SUM($F$95:N96)-O182)>0,-O182,-SUM($F$95:N96)),0) -> 0 | P96: =IF(P182>0,IF((SUM($F$95:O96)-P182)>0,-P182,-SUM($F$95:O96)),0) -> 0 | Q96: =IF(Q182>0,IF((SUM($F$95:P96)-Q182)>0,-Q182,-SUM($F$95:P96)),0) -> 0 | R96: =IF(R182>0,IF((SUM($F$95:Q96)-R182)>0,-R182,-SUM($F$95:Q96)),0) -> 0 | S96: =IF(S182>0,IF((SUM($F$95:R96)-S182)>0,-S182,-SUM($F$95:R96)),0) -> 0 | T96: =IF(T182>0,IF((SUM($F$95:S96)-T182)>0,-T182,-SUM($F$95:S96)),0) -> 0 | U96: =IF(U182>0,IF((SUM($F$95:T96)-U182)>0,-U182,-SUM($F$95:T96)),0) -> 0 | ... BM96: =IF(BM182>0,IF((SUM($F$95:BL96)-BM182)>0,-BM182,-SUM($F$95:BL96)),0) -> 0
B97: % КРЕДИТ проектное фин-ие | D97: млн. руб. | E97: =SUM(F97:BM97) -> 0
C98: НАЧИСЛЕНИЕ | D98: млн. руб. | E98: =SUM(F98:BM98) -> 4749.5842 | F98: =SUM($F$95:F96)*F$198/4 -> 0 | G98: =SUM($F$95:G96)*G$198/4 -> 0 | H98: =SUM($F$95:H96)*H$198/4 -> 0 | I98: =SUM($F$95:I96)*I$198/4 -> 0 | J98: =SUM($F$95:J96)*J$198/4 -> 0 | K98: =SUM($F$95:K96)*K$198/4 -> 0 | L98: =SUM($F$95:L96)*L$198/4 -> 0 | M98: =SUM($F$95:M96)*M$198/4 -> 0 | ... BM98: =SUM($F$95:BM96)*BM$198/4 -> 0
C99: УПЛАТА | D99: млн. руб. | E99: =SUM(F99:BM99) -> -4749.5842 | N99: =IF(N183>0,IF((SUM($F$98:M99,N98)-N183)>0,-N183,-SUM($F$98:M99)),0) -> 0 | O99: =IF(O183>0,IF((SUM($F$98:N99,O98)-O183)>0,-O183,-SUM($F$98:N99)),0) -> 0 | P99: =IF(P183>0,IF((SUM($F$98:O99,P98)-P183)>0,-P183,-SUM($F$98:O99)),0) -> 0 | Q99: =IF(Q183>0,IF((SUM($F$98:P99,Q98)-Q183)>0,-Q183,-SUM($F$98:P99)),0) -> 0 | R99: =IF(R183>0,IF((SUM($F$98:Q99,R98)-R183)>0,-R183,-SUM($F$98:Q99)),0) -> 0 | S99: =IF(S183>0,IF((SUM($F$98:R99,S98)-S183)>0,-S183,-SUM($F$98:R99)),0) -> 0 | T99: =IF(T183>0,IF((SUM($F$98:S99,T98)-T183)>0,-T183,-SUM($F$98:S99)),0) -> 0 | U99: =IF(U183>0,IF((SUM($F$98:T99,U98)-U183)>0,-U183,-SUM($F$98:T99)),0) -> 0 | ... BM99: =IF(BM183>0,IF((SUM($F$98:BL99,BM98)-BM183)>0,-BM183,-SUM($F$98:BL99)),0) -> 0
C100: НАЧИСЛЕНИЕ КАП. | D100: млн. руб. | E100: =SUM(F100:BM100) -> 756.70762 | F100: =SUM($F$98:F99)*F$198/4 -> 0 | G100: =SUM($F$98:G99)*G$198/4 -> 0 | H100: =SUM($F$98:H99)*H$198/4 -> 0 | I100: =SUM($F$98:I99)*I$198/4 -> 0 | J100: =SUM($F$98:J99)*J$198/4 -> 0 | K100: =SUM($F$98:K99)*K$198/4 -> 0 | L100: =SUM($F$98:L99)*L$198/4 -> 0 | M100: =SUM($F$98:M99)*M$198/4 -> 0 | ... BM100: =SUM($F$98:BM99)*BM$198/4 -> 0
C101: УПЛАТА КАП. | D101: млн. руб. | E101: =SUM(F101:BM101) -> -756.70762 | N101: =IF(N184>0,IF((SUM($F$100:M101,N100)-N184)>0,-N184,-SUM($F$100:M101)),0) -> 0 | O101: =IF(O184>0,IF((SUM($F$100:N101,O100)-O184)>0,-O184,-SUM($F$100:N101)),0) -> 0 | P101: =IF(P184>0,IF((SUM($F$100:O101,P100)-P184)>0,-P184,-SUM($F$100:O101)),0) -> 0 | Q101: =IF(Q184>0,IF((SUM($F$100:P101,Q100)-Q184)>0,-Q184,-SUM($F$100:P101)),0) -> 0 | R101: =IF(R184>0,IF((SUM($F$100:Q101,R100)-R184)>0,-R184,-SUM($F$100:Q101)),0) -> 0 | S101: =IF(S184>0,IF((SUM($F$100:R101,S100)-S184)>0,-S184,-SUM($F$100:R101)),0) -> 0 | T101: =IF(T184>0,IF((SUM($F$100:S101,T100)-T184)>0,-T184,-SUM($F$100:S101)),0) -> 0 | U101: =IF(U184>0,IF((SUM($F$100:T101,U100)-U184)>0,-U184,-SUM($F$100:T101)),0) -> 0 | ... BM101: =IF(BM184>0,IF((SUM($F$100:BL101,BM100)-BM184)>0,-BM184,-SUM($F$100:BL101)),0) -> 0
B102: КОМИССИИ по кредиту | D102: млн. руб. | E102: =SUM(F102:BM102) -> 0
C103: НАЧИСЛЕНИЕ | D103: млн. руб. | E103: =SUM(F103:BM103) -> 166.85488 | F103: =IF(F60<>0,'DB1'!$O$27+'DB1'!$O$28)+IF(F$5=EOMONTH('DB1'!$U$25,2),'DB1'!$O$29,0) -> 0 | G103: =IF(G60<>0,'DB1'!$O$27+'DB1'!$O$28)+IF(G$5=EOMONTH('DB1'!$U$25,2),'DB1'!$O$29,0) -> 0 | H103: =IF(H60<>0,'DB1'!$O$27+'DB1'!$O$28)+IF(H$5=EOMONTH('DB1'!$U$25,2),'DB1'!$O$29,0) -> 0 | I103: =IF(I60<>0,'DB1'!$O$27+'DB1'!$O$28)+IF(I$5=EOMONTH('DB1'!$U$25,2),'DB1'!$O$29,0) -> 0 | J103: =IF(J60<>0,'DB1'!$O$27+'DB1'!$O$28)+IF(J$5=EOMONTH('DB1'!$U$25,2),'DB1'!$O$29,0) -> 0 | K103: =IF(K60<>0,'DB1'!$O$27+'DB1'!$O$28)+IF(K$5=EOMONTH('DB1'!$U$25,2),'DB1'!$O$29,0) -> 0 | L103: =IF(L60<>0,'DB1'!$O$27+'DB1'!$O$28)+IF(L$5=EOMONTH('DB1'!$U$25,2),'DB1'!$O$29,0) -> 0 | M103: =IF(M60<>0,'DB1'!$O$27+'DB1'!$O$28)+IF(M$5=EOMONTH('DB1'!$U$25,2),'DB1'!$O$29,0) -> 0 | ... R103: =IF(R60<>0,'DB1'!$O$27+'DB1'!$O$28)+IF(R$5=EOMONTH('DB1'!$U$25,2),'DB1'!$O$29,0) -> 0 | U103: =IF(U60<>0,'DB1'!$O$27+'DB1'!$O$28)+IF(U$5=EOMONTH('DB1'!$U$25,2),'DB1'!$O$29,0) -> 0 | V103: =IF(V60<>0,'DB1'!$O$27+'DB1'!$O$28)+IF(V$5=EOMONTH('DB1'!$U$25,2),'DB1'!$O$29,0) -> 0 | W103: =IF(W60<>0,'DB1'!$O$27+'DB1'!$O$28)+IF(W$5=EOMONTH('DB1'!$U$25,2),'DB1'!$O$29,0) -> 0 | X103: =IF(X60<>0,'DB1'!$O$27+'DB1'!$O$28)+IF(X$5=EOMONTH('DB1'!$U$25,2),'DB1'!$O$29,0) -> 0 | Y103: =IF(Y60<>0,'DB1'!$O$27+'DB1'!$O$28)+IF(Y$5=EOMONTH('DB1'!$U$25,2),'DB1'!$O$29,0) -> 0 | Z103: =IF(Z60<>0,'DB1'!$O$27+'DB1'!$O$28)+IF(Z$5=EOMONTH('DB1'!$U$25,2),'DB1'!$O$29,0) -> 0 | AA103: =IF(AA60<>0,'DB1'!$O$27+'DB1'!$O$28)+IF(AA$5=EOMONTH('DB1'!$U$25,2),'DB1'!$O$29,0) -> 0 | AB103: =IF(AB60<>0,'DB1'!$O$27+'DB1'!$O$28)+IF(AB$5=EOMONTH('DB1'!$U$25,2),'DB1'!$O$29,0) -> 0 | ... BM103: =IF(BM60<>0,'DB1'!$O$27+'DB1'!$O$28)+IF(BM$5=EOMONTH('DB1'!$U$25,2),'DB1'!$O$29,0) -> 0
C104: УПЛАТА | D104: млн. руб. | E104: =SUM(F104:BM104) -> -166.85488 | N104: =-N103 -> 0 | O104: =-O103 -> 0 | P104: =-P103 -> -166.85488 | Q104: =-Q103 -> 0 | R104: =-R103 -> 0 | U104: =-U103 -> 0 | V104: =-V103 -> 0 | W104: =-W103 -> 0 | X104: =-X103 -> 0 | Y104: =-Y103 -> 0 | Z104: =-Z103 -> 0 | AA104: =-AA103 -> 0 | AB104: =-AB103 -> 0 | ... BM104: =-BM103 -> 0
B105: ВНУТРЕННИЕ ОБОРОТЫ | D105: млн. руб. | E105: =SUM(F105:BM105) -> 0
C106: ПОСТУПЛЕНИЯ | D106: млн. руб. | E106: =SUM(F106:BM106) -> 0
C107: ВЫПЛАТЫ | D107: млн. руб. | E107: =SUM(F107:BM107) -> 0
B109: ССУДНАЯ ЗАДОЛЖЕННОСТЬ | F109: =SUM($F87:F88,$F$95:F96) -> 0 | G109: =SUM($F87:G88,$F$95:G96) -> 0 | H109: =SUM($F87:H88,$F$95:H96) -> 0 | I109: =SUM($F87:I88,$F$95:I96) -> 0 | J109: =SUM($F87:J88,$F$95:J96) -> 0 | K109: =SUM($F87:K88,$F$95:K96) -> 0 | L109: =SUM($F87:L88,$F$95:L96) -> 0 | M109: =SUM($F87:M88,$F$95:M96) -> 0 | ... BM109: =SUM($F87:BM88,$F$95:BM96) -> 0
B111: НАЛОГИ | E111: =SUM(F111:BM111) -> -2244.3118 | F111: =SUM(F112,F127) -> 0 | G111: =SUM(G112,G127) -> 0 | H111: =SUM(H112,H127) -> 0 | I111: =SUM(I112,I127) -> 0 | J111: =SUM(J112,J127) -> 0 | K111: =SUM(K112,K127) -> 0 | L111: =SUM(L112,L127) -> 0 | M111: =SUM(M112,M127) -> 0 | ... BM111: =SUM(BM112,BM127) -> 0
B112: НДС | E112: =SUM(F112:BM112) -> -258.67494 | G112: =F113+F120 -> 0 | H112: =G113+G120 -> 0 | I112: =H113+H120 -> 0 | J112: =I113+I120 -> 0 | K112: =J113+J120 -> 0 | L112: =K113+K120 -> 0 | M112: =L113+L120 -> 0 | N112: =M113+M120 -> 0 | ... BM112: =BL113+BL120 -> 0
C113: УПЛАТА | E113: =SUM(F113:BM113) -> -589.60785 | F113: =SUM(F114:F119) -> 0 | G113: =SUM(G114:G119) -> 0 | H113: =SUM(H114:H119) -> 0 | I113: =SUM(I114:I119) -> 0 | J113: =SUM(J114:J119) -> 0 | K113: =SUM(K114:K119) -> 0 | L113: =SUM(L114:L119) -> 0 | M113: =SUM(M114:M119) -> 0 | ... BM113: =SUM(BM114:BM119) -> 0
A114: =-E114 -> 0 | D114: ='DB1'!B9 -> АПАРТАМЕНТЫ | E114: =SUM(F114:BM114) -> 0 | F114: =-F27*(1-F$174)/(1+'TS1'!$J$84)*'TS1'!$J$84 -> 0 | G114: =-G27*(1-G$174)/(1+'TS1'!$J$84)*'TS1'!$J$84 -> 0 | H114: =-H27*(1-H$174)/(1+'TS1'!$J$84)*'TS1'!$J$84 -> 0 | I114: =-I27*(1-I$174)/(1+'TS1'!$J$84)*'TS1'!$J$84 -> 0 | J114: =-J27*(1-J$174)/(1+'TS1'!$J$84)*'TS1'!$J$84 -> 0 | K114: =-K27*(1-K$174)/(1+'TS1'!$J$84)*'TS1'!$J$84 -> 0 | L114: =-L27*(1-L$174)/(1+'TS1'!$J$84)*'TS1'!$J$84 -> 0 | M114: =-M27*(1-M$174)/(1+'TS1'!$J$84)*'TS1'!$J$84 -> 0 | ... BM114: =-BM27*(1-BM$174)/(1+'TS1'!$J$84)*'TS1'!$J$84 -> 0
...

Sheet CF2
B2: CF проекта | C2: ОЧЕРЕДЬ | D2: 2
F3: =IF((EOMONTH(F5,-3)+1)='DB2'!$U$25,"РнС",IF('CF2'!F5='DB2'!$U$27,"РнВ","")) | G3: =IF((EOMONTH(G5,-3)+1)='DB2'!$U$25,"РнС",IF('CF2'!G5='DB2'!$U$27,"РнВ","")) | H3: =IF((EOMONTH(H5,-3)+1)='DB2'!$U$25,"РнС",IF('CF2'!H5='DB2'!$U$27,"РнВ","")) | I3: =IF((EOMONTH(I5,-3)+1)='DB2'!$U$25,"РнС",IF('CF2'!I5='DB2'!$U$27,"РнВ","")) | J3: =IF((EOMONTH(J5,-3)+1)='DB2'!$U$25,"РнС",IF('CF2'!J5='DB2'!$U$27,"РнВ","")) | K3: =IF((EOMONTH(K5,-3)+1)='DB2'!$U$25,"РнС",IF('CF2'!K5='DB2'!$U$27,"РнВ","")) | L3: =IF((EOMONTH(L5,-3)+1)='DB2'!$U$25,"РнС",IF('CF2'!L5='DB2'!$U$27,"РнВ","")) | M3: =IF((EOMONTH(M5,-3)+1)='DB2'!$U$25,"РнС",IF('CF2'!M5='DB2'!$U$27,"РнВ","")) | ... BM3: =IF((EOMONTH(BM5,-3)+1)='DB2'!$U$25,"РнС",IF('CF2'!BM5='DB2'!$U$27,"РнВ",""))
F4: =DETAILS!K3 -> ФАКТ | G4: =DETAILS!L3 -> ФАКТ | H4: =DETAILS!M3 -> ФАКТ | I4: =DETAILS!N3 -> ФАКТ | J4: =DETAILS!O3 -> ФАКТ | K4: =DETAILS!P3 -> ФАКТ | L4: =DETAILS!Q3 -> ФАКТ | M4: =DETAILS!R3 -> ФАКТ
B5: СТАТЬЯ | E5: ВСЕГО | F5: =EOMONTH('DB2'!$U$22,2) -> 45107 | G5: =EOMONTH(F5,3) -> 45199 | H5: =EOMONTH(G5,3) -> 45291 | I5: =EOMONTH(H5,3) -> 45382 | J5: =EOMONTH(I5,3) -> 45473 | K5: =EOMONTH(J5,3) -> 45565 | L5: =EOMONTH(K5,3) -> 45657 | M5: =EOMONTH(L5,3) -> 45747 | N5: =EOMONTH(M5,3) -> 45838 | ... BM5: =EOMONTH(BL5,3) -> 50495
F6: =CONCATENATE(IF(MONTH(F5)<=3,"1",IF(MONTH(F5)<=6,"2",IF(MONTH(F5)<=9,"3","4"))),"Q",YEAR(F5)) -> 2Q2023 | G6: =CONCATENATE(IF(MONTH(G5)<=3,"1",IF(MONTH(G5)<=6,"2",IF(MONTH(G5)<=9,"3","4"))),"Q",YEAR(G5)) -> 3Q2023 | H6: =CONCATENATE(IF(MONTH(H5)<=3,"1",IF(MONTH(H5)<=6,"2",IF(MONTH(H5)<=9,"3","4"))),"Q",YEAR(H5)) -> 4Q2023 | I6: =CONCATENATE(IF(MONTH(I5)<=3,"1",IF(MONTH(I5)<=6,"2",IF(MONTH(I5)<=9,"3","4"))),"Q",YEAR(I5)) -> 1Q2024 | J6: =CONCATENATE(IF(MONTH(J5)<=3,"1",IF(MONTH(J5)<=6,"2",IF(MONTH(J5)<=9,"3","4"))),"Q",YEAR(J5)) -> 2Q2024 | K6: =CONCATENATE(IF(MONTH(K5)<=3,"1",IF(MONTH(K5)<=6,"2",IF(MONTH(K5)<=9,"3","4"))),"Q",YEAR(K5)) -> 3Q2024 | L6: =CONCATENATE(IF(MONTH(L5)<=3,"1",IF(MONTH(L5)<=6,"2",IF(MONTH(L5)<=9,"3","4"))),"Q",YEAR(L5)) -> 4Q2024 | M6: =CONCATENATE(IF(MONTH(M5)<=3,"1",IF(MONTH(M5)<=6,"2",IF(MONTH(M5)<=9,"3","4"))),"Q",YEAR(M5)) -> 1Q2025 | ... BM6: =CONCATENATE(IF(MONTH(BM5)<=3,"1",IF(MONTH(BM5)<=6,"2",IF(MONTH(BM5)<=9,"3","4"))),"Q",YEAR(BM5)) -> 1Q2038
B7: КОНТРАКТАЦИЯ | D7: м2
B8: ='DB2'!B8 -> КВАРТИРЫ | D8: м2 | E8: =SUM(F8:BM8) -> 50877.343 | F8: ='TS2'!F40 -> 0 | G8: ='TS2'!G40 -> 0 | H8: ='TS2'!H40 -> 0 | I8: ='TS2'!I40 -> 0 | J8: ='TS2'!J40 -> 0 | K8: ='TS2'!K40 -> 0 | L8: ='TS2'!L40 -> 0 | M8: ='TS2'!M40 -> 0 | ... BM8: ='TS2'!BM40 -> 0
B9: ='DB2'!B9 -> АПАРТАМЕНТЫ | D9: м2 | E9: =SUM(F9:BM9) -> 0 | F9: ='TS2'!F44 -> 0 | G9: ='TS2'!G44 -> 0 | H9: ='TS2'!H44 -> 0 | I9: ='TS2'!I44 -> 0 | J9: ='TS2'!J44 -> 0 | K9: ='TS2'!K44 -> 0 | L9: ='TS2'!L44 -> 0 | M9: ='TS2'!M44 -> 0 | ... BM9: ='TS2'!BM44 -> 0
B10: ='DB2'!B10 -> ОФИСЫ | D10: м2 | E10: =SUM(F10:BM10) -> 0 | F10: ='TS2'!F46 -> 0 | G10: ='TS2'!G46 -> 0 | H10: ='TS2'!H46 -> 0 | I10: ='TS2'!I46 -> 0 | J10: ='TS2'!J46 -> 0 | K10: ='TS2'!K46 -> 0 | L10: ='TS2'!L46 -> 0 | M10: ='TS2'!M46 -> 0 | ... BM10: ='TS2'!BM46 -> 0
B11: ='DB2'!B11 -> РИТЕЙЛ | D11: м2 | E11: =SUM(F11:BM11) -> 2556.0585 | F11: ='TS2'!F48 -> 0 | G11: ='TS2'!G48 -> 0 | H11: ='TS2'!H48 -> 0 | I11: ='TS2'!I48 -> 0 | J11: ='TS2'!J48 -> 0 | K11: ='TS2'!K48 -> 0 | L11: ='TS2'!L48 -> 0 | M11: ='TS2'!M48 -> 0 | ... BM11: ='TS2'!BM48 -> 0
B12: ='DB2'!B12 -> ТЦ | D12: м2 | E12: =SUM(F12:BM12) -> 0 | F12: ='TS2'!F50 -> 0 | G12: ='TS2'!G50 -> 0 | H12: ='TS2'!H50 -> 0 | I12: ='TS2'!I50 -> 0 | J12: ='TS2'!J50 -> 0 | K12: ='TS2'!K50 -> 0 | L12: ='TS2'!L50 -> 0 | M12: ='TS2'!M50 -> 0 | ... BM12: ='TS2'!BM50 -> 0
B13: ='DB2'!B16 -> ПАРКИНГ ЖИЛЬЕ | D13: шт. | E13: =SUM(F13:BM13) -> 513 | F13: ='TS2'!F52 -> 0 | G13: ='TS2'!G52 -> 0 | H13: ='TS2'!H52 -> 0 | I13: ='TS2'!I52 -> 0 | J13: ='TS2'!J52 -> 0 | K13: ='TS2'!K52 -> 0 | L13: ='TS2'!L52 -> 0 | M13: ='TS2'!M52 -> 0 | ... BM13: ='TS2'!BM52 -> 0
B14: ='DB2'!B17 -> ПАРКИНГ ОФИС | D14: шт. | E14: =SUM(F14:BM14) -> 0 | F14: ='TS2'!F54 -> 0 | G14: ='TS2'!G54 -> 0 | H14: ='TS2'!H54 -> 0 | I14: ='TS2'!I54 -> 0 | J14: ='TS2'!J54 -> 0 | K14: ='TS2'!K54 -> 0 | L14: ='TS2'!L54 -> 0 | M14: ='TS2'!M54 -> 0 | ... BM14: ='TS2'!BM54 -> 0
B16: ЦЕНЫ | D16: тыс. руб.
B17: =B8 -> КВАРТИРЫ | D17: тыс. руб. | E17: =IFERROR(E26/E8*1000,0) -> 630 | F17: =IF(F8=0,,IF(F8>0,IF(E17=0,'DB2'!$R$8*(1+'DB2'!$O$8),E17+'DB2'!$R$8*(100%-(1+'DB2'!$O$8))/SUMPRODUCT('TS2'!$F$43:$BM$43,'TS2'!$F$56:$BM$56)),)) -> 0 | G17: =IF(G8=0,,IF(G8>0,IF(F17=0,'DB2'!$R$8*(1+'DB2'!$O$8),F17+'DB2'!$R$8*(100%-(1+'DB2'!$O$8))/SUMPRODUCT('TS2'!$F$43:$BM$43,'TS2'!$F$56:$BM$56)),)) -> 0 | H17: =IF(H8=0,,IF(H8>0,IF(G17=0,'DB2'!$R$8*(1+'DB2'!$O$8),G17+'DB2'!$R$8*(100%-(1+'DB2'!$O$8))/SUMPRODUCT('TS2'!$F$43:$BM$43,'TS2'!$F$56:$BM$56)),)) -> 0 | I17: =IF(I8=0,,IF(I8>0,IF(H17=0,'DB2'!$R$8*(1+'DB2'!$O$8),H17+'DB2'!$R$8*(100%-(1+'DB2'!$O$8))/SUMPRODUCT('TS2'!$F$43:$BM$43,'TS2'!$F$56:$BM$56)),)) -> 0 | J17: =IF(J8=0,,IF(J8>0,IF(I17=0,'DB2'!$R$8*(1+'DB2'!$O$8),I17+'DB2'!$R$8*(100%-(1+'DB2'!$O$8))/SUMPRODUCT('TS2'!$F$43:$BM$43,'TS2'!$F$56:$BM$56)),)) -> 0 | K17: =IF(K8=0,,IF(K8>0,IF(J17=0,'DB2'!$R$8*(1+'DB2'!$O$8),J17+'DB2'!$R$8*(100%-(1+'DB2'!$O$8))/SUMPRODUCT('TS2'!$F$43:$BM$43,'TS2'!$F$56:$BM$56)),)) -> 0 | L17: =IF(L8=0,,IF(L8>0,IF(K17=0,'DB2'!$R$8*(1+'DB2'!$O$8),K17+'DB2'!$R$8*(100%-(1+'DB2'!$O$8))/SUMPRODUCT('TS2'!$F$43:$BM$43,'TS2'!$F$56:$BM$56)),)) -> 0 | M17: =IF(M8=0,,IF(M8>0,IF(L17=0,'DB2'!$R$8*(1+'DB2'!$O$8),L17+'DB2'!$R$8*(100%-(1+'DB2'!$O$8))/SUMPRODUCT('TS2'!$F$43:$BM$43,'TS2'!$F$56:$BM$56)),)) -> 0 | N17: =IF(N8>0,'TS2'!N42,0) -> 0 | O17: =IF(O8>0,'TS2'!O42,0) -> 0 | P17: =IF(P8>0,'TS2'!P42,0) -> 0 | Q17: =IF(Q8>0,'TS2'!Q42,0) -> 0 | R17: =IF(R8>0,'TS2'!R42,0) -> 0 | S17: =IF(S8>0,'TS2'!S42,0) -> 0 | T17: =IF(T8>0,'TS2'!T42,0) -> 0 | U17: =IF(U8>0,'TS2'!U42,0) -> 0 | ... BM17: =IF(BM8>0,'TS2'!BM42,0) -> 0
B18: =B9 -> АПАРТАМЕНТЫ | D18: тыс. руб. | E18: =IFERROR(E27/E9*1000,0) -> 0 | F18: =IF(F9=0,,IF(F9>0,IF(E18=0,'DB2'!$R$9*(1+'DB2'!$O$9),E18+'DB2'!$R$9*(100%-(1+'DB2'!$O$9))/SUMPRODUCT('TS2'!$F$45:$BM$45,'TS2'!$F$57:$BM$57)),)) -> 0 | G18: =IF(G9=0,,IF(G9>0,IF(F18=0,'DB2'!$R$9*(1+'DB2'!$O$9),F18+'DB2'!$R$9*(100%-(1+'DB2'!$O$9))/SUMPRODUCT('TS2'!$F$45:$BM$45,'TS2'!$F$57:$BM$57)),)) -> 0 | H18: =IF(H9=0,,IF(H9>0,IF(G18=0,'DB2'!$R$9*(1+'DB2'!$O$9),G18+'DB2'!$R$9*(100%-(1+'DB2'!$O$9))/SUMPRODUCT('TS2'!$F$45:$BM$45,'TS2'!$F$57:$BM$57)),)) -> 0 | I18: =IF(I9=0,,IF(I9>0,IF(H18=0,'DB2'!$R$9*(1+'DB2'!$O$9),H18+'DB2'!$R$9*(100%-(1+'DB2'!$O$9))/SUMPRODUCT('TS2'!$F$45:$BM$45,'TS2'!$F$57:$BM$57)),)) -> 0 | J18: =IF(J9=0,,IF(J9>0,IF(I18=0,'DB2'!$R$9*(1+'DB2'!$O$9),I18+'DB2'!$R$9*(100%-(1+'DB2'!$O$9))/SUMPRODUCT('TS2'!$F$45:$BM$45,'TS2'!$F$57:$BM$57)),)) -> 0 | K18: =IF(K9=0,,IF(K9>0,IF(J18=0,'DB2'!$R$9*(1+'DB2'!$O$9),J18+'DB2'!$R$9*(100%-(1+'DB2'!$O$9))/SUMPRODUCT('TS2'!$F$45:$BM$45,'TS2'!$F$57:$BM$57)),)) -> 0 | L18: =IF(L9=0,,IF(L9>0,IF(K18=0,'DB2'!$R$9*(1+'DB2'!$O$9),K18+'DB2'!$R$9*(100%-(1+'DB2'!$O$9))/SUMPRODUCT('TS2'!$F$45:$BM$45,'TS2'!$F$57:$BM$57)),)) -> 0 | M18: =IF(M9=0,,IF(M9>0,IF(L18=0,'DB2'!$R$9*(1+'DB2'!$O$9),L18+'DB2'!$R$9*(100%-(1+'DB2'!$O$9))/SUMPRODUCT('TS2'!$F$45:$BM$45,'TS2'!$F$57:$BM$57)),)) -> 0 | ... BM18: =IF(BM9=0,,IF(BM9>0,IF(BL18=0,'DB2'!$R$9*(1+'DB2'!$O$9),BL18+'DB2'!$R$9*(100%-(1+'DB2'!$O$9))/SUMPRODUCT('TS2'!$F$45:$BM$45,'TS2'!$F$57:$BM$57)),)) -> 0
B19: =B10 -> ОФИСЫ | D19: тыс. руб. | E19: =IFERROR(E28/E10*1000,0) -> 0 | F19: =IF(F10=0,,IF(F10>0,IF(E19=0,'DB2'!$R$10*(1+'DB2'!$O$10),E19+'DB2'!$R$10*(100%-(1+'DB2'!$O$10))/SUMPRODUCT('TS2'!$F$47:$BM$47,'TS2'!$F$58:$BM$58)),)) -> 0 | G19: =IF(G10=0,,IF(G10>0,IF(F19=0,'DB2'!$R$10*(1+'DB2'!$O$10),F19+'DB2'!$R$10*(100%-(1+'DB2'!$O$10))/SUMPRODUCT('TS2'!$F$47:$BM$47,'TS2'!$F$58:$BM$58)),)) -> 0 | H19: =IF(H10=0,,IF(H10>0,IF(G19=0,'DB2'!$R$10*(1+'DB2'!$O$10),G19+'DB2'!$R$10*(100%-(1+'DB2'!$O$10))/SUMPRODUCT('TS2'!$F$47:$BM$47,'TS2'!$F$58:$BM$58)),)) -> 0 | I19: =IF(I10=0,,IF(I10>0,IF(H19=0,'DB2'!$R$10*(1+'DB2'!$O$10),H19+'DB2'!$R$10*(100%-(1+'DB2'!$O$10))/SUMPRODUCT('TS2'!$F$47:$BM$47,'TS2'!$F$58:$BM$58)),)) -> 0 | J19: =IF(J10=0,,IF(J10>0,IF(I19=0,'DB2'!$R$10*(1+'DB2'!$O$10),I19+'DB2'!$R$10*(100%-(1+'DB2'!$O$10))/SUMPRODUCT('TS2'!$F$47:$BM$47,'TS2'!$F$58:$BM$58)),)) -> 0 | K19: =IF(K10=0,,IF(K10>0,IF(J19=0,'DB2'!$R$10*(1+'DB2'!$O$10),J19+'DB2'!$R$10*(100%-(1+'DB2'!$O$10))/SUMPRODUCT('TS2'!$F$47:$BM$47,'TS2'!$F$58:$BM$58)),)) -> 0 | L19: =IF(L10=0,,IF(L10>0,IF(K19=0,'DB2'!$R$10*(1+'DB2'!$O$10),K19+'DB2'!$R$10*(100%-(1+'DB2'!$O$10))/SUMPRODUCT('TS2'!$F$47:$BM$47,'TS2'!$F$58:$BM$58)),)) -> 0 | M19: =IF(M10=0,,IF(M10>0,IF(L19=0,'DB2'!$R$10*(1+'DB2'!$O$10),L19+'DB2'!$R$10*(100%-(1+'DB2'!$O$10))/SUMPRODUCT('TS2'!$F$47:$BM$47,'TS2'!$F$58:$BM$58)),)) -> 0 | ... BM19: =IF(BM10=0,,IF(BM10>0,IF(BL19=0,'DB2'!$R$10*(1+'DB2'!$O$10),BL19+'DB2'!$R$10*(100%-(1+'DB2'!$O$10))/SUMPRODUCT('TS2'!$F$47:$BM$47,'TS2'!$F$58:$BM$58)),)) -> 0
B20: =B11 -> РИТЕЙЛ | D20: тыс. руб. | E20: =IFERROR(E29/E11*1000,0) -> 700 | F20: =IF(F11>0,'DB2'!$R$11,0) -> 0 | G20: =IF(G11>0,'DB2'!$R$11,0) -> 0 | H20: =IF(H11>0,'DB2'!$R$11,0) -> 0 | I20: =IF(I11>0,'DB2'!$R$11,0) -> 0 | J20: =IF(J11>0,'DB2'!$R$11,0) -> 0 | K20: =IF(K11>0,'DB2'!$R$11,0) -> 0 | L20: =IF(L11>0,'DB2'!$R$11,0) -> 0 | M20: =IF(M11>0,'DB2'!$R$11,0) -> 0 | ... BM20: =IF(BM11>0,'DB2'!$R$11,0) -> 0
B21: =B12 -> ТЦ | D21: тыс. руб. | E21: =IFERROR(E30/E12*1000,0) -> 0 | F21: =IF(F12>0,'DB2'!$R$12,0) -> 0 | G21: =IF(G12>0,'DB2'!$R$12,0) -> 0 | H21: =IF(H12>0,'DB2'!$R$12,0) -> 0 | I21: =IF(I12>0,'DB2'!$R$12,0) -> 0 | J21: =IF(J12>0,'DB2'!$R$12,0) -> 0 | K21: =IF(K12>0,'DB2'!$R$12,0) -> 0 | L21: =IF(L12>0,'DB2'!$R$12,0) -> 0 | M21: =IF(M12>0,'DB2'!$R$12,0) -> 0 | ... BM21: =IF(BM12>0,'DB2'!$R$12,0) -> 0
B22: =B13 -> ПАРКИНГ ЖИЛЬЕ | D22: тыс. руб. | E22: =IFERROR(E31/E13*1000,0) -> 4500 | F22: =IF(F13=0,,IF(F13>0,IF(E22=0,'DB2'!$R$16*(1+'DB2'!$O$16),E22+'DB2'!$R$16*(100%-(1+'DB2'!$O$16))/SUMPRODUCT('TS2'!$F$53:$BM$53,'TS2'!$F$56:$BM$56)),)) -> 0 | G22: =IF(G13=0,,IF(G13>0,IF(F22=0,'DB2'!$R$16*(1+'DB2'!$O$16),F22+'DB2'!$R$16*(100%-(1+'DB2'!$O$16))/SUMPRODUCT('TS2'!$F$53:$BM$53,'TS2'!$F$56:$BM$56)),)) -> 0 | H22: =IF(H13=0,,IF(H13>0,IF(G22=0,'DB2'!$R$16*(1+'DB2'!$O$16),G22+'DB2'!$R$16*(100%-(1+'DB2'!$O$16))/SUMPRODUCT('TS2'!$F$53:$BM$53,'TS2'!$F$56:$BM$56)),)) -> 0 | I22: =IF(I13=0,,IF(I13>0,IF(H22=0,'DB2'!$R$16*(1+'DB2'!$O$16),H22+'DB2'!$R$16*(100%-(1+'DB2'!$O$16))/SUMPRODUCT('TS2'!$F$53:$BM$53,'TS2'!$F$56:$BM$56)),)) -> 0 | J22: =IF(J13=0,,IF(J13>0,IF(I22=0,'DB2'!$R$16*(1+'DB2'!$O$16),I22+'DB2'!$R$16*(100%-(1+'DB2'!$O$16))/SUMPRODUCT('TS2'!$F$53:$BM$53,'TS2'!$F$56:$BM$56)),)) -> 0 | K22: =IF(K13=0,,IF(K13>0,IF(J22=0,'DB2'!$R$16*(1+'DB2'!$O$16),J22+'DB2'!$R$16*(100%-(1+'DB2'!$O$16))/SUMPRODUCT('TS2'!$F$53:$BM$53,'TS2'!$F$56:$BM$56)),)) -> 0 | L22: =IF(L13=0,,IF(L13>0,IF(K22=0,'DB2'!$R$16*(1+'DB2'!$O$16),K22+'DB2'!$R$16*(100%-(1+'DB2'!$O$16))/SUMPRODUCT('TS2'!$F$53:$BM$53,'TS2'!$F$56:$BM$56)),)) -> 0 | M22: =IF(M13=0,,IF(M13>0,IF(L22=0,'DB2'!$R$16*(1+'DB2'!$O$16),L22+'DB2'!$R$16*(100%-(1+'DB2'!$O$16))/SUMPRODUCT('TS2'!$F$53:$BM$53,'TS2'!$F$56:$BM$56)),)) -> 0 | ... BM22: =IF(BM13=0,,IF(BM13>0,IF(BL22=0,'DB2'!$R$16*(1+'DB2'!$O$16),BL22+'DB2'!$R$16*(100%-(1+'DB2'!$O$16))/SUMPRODUCT('TS2'!$F$53:$BM$53,'TS2'!$F$56:$BM$56)),)) -> 0
B23: =B14 -> ПАРКИНГ ОФИС | D23: тыс. руб. | E23: =IFERROR(E32/E14*1000,0) -> 0 | F23: =IF(F14=0,,IF(F14>0,IF(E23=0,'DB2'!$R$17*(1+'DB2'!$O$17),E23+'DB2'!$R$17*(100%-(1+'DB2'!$O$17))/SUMPRODUCT('TS2'!$F$55:$BM$55,'TS2'!$F$58:$BM$58)),)) -> 0 | G23: =IF(G14=0,,IF(G14>0,IF(F23=0,'DB2'!$R$17*(1+'DB2'!$O$17),F23+'DB2'!$R$17*(100%-(1+'DB2'!$O$17))/SUMPRODUCT('TS2'!$F$55:$BM$55,'TS2'!$F$58:$BM$58)),)) -> 0 | H23: =IF(H14=0,,IF(H14>0,IF(G23=0,'DB2'!$R$17*(1+'DB2'!$O$17),G23+'DB2'!$R$17*(100%-(1+'DB2'!$O$17))/SUMPRODUCT('TS2'!$F$55:$BM$55,'TS2'!$F$58:$BM$58)),)) -> 0 | I23: =IF(I14=0,,IF(I14>0,IF(H23=0,'DB2'!$R$17*(1+'DB2'!$O$17),H23+'DB2'!$R$17*(100%-(1+'DB2'!$O$17))/SUMPRODUCT('TS2'!$F$55:$BM$55,'TS2'!$F$58:$BM$58)),)) -> 0 | J23: =IF(J14=0,,IF(J14>0,IF(I23=0,'DB2'!$R$17*(1+'DB2'!$O$17),I23+'DB2'!$R$17*(100%-(1+'DB2'!$O$17))/SUMPRODUCT('TS2'!$F$55:$BM$55,'TS2'!$F$58:$BM$58)),)) -> 0 | K23: =IF(K14=0,,IF(K14>0,IF(J23=0,'DB2'!$R$17*(1+'DB2'!$O$17),J23+'DB2'!$R$17*(100%-(1+'DB2'!$O$17))/SUMPRODUCT('TS2'!$F$55:$BM$55,'TS2'!$F$58:$BM$58)),)) -> 0 | L23: =IF(L14=0,,IF(L14>0,IF(K23=0,'DB2'!$R$17*(1+'DB2'!$O$17),K23+'DB2'!$R$17*(100%-(1+'DB2'!$O$17))/SUMPRODUCT('TS2'!$F$55:$BM$55,'TS2'!$F$58:$BM$58)),)) -> 0 | M23: =IF(M14=0,,IF(M14>0,IF(L23=0,'DB2'!$R$17*(1+'DB2'!$O$17),L23+'DB2'!$R$17*(100%-(1+'DB2'!$O$17))/SUMPRODUCT('TS2'!$F$55:$BM$55,'TS2'!$F$58:$BM$58)),)) -> 0 | ... BM23: =IF(BM14=0,,IF(BM14>0,IF(BL23=0,'DB2'!$R$17*(1+'DB2'!$O$17),BL23+'DB2'!$R$17*(100%-(1+'DB2'!$O$17))/SUMPRODUCT('TS2'!$F$55:$BM$55,'TS2'!$F$58:$BM$58)),)) -> 0
B25: КОНТРАКТАЦИЯ | D25: млн. руб. | E25: =SUM(F25:BM25) -> 36150.467 | F25: =SUM(F26:F32) -> 0 | G25: =SUM(G26:G32) -> 0 | H25: =SUM(H26:H32) -> 0 | I25: =SUM(I26:I32) -> 0 | J25: =SUM(J26:J32) -> 0 | K25: =SUM(K26:K32) -> 0 | L25: =SUM(L26:L32) -> 0 | M25: =SUM(M26:M32) -> 0 | ... BM25: =SUM(BM26:BM32) -> 0
B26: =B17 -> КВАРТИРЫ | D26: млн. руб. | E26: =SUM(F26:BM26) -> 32052.726 | F26: =F8*F17/10^3 -> 0 | G26: =G8*G17/10^3 -> 0 | H26: =H8*H17/10^3 -> 0 | I26: =I8*I17/10^3 -> 0 | J26: =J8*J17/10^3 -> 0 | K26: =K8*K17/10^3 -> 0 | L26: =L8*L17/10^3 -> 0 | M26: =M8*M17/10^3 -> 0 | ... BM26: =BM8*BM17/10^3 -> 0
B27: =B18 -> АПАРТАМЕНТЫ | D27: млн. руб. | E27: =SUM(F27:BM27) -> 0 | F27: =F9*F18/10^3 -> 0 | G27: =G9*G18/10^3 -> 0 | H27: =H9*H18/10^3 -> 0 | I27: =I9*I18/10^3 -> 0 | J27: =J9*J18/10^3 -> 0 | K27: =K9*K18/10^3 -> 0 | L27: =L9*L18/10^3 -> 0 | M27: =M9*M18/10^3 -> 0 | ... BM27: =BM9*BM18/10^3 -> 0
B28: =B19 -> ОФИСЫ | D28: млн. руб. | E28: =SUM(F28:BM28) -> 0 | F28: =F10*F19/10^3 -> 0 | G28: =G10*G19/10^3 -> 0 | H28: =H10*H19/10^3 -> 0 | I28: =I10*I19/10^3 -> 0 | J28: =J10*J19/10^3 -> 0 | K28: =K10*K19/10^3 -> 0 | L28: =L10*L19/10^3 -> 0 | M28: =M10*M19/10^3 -> 0 | ... BM28: =BM10*BM19/10^3 -> 0
B29: =B20 -> РИТЕЙЛ | D29: млн. руб. | E29: =SUM(F29:BM29) -> 1789.2409 | F29: =F11*F20/10^3 -> 0 | G29: =G11*G20/10^3 -> 0 | H29: =H11*H20/10^3 -> 0 | I29: =I11*I20/10^3 -> 0 | J29: =J11*J20/10^3 -> 0 | K29: =K11*K20/10^3 -> 0 | L29: =L11*L20/10^3 -> 0 | M29: =M11*M20/10^3 -> 0 | ... BM29: =BM11*BM20/10^3 -> 0
B30: =B21 -> ТЦ | D30: млн. руб. | E30: =SUM(F30:BM30) -> 0 | F30: =F12*F21/10^3 -> 0 | G30: =G12*G21/10^3 -> 0 | H30: =H12*H21/10^3 -> 0 | I30: =I12*I21/10^3 -> 0 | J30: =J12*J21/10^3 -> 0 | K30: =K12*K21/10^3 -> 0 | L30: =L12*L21/10^3 -> 0 | M30: =M12*M21/10^3 -> 0 | ... BM30: =BM12*BM21/10^3 -> 0
B31: =B22 -> ПАРКИНГ ЖИЛЬЕ | D31: млн. руб. | E31: =SUM(F31:BM31) -> 2308.5 | F31: =F13*F22/10^3 -> 0 | G31: =G13*G22/10^3 -> 0 | H31: =H13*H22/10^3 -> 0 | I31: =I13*I22/10^3 -> 0 | J31: =J13*J22/10^3 -> 0 | K31: =K13*K22/10^3 -> 0 | L31: =L13*L22/10^3 -> 0 | M31: =M13*M22/10^3 -> 0 | ... BM31: =BM13*BM22/10^3 -> 0
B32: =B23 -> ПАРКИНГ ОФИС | D32: млн. руб. | E32: =SUM(F32:BM32) -> 0 | F32: =F14*F23/10^3 -> 0 | G32: =G14*G23/10^3 -> 0 | H32: =H14*H23/10^3 -> 0 | I32: =I14*I23/10^3 -> 0 | J32: =J14*J23/10^3 -> 0 | K32: =K14*K23/10^3 -> 0 | L32: =L14*L23/10^3 -> 0 | M32: =M14*M23/10^3 -> 0 | ... BM32: =BM14*BM23/10^3 -> 0
B34: ПОСТУПЛЕНИЯ (до РнВ на эскроу) | D34: млн. руб. | E34: =SUM(F34:BM34) -> 36150.467 | F34: =IF(SUM($E$175:E175)>0,SUM($F$35:F47)-SUM(E$34:$F34),0) -> 0 | G34: =IF(SUM($E$175:F175)>0,SUM($F$35:G47)-SUM(F$34:$F34),0) -> 0 | H34: =IF(SUM($E$175:G175)>0,SUM($F$35:H47)-SUM($F$34:G34),0) -> 0 | I34: =IF(SUM($E$175:H175)>0,SUM($F$35:I47)-SUM($F$34:H34),0) -> 0 | J34: =IF(SUM($E$175:I175)>0,SUM($F$35:J47)-SUM($F$34:I34),0) -> 0 | K34: =IF(SUM($E$175:J175)>0,SUM($F$35:K47)-SUM($F$34:J34),0) -> 0 | L34: =IF(SUM($E$175:K175)>0,SUM($F$35:L47)-SUM($F$34:K34),0) -> 0 | M34: =IF(SUM($E$175:L175)>0,SUM($F$35:M47)-SUM($F$34:L34),0) -> 0 | N34: =IF(SUM($E$175:M175)>0,SUM($F$35:N35,$F$42:N42,$F$43:N43,$F$44:N44,$F$45:N45,$F$46:N46,)-SUM($F$34:M34),0) -> 0 | O34: =IF(SUM($E$175:N175)>0,SUM($F$35:O35,$F$42:O42,$F$43:O43,$F$44:O44,$F$45:O45,$F$46:O46,)-SUM($F$34:N34),0) -> 0 | P34: =IF(SUM($E$175:O175)>0,SUM($F$35:P35,$F$42:P42,$F$43:P43,$F$44:P44,$F$45:P45,$F$46:P46,)-SUM($F$34:O34),0) -> 0 | Q34: =IF(SUM($E$175:P175)>0,SUM($F$35:Q35,$F$42:Q42,$F$43:Q43,$F$44:Q44,$F$45:Q45,$F$46:Q46,)-SUM($F$34:P34),0) -> 0 | R34: =IF(SUM($E$175:Q175)>0,SUM($F$35:R35,$F$42:R42,$F$43:R43,$F$44:R44,$F$45:R45,$F$46:R46,)-SUM($F$34:Q34),0) -> 0 | S34: =IF(SUM($E$175:R175)>0,SUM($F$35:S35,$F$42:S42,$F$43:S43,$F$44:S44,$F$45:S45,$F$46:S46,)-SUM($F$34:R34),0) -> 0 | T34: =IF(SUM($E$175:S175)>0,SUM($F$35:T35,$F$42:T42,$F$43:T43,$F$44:T44,$F$45:T45,$F$46:T46,)-SUM($F$34:S34),0) -> 0 | U34: =IF(SUM($E$175:T175)>0,SUM($F$35:U35,$F$42:U42,$F$43:U43,$F$44:U44,$F$45:U45,$F$46:U46,)-SUM($F$34:T34),0) -> 0 | ... BM34: =IF(SUM($E$175:BL175)>0,SUM($F$35:BM35,$F$42:BM42,$F$43:BM43,$F$44:BM44,$F$45:BM45,$F$46:BM46,)-SUM($F$34:BL34),0) -> 0
B35: =B26 -> КВАРТИРЫ | D35: млн. руб. | E35: =SUM(F35:BM35) -> 32052.726 | F35: =DETAILS!K16/1000000 -> 0 | G35: =DETAILS!L16/1000000 -> 0 | H35: =DETAILS!M16/1000000 -> 0 | I35: =DETAILS!N16/1000000 -> 0 | J35: =DETAILS!O16/1000000 -> 0 | K35: =DETAILS!P16/1000000 -> 0 | L35: =DETAILS!Q16/1000000 -> 0 | M35: =DETAILS!R16/1000000 -> 0 | N35: =N39+N41+N26*(1-N36) -> 0 | O35: =O39+O41+O26*(1-O36) -> 0 | P35: =P39+P41+P26*(1-P36) -> 0 | Q35: =Q39+Q41+Q26*(1-Q36) -> 0 | R35: =R39+R41+R26*(1-R36) -> 0 | S35: =S39+S41+S26*(1-S36) -> 0 | T35: =T39+T41+T26*(1-T36) -> 0 | U35: =U39+U41+U26*(1-U36) -> 0 | ... BM35: =BM39+BM41+BM26*(1-BM36) -> 0
C36: доля рассрочки | D36: % | F36: ='CF1'!F36 -> 0 | G36: ='CF1'!G36 -> 0 | H36: ='CF1'!H36 -> 0 | I36: ='CF1'!I36 -> 0 | J36: ='CF1'!J36 -> 0 | K36: ='CF1'!K36 -> 0 | L36: ='CF1'!L36 -> 0 | M36: ='CF1'!M36 -> 0 | ... BM36: ='CF1'!BM36 -> 0
C37: рассрочка | D37: млн. руб. | N37: =N26*N36*N174 -> 0 | O37: =O26*O36*O174 -> 0 | P37: =P26*P36*P174 -> 0 | Q37: =Q26*Q36*Q174 -> 0 | R37: =R26*R36*R174 -> 0 | S37: =S26*S36*S174 -> 0 | T37: =T26*T36*T174 -> 0 | U37: =U26*U36*U174 -> 0 | ... BM37: =BM26*BM36*BM174 -> 0
C38: ПВ | D38: % | N38: ='CF1'!N38 -> 0 | O38: ='CF1'!O38 -> 0 | P38: ='CF1'!P38 -> 0 | Q38: ='CF1'!Q38 -> 0 | R38: ='CF1'!R38 -> 0 | S38: ='CF1'!S38 -> 0.3 | T38: ='CF1'!T38 -> 0.3 | U38: ='CF1'!U38 -> 0.3 | ... BM38: ='CF1'!BM38 -> 0
C39: ПВ | D39: млн. руб. | N39: =N37*N38 -> 0 | O39: =O37*O38 -> 0 | P39: =P37*P38 -> 0 | Q39: =Q37*Q38 -> 0 | R39: =R37*R38 -> 0 | S39: =S37*S38 -> 0 | T39: =T37*T38 -> 0 | U39: =U37*U38 -> 0 | ... BM39: =BM37*BM38 -> 0
C40: остаток | D40: млн. руб. | N40: =N37-N39 -> 0 | O40: =O37-O39 -> 0 | P40: =P37-P39 -> 0 | Q40: =Q37-Q39 -> 0 | R40: =R37-R39 -> 0 | S40: =S37-S39 -> 0 | T40: =T37-T39 -> 0 | U40: =U37-U39 -> 0 | ... BM40: =BM37-BM39 -> 0
C41: поступление остатка | D41: млн. руб. | N41: =N40/SUM(N174:$AH$174) -> 0 | O41: =O40/SUM(O174:$AH$174) -> 0 | P41: =P40/SUM(P174:$AH$174) -> 0 | Q41: =Q40/SUM(Q174:$AH$174) -> 0 | R41: =R40/SUM(R174:$AH$174) -> 0 | S41: =S40/SUM(S174:$AH$174) -> 0 | T41: =T40/SUM(T174:$AH$174) -> 0 | U41: =U40/SUM(U174:$AH$174) -> 0 | ... W41: =W40/SUM(W174:$AH$174) -> 0 | X41: =W41+X40/SUM(X174:$AH$174) -> 39.930545 | Y41: =X41+Y40/SUM(Y174:$AH$174) -> 73.718696 | Z41: =Y41+Z40/SUM(Z174:$AH$174) -> 112.20048 | AA41: =Z41+AA40/SUM(AA174:$AH$174) -> 156.54929 | AB41: =AA41+AB40/SUM(AB174:$AH$174) -> 208.44144 | AC41: =AB41+AC40/SUM(AC174:$AH$174) -> 249.74139 | AD41: =AC41+AD40/SUM(AD174:$AH$174) -> 300.42859 | AE41: =AD41+AE40/SUM(AE174:$AH$174) -> 365.19668 | ... AH41: =AG41+AH40/SUM(AH174:$AH$174) -> 453.43292 | AJ41: =AJ40/SUM($AH174:AJ$174) -> 0 | AK41: =AK40/SUM($AH174:AK$174) -> 0 | AL41: =AL40/SUM($AH174:AL$174) -> 0 | AM41: =AM40/SUM($AH174:AM$174) -> 0 | AN41: =AN40/SUM($AH174:AN$174) -> 0 | AO41: =AO40/SUM($AH174:AO$174) -> 0 | AP41: =AP40/SUM($AH174:AP$174) -> 0 | AQ41: =AQ40/SUM($AH174:AQ$174) -> 0 | ... BM41: =BM40/SUM($AH174:BM$174) -> 0
B42: =B27 -> АПАРТАМЕНТЫ | D42: млн. руб. | E42: =SUM(F42:BM42) -> 0 | G42: =G27*'DB2'!$N$9+SUM($F27:F27)-SUM($F42:F42) -> 0 | H42: =H27*'DB2'!$N$9+SUM($F27:G27)-SUM($F42:G42) -> 0 | I42: =I27*'DB2'!$N$9+SUM($F27:H27)-SUM($F42:H42) -> 0 | J42: =J27*'DB2'!$N$9+SUM($F27:I27)-SUM($F42:I42) -> 0 | K42: =K27*'DB2'!$N$9+SUM($F27:J27)-SUM($F42:J42) -> 0 | L42: =L27*'DB2'!$N$9+SUM($F27:K27)-SUM($F42:K42) -> 0 | M42: =M27*'DB2'!$N$9+SUM($F27:L27)-SUM($F42:L42) -> 0 | N42: =N27*'DB2'!$N$9+SUM($F27:M27)-SUM($F42:M42) -> 0 | ... BM42: =BM27*'DB2'!$N$9+SUM($F27:BL27)-SUM($F42:BL42) -> 0
B43: =B28 -> ОФИСЫ | D43: млн. руб. | E43: =SUM(F43:BM43) -> 0 | G43: =G28*'DB2'!$N$10+SUM($F28:F28)-SUM($F43:F43) -> 0 | H43: =H28*'DB2'!$N$10+SUM($F28:G28)-SUM($F43:G43) -> 0 | I43: =I28*'DB2'!$N$10+SUM($F28:H28)-SUM($F43:H43) -> 0 | J43: =J28*'DB2'!$N$10+SUM($F28:I28)-SUM($F43:I43) -> 0 | K43: =K28*'DB2'!$N$10+SUM($F28:J28)-SUM($F43:J43) -> 0 | L43: =L28*'DB2'!$N$10+SUM($F28:K28)-SUM($F43:K43) -> 0 | M43: =M28*'DB2'!$N$10+SUM($F28:L28)-SUM($F43:L43) -> 0 | N43: =N28*'DB2'!$N$10+SUM($F28:M28)-SUM($F43:M43) -> 0 | ... BM43: =BM28*'DB2'!$N$10+SUM($F28:BL28)-SUM($F43:BL43) -> 0
B44: =B29 -> РИТЕЙЛ | D44: млн. руб. | E44: =SUM(F44:BM44) -> 1789.2409 | F44: =DETAILS!K17/1000000 -> 0 | G44: =DETAILS!L17/1000000 -> 0 | H44: =DETAILS!M17/1000000 -> 0 | I44: =DETAILS!N17/1000000 -> 0 | J44: =DETAILS!O17/1000000 -> 0 | K44: =DETAILS!P17/1000000 -> 0 | L44: =DETAILS!Q17/1000000 -> 0 | M44: =DETAILS!R17/1000000 -> 0 | ... BM44: =DETAILS!BR17/1000000 -> 0
B45: =B30 -> ТЦ | D45: млн. руб. | E45: =SUM(F45:BM45) -> 0 | G45: =G30*'DB2'!$N$12+SUM($F30:F30)-SUM($F45:F45) -> 0 | H45: =H30*'DB2'!$N$12+SUM($F30:G30)-SUM($F45:G45) -> 0 | I45: =I30*'DB2'!$N$12+SUM($F30:H30)-SUM($F45:H45) -> 0 | J45: =J30*'DB2'!$N$12+SUM($F30:I30)-SUM($F45:I45) -> 0 | K45: =K30*'DB2'!$N$12+SUM($F30:J30)-SUM($F45:J45) -> 0 | L45: =L30*'DB2'!$N$12+SUM($F30:K30)-SUM($F45:K45) -> 0 | M45: =M30*'DB2'!$N$12+SUM($F30:L30)-SUM($F45:L45) -> 0 | N45: =N30*'DB2'!$N$12+SUM($F30:M30)-SUM($F45:M45) -> 0 | ... BM45: =BM30*'DB2'!$N$12+SUM($F30:BL30)-SUM($F45:BL45) -> 0
B46: =B31 -> ПАРКИНГ ЖИЛЬЕ | D46: млн. руб. | E46: =SUM(F46:BM46) -> 2308.5 | F46: =DETAILS!K19/1000000 -> 0 | G46: =DETAILS!L19/1000000 -> 0 | H46: =DETAILS!M19/1000000 -> 0 | I46: =DETAILS!N19/1000000 -> 0 | J46: =DETAILS!O19/1000000 -> 0 | K46: =DETAILS!P19/1000000 -> 0 | L46: =DETAILS!Q19/1000000 -> 0 | M46: =DETAILS!R19/1000000 -> 0 | ... BM46: =DETAILS!BR19/1000000 -> 0
B47: =B32 -> ПАРКИНГ ОФИС | D47: млн. руб. | E47: =SUM(F47:BM47) -> 0 | G47: =G32*'DB2'!$N$17+SUM($F32:F32)-SUM($F47:F47) -> 0 | H47: =H32*'DB2'!$N$17+SUM($F32:G32)-SUM($F47:G47) -> 0 | I47: =I32*'DB2'!$N$17+SUM($F32:H32)-SUM($F47:H47) -> 0 | J47: =J32*'DB2'!$N$17+SUM($F32:I32)-SUM($F47:I47) -> 0 | K47: =K32*'DB2'!$N$17+SUM($F32:J32)-SUM($F47:J47) -> 0 | L47: =L32*'DB2'!$N$17+SUM($F32:K32)-SUM($F47:K47) -> 0 | M47: =M32*'DB2'!$N$17+SUM($F32:L32)-SUM($F47:L47) -> 0 | N47: =N32*'DB2'!$N$17+SUM($F32:M32)-SUM($F47:M47) -> 0 | ... BM47: =BM32*'DB2'!$N$17+SUM($F32:BL32)-SUM($F47:BL47) -> 0
B50: РАСХОДЫ | D50: млн. руб. | E50: =SUM(F50:BM50) -> -2760.3491 | F50: =SUM(F53:F56) -> 0 | G50: =SUM(G51:G56) -> 0 | H50: =SUM(H51:H56) -> 0 | I50: =SUM(I51:I56) -> 0 | J50: =SUM(J51:J56) -> 0 | K50: =SUM(K51:K56) -> 0 | L50: =SUM(L51:L56) -> 0 | M50: =SUM(M51:M56) -> 0 | N50: =SUM(N51:N56) -> -3 | ... BM50: =SUM(BM51:BM56) -> 0
B51: БРОКЕРИДЖ | D51: млн. руб. | E51: =SUM(G51:BM51) -> -1084.514 | F51: =DETAILS!K101/1000000 -> 0 | G51: =DETAILS!L101/1000000 -> 0 | H51: =DETAILS!M101/1000000 -> 0 | I51: =DETAILS!N101/1000000 -> 0 | J51: =DETAILS!O101/1000000 -> 0 | K51: =DETAILS!P101/1000000 -> 0 | L51: =DETAILS!Q101/1000000 -> 0 | M51: =DETAILS!R101/1000000 -> 0 | ... BM51: =DETAILS!BR101/1000000 -> 0
B52: УПРАВЛЕНИЕ ПРОДАЖАМИ | D52: млн. руб. | E52: =SUM(G52:BM52) -> -433.8056 | F52: =DETAILS!K102/1000000 -> 0 | G52: =DETAILS!L102/1000000 -> 0 | H52: =DETAILS!M102/1000000 -> 0 | I52: =DETAILS!N102/1000000 -> 0 | J52: =DETAILS!O102/1000000 -> 0 | K52: =DETAILS!P102/1000000 -> 0 | L52: =DETAILS!Q102/1000000 -> 0 | M52: =DETAILS!R102/1000000 -> 0 | ... BM52: =DETAILS!BR102/1000000 -> 0
B53: РЕКЛАМА И МАРКЕТИНГ | D53: млн. руб. | E53: =SUM(F53:BM53) -> -1084.514 | F53: =SUMIFS(DETAILS!K$107:K$122,DETAILS!$C$107:$C$122,'CF2'!$D$2)/1000000 -> 0 | G53: =SUMIFS(DETAILS!L$107:L$122,DETAILS!$C$107:$C$122,'CF2'!$D$2)/1000000 -> 0 | H53: =SUMIFS(DETAILS!M$107:M$122,DETAILS!$C$107:$C$122,'CF2'!$D$2)/1000000 -> 0 | I53: =SUMIFS(DETAILS!N$107:N$122,DETAILS!$C$107:$C$122,'CF2'!$D$2)/1000000 -> 0 | J53: =SUMIFS(DETAILS!O$107:O$122,DETAILS!$C$107:$C$122,'CF2'!$D$2)/1000000 -> 0 | K53: =SUMIFS(DETAILS!P$107:P$122,DETAILS!$C$107:$C$122,'CF2'!$D$2)/1000000 -> 0 | L53: =SUMIFS(DETAILS!Q$107:Q$122,DETAILS!$C$107:$C$122,'CF2'!$D$2)/1000000 -> 0 | M53: =SUMIFS(DETAILS!R$107:R$122,DETAILS!$C$107:$C$122,'CF2'!$D$2)/1000000 -> 0 | ... BM53: =SUMIFS(DETAILS!BR$107:BR$122,DETAILS!$C$107:$C$122,'CF2'!$D$2)/1000000 -> 0
B54: АРЕНДА ЗУ/НАЛОГ ЗУ | D54: млн. руб. | E54: =SUM(F54:BM54) -> -15.184085 | F54: =SUMIFS(DETAILS!K$281:K$286,DETAILS!$C$281:$C$286,'CF2'!$D$2)/10^6-F62 -> 0 | G54: =SUMIFS(DETAILS!L$281:L$286,DETAILS!$C$281:$C$286,'CF2'!$D$2)/10^6-G62 -> 0 | H54: =SUMIFS(DETAILS!M$281:M$286,DETAILS!$C$281:$C$286,'CF2'!$D$2)/10^6-H62 -> 0 | I54: =SUMIFS(DETAILS!N$281:N$286,DETAILS!$C$281:$C$286,'CF2'!$D$2)/10^6-I62 -> 0 | J54: =SUMIFS(DETAILS!O$281:O$286,DETAILS!$C$281:$C$286,'CF2'!$D$2)/10^6-J62 -> 0 | K54: =SUMIFS(DETAILS!P$281:P$286,DETAILS!$C$281:$C$286,'CF2'!$D$2)/10^6-K62 -> 0 | L54: =SUMIFS(DETAILS!Q$281:Q$286,DETAILS!$C$281:$C$286,'CF2'!$D$2)/10^6-L62 -> 0 | M54: =SUMIFS(DETAILS!R$281:R$286,DETAILS!$C$281:$C$286,'CF2'!$D$2)/10^6-M62 -> 0 | ... BM54: =SUMIFS(DETAILS!BR$281:BR$286,DETAILS!$C$281:$C$286,'CF2'!$D$2)/10^6-BM62 -> 0
B55: РЕГИСТРАЦИЯ ДОГОВОРОВ | D55: млн. руб. | E55: =SUM(F55:BM55) -> -61.331381 | F55: =DETAILS!K104/1000000 -> 0 | G55: =DETAILS!L104/1000000 -> 0 | H55: =DETAILS!M104/1000000 -> 0 | I55: =DETAILS!N104/1000000 -> 0 | J55: =DETAILS!O104/1000000 -> 0 | K55: =DETAILS!P104/1000000 -> 0 | L55: =DETAILS!Q104/1000000 -> 0 | M55: =DETAILS!R104/1000000 -> 0 | ... BM55: =DETAILS!BR104/1000000 -> 0
B56: АХР | D56: млн. руб. | E56: =SUM(F56:BM56) -> -81 | F56: =SUMIFS(DETAILS!K$47:K$93,DETAILS!$C$47:$C$93,2)/1000000 -> 0 | G56: =SUMIFS(DETAILS!L$47:L$93,DETAILS!$C$47:$C$93,2)/1000000 -> 0 | H56: =SUMIFS(DETAILS!M$47:M$93,DETAILS!$C$47:$C$93,2)/1000000 -> 0 | I56: =SUMIFS(DETAILS!N$47:N$93,DETAILS!$C$47:$C$93,2)/1000000 -> 0 | J56: =SUMIFS(DETAILS!O$47:O$93,DETAILS!$C$47:$C$93,2)/1000000 -> 0 | K56: =SUMIFS(DETAILS!P$47:P$93,DETAILS!$C$47:$C$93,2)/1000000 -> 0 | L56: =SUMIFS(DETAILS!Q$47:Q$93,DETAILS!$C$47:$C$93,2)/1000000 -> 0 | M56: =SUMIFS(DETAILS!R$47:R$93,DETAILS!$C$47:$C$93,2)/1000000 -> 0 | ... BM56: =SUMIFS(DETAILS!BR$47:BR$93,DETAILS!$C$47:$C$93,2)/1000000 -> 0
B59: ИНВЕСТИЦИИ | D59: млн. руб. | E59: =SUM(F59:BM59) -> -22598.42 | F59: =SUM(F60:F74) -> 0 | G59: =SUM(G60:G74) -> 0 | H59: =SUM(H60:H74) -> 0 | I59: =SUM(I60:I74) -> 0 | J59: =SUM(J60:J74) -> 0 | K59: =SUM(K60:K74) -> 0 | L59: =SUM(L60:L74) -> 0 | M59: =SUM(M60:M74) -> 0 | ... BM59: =SUM(BM60:BM74) -> 0
B60: ВХОД | D60: млн. руб. | E60: =SUM(F60:BM60) -> -526.5 | F60: =SUMIFS(DETAILS!K$138:K$146,DETAILS!$C$138:$C$146,'CF2'!$D$2)/10^6 -> 0 | G60: =SUMIFS(DETAILS!L$138:L$146,DETAILS!$C$138:$C$146,'CF2'!$D$2)/10^6 -> 0 | H60: =SUMIFS(DETAILS!M$138:M$146,DETAILS!$C$138:$C$146,'CF2'!$D$2)/10^6 -> 0 | I60: =SUMIFS(DETAILS!N$138:N$146,DETAILS!$C$138:$C$146,'CF2'!$D$2)/10^6 -> 0 | J60: =SUMIFS(DETAILS!O$138:O$146,DETAILS!$C$138:$C$146,'CF2'!$D$2)/10^6 -> 0 | K60: =SUMIFS(DETAILS!P$138:P$146,DETAILS!$C$138:$C$146,'CF2'!$D$2)/10^6 -> 0 | L60: =SUMIFS(DETAILS!Q$138:Q$146,DETAILS!$C$138:$C$146,'CF2'!$D$2)/10^6 -> 0 | M60: =SUMIFS(DETAILS!R$138:R$146,DETAILS!$C$138:$C$146,'CF2'!$D$2)/10^6 -> 0 | ... BM60: =SUMIFS(DETAILS!BR$138:BR$146,DETAILS!$C$138:$C$146,'CF2'!$D$2)/10^6 -> 0
B61: ВРИ | D61: млн. руб. | E61: =SUM(F61:BM61) -> -1955.3219 | F61: =(DETAILS!K277+DETAILS!K278+DETAILS!K279)/1000000 -> 0 | G61: =(DETAILS!L277+DETAILS!L278+DETAILS!L279)/1000000 -> 0 | H61: =(DETAILS!M277+DETAILS!M278+DETAILS!M279)/1000000 -> 0 | I61: =(DETAILS!N277+DETAILS!N278+DETAILS!N279)/1000000 -> 0 | J61: =(DETAILS!O277+DETAILS!O278+DETAILS!O279)/1000000 -> 0 | K61: =(DETAILS!P277+DETAILS!P278+DETAILS!P279)/1000000 -> 0 | L61: =(DETAILS!Q277+DETAILS!Q278+DETAILS!Q279)/1000000 -> 0 | M61: =(DETAILS!R277+DETAILS!R278+DETAILS!R279)/1000000 -> 0 | ... BM61: =(DETAILS!BR277+DETAILS!BR278+DETAILS!BR279)/1000000 -> 0
B62: АРЕНДА ЗУ/ПРОЧИЕ РАБОТЫ ПО ЗУ | D62: млн. руб. | E62: =SUM(F62:BM62) -> -114.06467 | F62: =SUMIFS(DETAILS!K$281:K$286,DETAILS!$C$281:$C$286,'CF2'!$D$2)/10^6*F174 -> 0 | G62: =SUMIFS(DETAILS!L$281:L$286,DETAILS!$C$281:$C$286,'CF2'!$D$2)/10^6*G174 -> 0 | H62: =SUMIFS(DETAILS!M$281:M$286,DETAILS!$C$281:$C$286,'CF2'!$D$2)/10^6*H174 -> 0 | I62: =SUMIFS(DETAILS!N$281:N$286,DETAILS!$C$281:$C$286,'CF2'!$D$2)/10^6*I174 -> 0 | J62: =SUMIFS(DETAILS!O$281:O$286,DETAILS!$C$281:$C$286,'CF2'!$D$2)/10^6*J174 -> 0 | K62: =SUMIFS(DETAILS!P$281:P$286,DETAILS!$C$281:$C$286,'CF2'!$D$2)/10^6*K174 -> 0 | L62: =SUMIFS(DETAILS!Q$281:Q$286,DETAILS!$C$281:$C$286,'CF2'!$D$2)/10^6*L174 -> 0 | M62: =SUMIFS(DETAILS!R$281:R$286,DETAILS!$C$281:$C$286,'CF2'!$D$2)/10^6*M174 -> 0 | ... BM62: =SUMIFS(DETAILS!BR$281:BR$286,DETAILS!$C$281:$C$286,'CF2'!$D$2)/10^6*BM174 -> 0
B63: ='DB2'!B31 -> ПРОЕКТИРОВАНИЕ (П+РД) | D63: млн. руб. | E63: =SUM(F63:BM63) -> -627.96497 | F63: =SUMIFS(DETAILS!K$148:K$222,DETAILS!$C$148:$C$222,'CF2'!$D$2)/10^6 -> 0 | G63: =SUMIFS(DETAILS!L$148:L$222,DETAILS!$C$148:$C$222,'CF2'!$D$2)/10^6 -> 0 | H63: =SUMIFS(DETAILS!M$148:M$222,DETAILS!$C$148:$C$222,'CF2'!$D$2)/10^6 -> 0 | I63: =SUMIFS(DETAILS!N$148:N$222,DETAILS!$C$148:$C$222,'CF2'!$D$2)/10^6 -> 0 | J63: =SUMIFS(DETAILS!O$148:O$222,DETAILS!$C$148:$C$222,'CF2'!$D$2)/10^6 -> 0 | K63: =SUMIFS(DETAILS!P$148:P$222,DETAILS!$C$148:$C$222,'CF2'!$D$2)/10^6 -> 0 | L63: =SUMIFS(DETAILS!Q$148:Q$222,DETAILS!$C$148:$C$222,'CF2'!$D$2)/10^6 -> 0 | M63: =SUMIFS(DETAILS!R$148:R$222,DETAILS!$C$148:$C$222,'CF2'!$D$2)/10^6 -> 0 | ... BM63: =SUMIFS(DETAILS!BR$148:BR$222,DETAILS!$C$148:$C$222,'CF2'!$D$2)/10^6 -> 0
B64: ='DB2'!B32 -> СОГЛАСОВАНИЯ | D64: млн. руб. | E64: =SUM(F64:BM64) -> -96.609996 | F64: =SUMIFS(DETAILS!K$224:K$263,DETAILS!$C$224:$C$263,'CF2'!$D$2)/10^6 -> 0 | G64: =SUMIFS(DETAILS!L$224:L$263,DETAILS!$C$224:$C$263,'CF2'!$D$2)/10^6 -> 0 | H64: =SUMIFS(DETAILS!M$224:M$263,DETAILS!$C$224:$C$263,'CF2'!$D$2)/10^6 -> 0 | I64: =SUMIFS(DETAILS!N$224:N$263,DETAILS!$C$224:$C$263,'CF2'!$D$2)/10^6 -> 0 | J64: =SUMIFS(DETAILS!O$224:O$263,DETAILS!$C$224:$C$263,'CF2'!$D$2)/10^6 -> 0 | K64: =SUMIFS(DETAILS!P$224:P$263,DETAILS!$C$224:$C$263,'CF2'!$D$2)/10^6 -> 0 | L64: =SUMIFS(DETAILS!Q$224:Q$263,DETAILS!$C$224:$C$263,'CF2'!$D$2)/10^6 -> 0 | M64: =SUMIFS(DETAILS!R$224:R$263,DETAILS!$C$224:$C$263,'CF2'!$D$2)/10^6 -> 0 | ... BM64: =SUMIFS(DETAILS!BR$224:BR$263,DETAILS!$C$224:$C$263,'CF2'!$D$2)/10^6 -> 0
B65: ='DB2'!B33 -> СМР жилье | D65: млн. руб. | E65: =SUM(F65:BM65) -> -13235.569 | F65: =SUMIFS(DETAILS!K$288:K$317,DETAILS!$C$288:$C$317,'CF2'!$D$2)/10^6 -> 0 | G65: =SUMIFS(DETAILS!L$288:L$317,DETAILS!$C$288:$C$317,'CF2'!$D$2)/10^6 -> 0 | H65: =SUMIFS(DETAILS!M$288:M$317,DETAILS!$C$288:$C$317,'CF2'!$D$2)/10^6 -> 0 | I65: =SUMIFS(DETAILS!N$288:N$317,DETAILS!$C$288:$C$317,'CF2'!$D$2)/10^6 -> 0 | J65: =SUMIFS(DETAILS!O$288:O$317,DETAILS!$C$288:$C$317,'CF2'!$D$2)/10^6 -> 0 | K65: =SUMIFS(DETAILS!P$288:P$317,DETAILS!$C$288:$C$317,'CF2'!$D$2)/10^6 -> 0 | L65: =SUMIFS(DETAILS!Q$288:Q$317,DETAILS!$C$288:$C$317,'CF2'!$D$2)/10^6 -> 0 | M65: =SUMIFS(DETAILS!R$288:R$317,DETAILS!$C$288:$C$317,'CF2'!$D$2)/10^6 -> 0 | ... BM65: =SUMIFS(DETAILS!BR$288:BR$317,DETAILS!$C$288:$C$317,'CF2'!$D$2)/10^6 -> 0
B66: ='DB2'!B34 -> СМР офисы | D66: млн. руб. | E66: =SUM(F66:BM66) -> 0 | F66: ='DB2'!$J$34*-'TS2'!F25 -> 0 | G66: ='DB2'!$J$34*-'TS2'!G25 -> 0 | H66: ='DB2'!$J$34*-'TS2'!H25 -> 0 | I66: ='DB2'!$J$34*-'TS2'!I25 -> 0 | J66: ='DB2'!$J$34*-'TS2'!J25 -> 0 | K66: ='DB2'!$J$34*-'TS2'!K25 -> 0 | L66: ='DB2'!$J$34*-'TS2'!L25 -> 0 | M66: ='DB2'!$J$34*-'TS2'!M25 -> 0 | ... BM66: ='DB2'!$J$34*-'TS2'!BM25 -> 0
B67: ='DB2'!B35 -> СМР ТЦ | D67: млн. руб. | E67: =SUM(F67:BM67) -> 0 | F67: ='DB2'!$J$35*-'TS2'!F25 -> 0 | G67: ='DB2'!$J$35*-'TS2'!G25 -> 0 | H67: ='DB2'!$J$35*-'TS2'!H25 -> 0 | I67: ='DB2'!$J$35*-'TS2'!I25 -> 0 | J67: ='DB2'!$J$35*-'TS2'!J25 -> 0 | K67: ='DB2'!$J$35*-'TS2'!K25 -> 0 | L67: ='DB2'!$J$35*-'TS2'!L25 -> 0 | M67: ='DB2'!$J$35*-'TS2'!M25 -> 0 | ... BM67: ='DB2'!$J$35*-'TS2'!BM25 -> 0
